Workbook

Sheet close
D9: Stock | F9: AUD | G9: AED
E10: Total Stock In Australia Value | F10: 130001.91 | G10: =F10*2.55 -> 331504.87
E11: Total Stock In Dubai Value | F11: =G11/2.55 -> 40064 | G11: 102163.2
E12: Less: GST | F12: -15460 | G12: =F12*2.55 -> -39423
E13: Final Stock Value | G13: =SUM(G10:G12) -> 394245.07
E14: Dubai Local Purchased Stock | G14: 127865 | I14: 372911
D15: Payment
E16: Cash In Hand Dubai | G16: 530815
D18: Receivable | E18: From Waheed Bhai | G18: 67567.84
E19: From Abdul Rehman Bhai | G19: 35995.79
E20: GST Refund Pending | F20: 90397.72 | G20: =F20*2.55 -> 230514.19
E21: Gift Card Balance JB Hifi / Harvey | F21: 3501 | G21: =F21*2.55 -> 8927.55
G22: =SUM(G13:G21) -> 1395930.4
D25: Payables | E25: AMGT Cards $36016.19 USD | G25: =36016.19*3.674 -> 132323.48
E26: AB Card Balance | G26: 12213.3
E27: AR Credit Card | G27: 6118.27
E28: AR Investment | G28: 175000
E29: Abdul Majid Bhai $13754.7 CAD | G29: =13754.7*2.67 -> 36725.049
E30: Jawed Bhai | F30: 84000 | G30: =F30*2.55 -> 214200
G31: =SUM(G25:G30) -> 576580.1
E33: Net Profit | G33: =G22-G31 -> 819350.34
E37: Sell Purchase Profit | G37: 899001
E38: Expenses | G38: -291967
E40: Cash In Hand Dubai | G40: 530815
D42: Receivable | E42: From Waheed Bhai | G42: 65225.34
E43: From Abdul Rehman Bhai | G43: 35995.79
E44: GST Refund Pending | F44: 85522.81 | G44: =F44*2.5 -> 213807.02
E45: Gift Card Balance JB Hifi / Harvey | F45: 3501 | G45: =F45*2.55 -> 8927.55
G46: =SUM(G37:G45) -> 1461804.7
D49: Payables | E49: AMGT Cards $36016.19 USD | G49: 132947
E50: AB Card Balance | G50: 12213.3
E51: AR Credit Card | G51: 6118.27
E52: AR Investment | G52: 175000
E53: Abdul Majid Bhai | G53: 41625.05
E54: Jawed Bhai | F54: 84000 | G54: =F54*2.45 -> 205800
E55: Faisal Bhai | G55: 60000
G56: =SUM(G49:G55) -> 633703.62
E58: Net Profit | G58: =G46-G56 -> 828101.09
E60: AR Profit Add | G60: =G58/2 -> 414050.54
E61: WB Profit Add | G61: =G58/2 -> 414050.54
E64: DEC-2024 CLOSING
E65: Total Stock Value | G65: 974562
E66: Less: Pending Stock | G66: -206740.98
E67: Cash In Hand | G67: 184535
D69: Receivable
E70: AHMED SODANI | G70: 2000
E71: ANAS GOHAR | G71: 450
E72: FAISAL BHAI HOLD STOCK KARACHI | G72: 14158.11
E73: HAMZA CUSTOMER | G73: 9730
E74: POWER PLAY | G74: 12800
E75: SAAD & WAJAHAT | G75: 35982
E76: SIR ASHFAQ AMGT | G76: 3205
E77: GST REFUND AUSTRALIA | F77: 69626.87 | G77: =F77*2.33 -> 162230.61
E78: GST REFUND NEWZEALAND | F78: 79794.11 | G78: =F78*2.19 -> 174749.1
G80: =SUM(G65:G79) -> 1367660.8
D82: Payables
E83: ABDUL MAJID BHAI | G83: 36725
E84: AR STAFF | G84: 525951.87
E85: ASHFAQ SAHAB CARD | G85: 12213.3
E86: FAISAL BHAI | G86: 73928.28
E87: JAWED BHAI AUSTRALIA | F87: 288 | G87: =F87*2.33 -> 671.04
E88: WAHEED BHAI | G88: =453332-206740.98 -> 246591.02
E89: RAAZ | G89: 59949
E90: Shipping Charges | F90: 12868 | G90: =F90*2.33 -> 29982.44
G91: =SUM(G83:G90) -> 986011.95
E93: Net Profit | G93: =G80-G91 -> 381648.89 | H93: 381648

Sheet Cards Payments
D6: Ashfaq Sahab Card
C7: Date | D7: Particular | E7: Dr | F7: Cr | G7: Balance
C9: 45488 | D9: Opening From Zameer Bhai | E9: 32682.5 | G9: =G8+E9-F9 -> 32682.5
C10: 45491 | D10: Purchasing | E10: 9141.22 | G10: =G9+E10-F10 -> 41823.72
C11: 45491 | D11: Purchasing | E11: 10969.47 | G11: =G10+E11-F11 -> 52793.19
C12: 45492 | D12: Purchasing | E12: 2737.9 | G12: =G11+E12-F12 -> 55531.09
C13: 45492 | D13: Purchasing | E13: 7301.07 | G13: =G12+E13-F13 -> 62832.16
C14: 45492 | D14: Cash Deposit by Faisal bhai | F14: 20000 | G14: =G13+E14-F14 -> 42832.16
C15: 45492 | D15: Purchasing | E15: 5475.81 | G15: =G14+E15-F15 -> 48307.97
C16: 45492 | D16: Refund | F16: 5101.73 | G16: =G15+E16-F16 -> 43206.24
C17: 45492 | D17: Purchasing | E17: 10951.6 | G17: =G16+E17-F17 -> 54157.84
C18: 45492 | D18: Purchasing | E18: 3650.54 | G18: =G17+E18-F18 -> 57808.38
C19: 45497 | D19: Purchasing 2142 AUD @2.523 | E19: 5407.27 | G19: =G18+E19-F19 -> 63215.65
C20: 45497 | D20: Purchasing 4284 AUD @2.523 | E20: 10814.54 | G20: =G19+E20-F20 -> 74030.19
C21: 45497 | D21: Purchasing 1428 AUD @2.523 | E21: 3604.85 | G21: =G20+E21-F21 -> 77635.04
C22: 45497 | D22: Purchasing 7140 AUD @2.523 | E22: 18024.23 | G22: =G21+E22-F22 -> 95659.27
C23: 45497 | D23: Purchasing 8568 AUD @2.523 | E23: 21629.08 | G23: =G22+E23-F23 -> 117288.35
C24: 45497 | D24: Purchasing 2856 AUD @2.523 | E24: 7209.7 | G24: =G23+E24-F24 -> 124498.05
C25: 45502 | D25: Harvey | E25: 5348.06 | G25: =G24+E25-F25 -> 129846.11
C26: 45504 | D26: Payment By A/R | F26: 129000 | G26: =G25+E26-F26 -> 846.11
C27: 45516 | D27: Payment By A/R | F27: 54801.43 | G27: =G26+E27-F27 -> -53955.32
C28: 45517 | D28: Refund | F28: 5613.73 | G28: =G27+E28-F28 -> -59569.05
C29: 45517 | D29: Bussings Purchasing | E29: 75260 | G29: =G28+E29-F29 -> 15690.95 | I29: =75260/30000 -> 2.5086667
C30: 45517 | D30: Refund | F30: 5613.73 | G30: =G29+E30-F30 -> 10077.22
C31: 45517 | D31: Refund | F31: 4210.3 | G31: =G30+E31-F31 -> 5866.92
C32: 45517 | D32: Refund | F32: 7017.17 | G32: =G31+E32-F32 -> -1150.25
C33: 45517 | D33: Refund | F33: 11227.46 | G33: =G32+E33-F33 -> -12377.71
C34: 45517 | D34: Refund | F34: 4897.37 | G34: =G33+E34-F34 -> -17275.08
C35: 45517 | D35: Refund | F35: 8401.52 | G35: =G34+E35-F35 -> -25676.6
C36: 45517 | D36: Refund | F36: 4200.76 | G36: =G35+E36-F36 -> -29877.36
C37: 45517 | D37: Refund | F37: 4200.76 | G37: =G36+E37-F37 -> -34078.12
C38: 45517 | D38: Refund | F38: 5601.01 | G38: =G37+E38-F38 -> -39679.13
C39: 45517 | D39: Refund | F39: 5601.01 | G39: =G38+E39-F39 -> -45280.14
C40: 45517 | D40: Refund | F40: 9801.77 | G40: =G39+E40-F40 -> -55081.91
C41: 45517 | D41: Refund | F41: 9801.77 | G41: =G40+E41-F41 -> -64883.68
... C50: 45517 | D50: Refund | F50: 26604.8 | G50: =G49+E50-F50 -> -180569.28
C51: 45523 | D51: Purchasing Bunnings | E51: 35350.33 | G51: =G50+E51-F51 -> -145218.95
C52: 45546 | D52: Harvey Norman Domayne | E52: 2021.67 | G52: =G51+E52-F52 -> -143197.28 | H52: =J52*I52 -> 151083.93 | I52: 2.53 | J52: =1629.99+2397+1000+298+298+298+690+298+598+598+3500+894+3500+894+894+299+299+299+7491+8541+297+8541+5694+594+594+596+596+2384+299+299+598+1529.98+598+297+297+299+299+298+297+297+297 -> 59716.97
C53: 45546 | D53: Harvey Norman Av/it Po | E53: 6065.01 | G53: =G52+E53-F53 -> -137132.27
C54: 45546 | D54: Jb Hi Fi Macquarie $522 | F54: 1229.17 | G54: =G53+E54-F54 -> -138361.44
C55: 45549 | D55: Purchasing Bunnings | E55: 1524.19 | G55: =G54+E55-F55 -> -136837.25
C56: 45548 | D56: JB HiFi | E56: 1761.04 | G56: =G55+E56-F56 -> -135076.21
C57: 45548 | D57: Purchasing Bunnings | E57: 760.56 | G57: =G56+E57-F57 -> -134315.65
C58: 45548 | D58: Purchasing Bunnings | E58: 760.56 | G58: =G57+E58-F58 -> -133555.09
C59: 45548 | D59: Harvey Norman | E59: 2552.23 | G59: =G58+E59-F59 -> -131002.86
C60: 45549 | D60: JB HiFi | E60: 21798.59 | G60: =G59+E60-F60 -> -109204.27
C61: 45549 | D61: JB HiFi | E61: 19118.75 | G61: =G60+E61-F61 -> -90085.52
C62: 45549 | D62: JB HiFi | E62: 763.11 | G62: =G61+E62-F62 -> -89322.41
C63: 45549 | D63: JB HiFi | E63: 763.11 | G63: =G62+E63-F63 -> -88559.3
C64: 45549 | D64: JB HiFi | E64: 763.11 | G64: =G63+E64-F64 -> -87796.19
C65: 45549 | D65: Harvey Norman | E65: 2281.69 | G65: =G64+E65-F65 -> -85514.5
C66: 45549 | D66: Harvey Norman | E66: 2281.69 | G66: =G65+E66-F66 -> -83232.81
... C103: 45562 | D103: Purchasing Bunnings | E103: 778.84 | G103: =G102+E103-F103 -> 12212.34
G104: =G103+E104-F104 -> 12212.34
G105: =G104+E105-F105 -> 12212.34
D106: Noman Bhai Card
C107: Date | D107: Particular | E107: Dr | F107: Cr | G107: Balance
C109: 45540 | D109: Noman Bhai Card $20000 ($13,525.98 USA) | E109: =13525.98*3.674 -> 49694.451 | G109: =G108+E109-F109 -> 49694.451
C110: 45540 | D110: Noman Bhai Card $52800 ($35,708.59 USA) | E110: =35708.59*3.674 -> 131193.36 | G110: =G109+E110-F110 -> 180887.81
C111: 45540 | D111: 26/08 burlington stores $30.29 | E111: =30.29*3.674 -> 111.28546 | G111: =G110+E111-F111 -> 180999.1
C112: 45540 | D112: 26/08 Exonmobil inside $4.32 | E112: =4.32*3.674 -> 15.87168 | G112: =G111+E112-F112 -> 181014.97
C113: 45540 | D113: 27/08 Sun wing Super.mrkt $5.49 | E113: =5.49*3.674 -> 20.17026 | G113: =G112+E113-F113 -> 181035.14
C114: 45540 | D114: 28/08 UA.FH DeerPark $13.08 | E114: =13.08*3.674 -> 48.05592 | G114: =G113+E114-F114 -> 181083.19
C115: 45540 | D115: 28/08 Saks Off Deer Park $39.22 | E115: =39.22*3.674 -> 144.09428 | G115: =G114+E115-F115 -> 181227.29
C116: 45540 | D116: 29/08 TJ Max $108.61 | E116: =108.61*3.674 -> 399.03314 | G116: =G115+E116-F116 -> 181626.32
C117: 45540 | D117: 30/08 Uniqlo USA LLC $20 | E117: =20*3.674 -> 73.48 | G117: =G116+E117-F117 -> 181699.8
C118: 45540 | D118: 31/08 Abdo Halal Grill $21.73 | E118: =21.73*3.674 -> 79.83602 | G118: =G117+E118-F118 -> 181779.64
C119: 45549 | D119: Paid by A/R (to Waseem) $35,708 | F119: 131192.59 | G119: =G118+E119-F119 -> 50587.047
C120: 45553 | D120: Paid by A/R (to Waseem) $13000 | F120: 47762 | G120: =G119+E120-F120 -> 2825.0469
C121: 45576 | D121: Paid by A/R (to Waseem) $768.72 | F121: =768.72*3.675 -> 2825.046 | G121: =G120+E121-F121 -> 0.00094000003
G122: =G121+E122-F122 -> 0.00094000003
G123: =G122+E123-F123 -> 0.00094000003
G124: =G123+E124-F124 -> 0.00094000003
D125: TOTAL | G125: =G124+E125-F125 -> 0.00094000003
D127: Ashfaq Sahab Card
C128: Date | D128: Particular | E128: Dr | F128: Cr | G128: Balance
C130: 45449 | D130: Cash Emirates Card | F130: 30100 | G130: =G129+E130-F130 -> -30100 | J130: 45448 | K130: Paid to Ashafaq Sahab (V3 Purchasing Card Payment) | M130: 31900
C131: 45451 | D131: Cash Emirates Card | F131: 42200 | G131: =G130+E131-F131 -> -72300 | J131: 45451 | K131: Paid to Waseem Bhai For V3 Purchasing Card Deposit | M131: 40400
C132: 45455 | D132: Cash Emirates Card | F132: 60640 | G132: =G131+E132-F132 -> -132940 | J132: 45455 | K132: Deposite Ashafaq Sahab Card Payment (Paid to Waseem Bhai) | M132: 60640
C133: 45458 | D133: Cash Emirates Card | F133: 21320 | G133: =G132+E133-F133 -> -154260 | J133: 45457 | K133: Deposite Ashafaq Sahab Card Payment (Paid to Waseem Bhai) | M133: 21320
C134: 45459 | D134: Cash Emirates Card | F134: 8350 | G134: =G133+E134-F134 -> -162610 | J134: 45462 | K134: Deposite Ashafaq Sahab Card Payment (Paid to Waseem Bhai) | M134: 6000
C135: 45463 | D135: Cash Emirates Card | F135: 6000 | G135: =G134+E135-F135 -> -168610 | J135: 45463 | K135: Deposite Ashafaq Sahab Card Payment (Paid to Waseem Bhai) | M135: 8350
C136: 45470 | D136: Cash Emirates Card | F136: 21000 | G136: =G135+E136-F136 -> -189610 | J136: 45469 | K136: Deposite Ashafaq Sahab Card Payment (Paid to Waseem Bhai) | M136: 21000
C137: 45471 | D137: Cash Emirates Card | F137: 31250 | G137: =G136+E137-F137 -> -220860 | J137: 45471 | K137: Deposite Ashafaq Sahab Card Payment (Paid to Waseem Bhai) | M137: 31250
C138: 45473 | D138: Cash Emirates Card | F138: 10000 | G138: =G137+E138-F138 -> -230860 | J138: 45474 | K138: Deposite Ashafaq Sahab Card Payment (Paid to Waseem Bhai) | M138: 73200
C139: 45474 | D139: Cash Emirates Card | F139: 10000 | G139: =G138+E139-F139 -> -240860 | J139: 45479 | K139: Deposite Ashafaq Sahab Card Payment | M139: 50000
C140: 45474 | D140: Cash Emirates Card | F140: 63000 | G140: =G139+E140-F140 -> -303860 | J140: 45491 | K140: Deposit Ashfaq Sahab Card | M140: 20000
C141: 45474 | D141: Cash Emirates Card | F141: 10200 | G141: =G140+E141-F141 -> -314060 | M141: =SUM(M130:M140) -> 364060
C142: 45480 | D142: Cash Emirates Card | F142: 50000 | G142: =G141+E142-F142 -> -364060
C143: 45492 | D143: Cash Emirates Card | F143: 20000 | G143: =G142+E143-F143 -> -384060
D151: AR ENBD CARD
C152: Date | D152: Particular | E152: Dr | F152: Cr | G152: Balance
G153: 2
C154: 45352 | D154: Payment Deposit | E154: 5000 | G154: =G153+E154-F154 -> 5002
C155: 45354 | D155: Payment Deposit | E155: 3990 | G155: =G154+E155-F155 -> 8992
C156: 45355 | D156: withdrawl (Oasis Tower Baniyas) | F156: 8900 | G156: =G155+E156-F156 -> 92
C157: 45357 | D157: Cash Deposit | E157: 500 | G157: =G156+E157-F157 -> 592
C158: 45369 | D158: Cash Deposit | E158: 11840 | G158: =G157+E158-F158 -> 12432
C159: 45371 | D159: withdrawl (Baniyas) | F159: 12400 | G159: =G158+E159-F159 -> 32
C160: 45389 | D160: Account Credited | E160: 1000 | G160: =G159+E160-F160 -> 1032
...

Sheet Problem
B3: 45542 | C3: Shipping Charges Pending | D3: Whatsapp py msg krdya he list
B5: 45542 | C5: Last purchasing Kissy howi he?? Ref1021 wali
B6: 45546 | C6: Refund Charges pending
C7: jo Pcs Returned howe hein unki GST amount ??
C8: Old 62 pcs Returned Pending
C10: Closing Report GST Amount
G18: Closing 31-AUG-2024
G20: Old Purchasing 62Units | I20: 56619.68
G21: New Purchasing 400 Units | I21: 357286.16
G22: Total Purchasing | I22: =SUM(I20:I21) -> 413905.84
G25: AMGT Receivable | I25: 77862.79
G26: A/R Receivable | I26: 31312
G27: Waheed Bhai Receivable | I27: 161424
G28: GST Receivable | I28: 100802
G30: Total Receivable amount | I30: =SUM(I25:I29) -> 371400.79
G32: Total Value (413905.8+371400.8) | I32: =I22+I30 -> 785306.63
G34: Jawed Bhai Payable $81000 | I34: -204120
G35: AR Investment | I35: -103870
G36: WB Invesment
G37: Credit Card Payable | I37: -57181
B39: Date | C39: Card No | D39: Units | E39: Amount AUD
C40: Invoice No.1
B41: 45457 | C41: 6866 | D41: 3units | E41: 1791 | F41: =1791/3 -> 597
B42: 45457 | C42: 6866 | D42: 3units | E42: 1791 | F42: =1791/3 -> 597
B43: 45459 | C43: 6866 | D43: 4units | E43: 2388 | F43: =2388/4 -> 597
B44: 45457 | C44: 6866 | D44: 4units | E44: 2388 | F44: =2388/4 -> 597
B45: 45457 | C45: 6866 | D45: 2units | E45: 1194 | F45: =1194/2 -> 597
B46: 45448 | C46: 6866 | D46: 4units | E46: 2088 | F46: =2088/4 -> 522
B47: 45458 | C47: 6866 | D47: 19units | E47: 11343 | F47: =11343/19 -> 597
B48: 45458 | C48: 6866 | D48: 6units | E48: 3582 | F48: =3582/6 -> 597
B50: Date | C50: Card No | D50: Units | E50: Amount AUD
C51: Invoice No.2
B52: 45459 | C52: 6866 | D52: 7units | E52: 4179 | F52: =4179/7 -> 597
B53: 45459 | C53: 6866 | D53: 8units | E53: 4776 | F53: =4776/8 -> 597
B54: 45459 | C54: 6866 | D54: 7units | E54: 4179 | F54: =4179/7 -> 597
B55: 45460 | C55: 6866 | D55: 8units | E55: 4776 | F55: =4776/8 -> 597
B56: 45458 | C56: 6866 | D56: 9units | E56: 5373 | F56: =5373/9 -> 597
B57: 45459 | C57: 6866 | D57: 12units | E57: 7164 | F57: =7164/12 -> 597 | J57: 14709.5
B59: Date | C59: Card No | D59: Units | E59: Amount AUD
C60: Invoice No.3
B61: 45460 | C61: 6012 | D61: 4units | E61: 2388 | G61: 5613.73
B62: 45459 | C62: 6012 | D62: 4units | E62: 2388 | G62: 5613.73
B63: 45460 | C63: 6012 | D63: 4units | E63: 2388 | G63: 4210.3
B64: 45459 | C64: 6012 | D64: 5units | E64: 2985 | G64: 7017.17
B65: 45459 | C65: 6012 | D65: 8units | E65: 4776 | G65: 11227.46
B66: 45449 | C66: 6866 | D66: 8units | E66: 4176.24 | G66: =SUM(G61:G65) -> 33682.39 | H66: Actual Re | I66: Rate | J66: Aed
B67: 45460 | C67: 6866 | D67: 16units | E67: 6866 | H67: 86633.45 | I67: 2.5 | J67: =H67*I67 -> 216583.62
B68: 45449 | C68: 6866 | D68: 7units | E68: 3654.21 | H68: 86633.45 | I68: 2.33 | J68: =H68*I68 -> 201855.94
E70: 86633.45 | F70: 2.345 | G70: =E70*F70 -> 203155.44
C72: Card No | D72: AUD | E72: AED
C74: Card No.6866 | D74: =SUM(D83:D103) -> 71708.75 | E74: =SUM(E83:E103) -> 168191.57 | F74: =E74/D74 -> 2.3454818
C76: Card No.6012 | D76: 14925 | E76: 33682.39 | F76: =E76/D76 -> 2.2567765
C78: TOTAL AMOUNT | D78: =SUM(D74:D77) -> 86633.75 | E78: =SUM(E74:E77) -> 201873.96
D80: 2686
B82: Date | C82: Details | D82: AUD | E82: AED
B83: 45520 | C83: *BUNNINGS 582000 GLADESVILLE AUS 1,791.00 AUD (1 AED = AUD 0.42635) | D83: 1791 | E83: 4200.76
B84: 45520 | C84: *BUNNINGS 722000 TAREE AUS 3,582.00 AUD (1 AED = AUD 0.42635) | D84: 3582 | E84: 8401.52
B85: 45520 | C85: *BUNNINGS PYMBLE PYMBLE AUS 4,176.40 AUD (1 AED = AUD 0.42635) | D85: 4176.4 | E85: 9795.67
B86: 45520 | C86: *BUNNINGS 553000 CARLINGFORD AUS 2,388.00 AUD (1 AED = AUD 0.42635) | D86: 2388 | E86: 5601.01
B87: 45520 | C87: *BUNNINGS 757000 CHATSWOOD AUS 1,194.00 AUD (1 AED = AUD 0.42635) | D87: 1194 | E87: 2800.5
B88: 45520 | C88: *BUNNINGS 572000 PENRITH AUS 2,088.00 AUD (1 AED = AUD 0.42635) | D88: 2088 | E88: 4897.37
B89: 45520 | C89: *BUNNINGS 441000 PENRITH AUS 3,654.35 AUD (1 AED = AUD 0.42635) | D89: 3654.35 | E89: 8571.21
B90: 45520 | C90: *BUNNINGS 409000 GREENACRE AUS 1,791.00 AUD (1 AED = AUD 0.42635) | D90: 1791 | E90: 4200.76
B91: 45520 | C91: *BUNNINGS 689000 MILL PARK AUS 4,179.00 AUD (1 AED = AUD 0.42635) | D91: 4179 | E91: 9801.77
B92: 45520 | C92: *BUNNINGS 758000 RAVENHALL AUS 2,388.00 AUD (1 AED = AUD 0.42635) | D92: 2388 | E92: 5601.01
B93: 45520 | C93: *BUNNINGS 676000 NUNAWADING AUS 4,179.00 AUD (1 AED = AUD 0.42635) | D93: 4179 | E93: 9801.77
B95: 45523 | C95: *BUNNINGS 605000 NARRE WARREN AUS 4,776.00 AUD (1 AED = AUD 0.42635) | D95: 4776 | E95: 11202.02
... B100: 45523 | C100: *BUNNINGS 731000 PAKENHAM AUS 6,866.00 AUD (1 AED = AUD 0.42635) | D100: 6866 | E100: 16104.08

Sheet Total
A3: Payment From/To | C3: Date | D3: Shipment | E3: Pur/Sell | F3: Details | G3: Dollar | H3: Rate | I3: Purchasing | J3: Sell | K3: Total AED | M3: Stock Qnty
A5: WB | C5: 45397 | D5: Ref#1001V2 | E5: Purchasing | F5: 1st Shipment Purchasing Invoice (1) Starlink V2 Device 16Units $5774.55 | G5: 5774.55 | H5: 2.42 | I5: =G5*H5 -> 13974.411 | K5: =K4+I5-J5 -> 13974.411
A6: WB | C6: 45397 | D6: Ref#1002 V2 | E6: Purchasing | F6: 2nd Shipment Purchasing Invoice (2) Starlink V2 Device 11Units $3970.01 | G6: =11*360.91 -> 3970.01 | H6: 2.42 | I6: =G6*H6 -> 9607.4242 | K6: =K5+I6-J6 -> 23581.835
A7: WB | C7: 45397 | D7: Ref#1001V2 | E7: Exp | F7: 1st Shipping Invoice V2 $1516.06 | G7: 1516.06 | H7: 2.42 | I7: =G7*H7 -> 3668.8652 | K7: =K6+I7-J7 -> 27250.7
A8: WB | C8: 45397 | D8: Ref#1002 V2 | E8: Exp | F8: Sasco Shipping Charges (1st Invoice) | I8: 660 | K8: =K7+I8-J8 -> 27910.7
A9: WB | D9: Ref#1002 V2 | E9: Exp | F9: Sasco Shipping Charges (2nd Invoice) | I9: 650 | K9: =K8+I9-J9 -> 28560.7
A10: AR | C10: 45420 | D10: Ref#1001V2 | E10: Sell | F10: Sell By A/R V2 20pcs @1450 | J10: =20*1450 -> 29000 | K10: =K9+I10-J10 -> -439.2996
A11: AR | C11: 45427 | D11: Ref#1002 V2 | E11: Sell | F11: V2 Sold AMGT 5pcs @1190 (09/05/2024) | J11: =5*1190 -> 5950 | K11: =K10+I11-J11 -> -6389.2996
A12: AR | C12: 45428 | D12: Ref#1002 V2 | E12: Sell | F12: Sold To A/R 2pcs @1000 | J12: =2*1000 -> 2000 | K12: =K11+I12-J12 -> -8389.2996
A13: … | K13: =K12+I13-J13 -> -8389.2996
A14: AR | C14: 45419 | D14: Ref#1003V3 | E14: Exp | F14: V3 106pcs Import Charges (Paid By A/R Dubai) | I14: 4230 | K14: =K13+I14-J14 -> -4159.2996
A15: AR | C15: 45420 | D15: Ref#1003V3 | E15: Exp | F15: Hamali Charges (by Amgt 09pcs sell) | I15: 10 | K15: =K14+I15-J15 -> -4149.2996
A16: WB | C16: 45423 | D16: Ref#1003V3 | E16: Exp | F16: Car Petrol | G16: 58 | H16: 2.42 | I16: =G16*H16 -> 140.36 | K16: =K15+I16-J16 -> -4008.9396
A17: WB | C17: 45423 | D17: Ref#1003V3 | E17: Exp | F17: Van Petrol | G17: 28 | H17: 2.42 | I17: =G17*H17 -> 67.76 | K17: =K16+I17-J17 -> -3941.1796
A18: WB | C18: 45423 | D18: Ref#1003V3 | E18: Exp | F18: Van Hire | G18: 101 | H18: 2.42 | I18: =G18*H18 -> 244.42 | K18: =K17+I18-J18 -> -3696.7596
A19: WB | C19: 45423 | D19: Ref#1003V3 | E19: Purchasing | F19: 1 Unit Purchase Waheed Bhai Card | G19: 522.04 | H19: 2.42 | I19: =G19*H19 -> 1263.3368 | K19: =K18+I19-J19 -> -2433.4228
A20: WB | C20: 45423 | D20: Ref#1003V3 | E20: Exp | F20: Shipping Charges | G20: 4327.63 | H20: 2.42 | I20: =G20*H20 -> 10472.865 | K20: =K19+I20-J20 -> 8039.4418
A21: AR | C21: 45423 | D21: Ref#1003V3 | E21: Purchasing | F21: 7units Purchase A/R Card | G21: 3654.28 | H21: 2.42 | I21: =G21*H21 -> 8843.3576 | K21: =K20+I21-J21 -> 16882.799
A22: AB | C22: 45423 | D22: Ref#1003V3 | E22: Purchasing | F22: 46Units Purchase Ashfaq Sahab Card | G22: 24013.84 | H22: 2.42 | I22: =G22*H22 -> 58113.493 | K22: =K21+I22-J22 -> 74996.292
A23: AB | C23: 45423 | D23: Ref#1003V3 | E23: Purchasing | F23: Card Payment Ashfaq Sahab | G23: 18944 | H23: 2.42 | I23: =G23*H23 -> 45844.48 | K23: =K22+I23-J23 -> 120840.77
A24: AR | C24: 45423 | D24: Ref#1003V3 | E24: Purchasing | F24: Card Payment Abdul Rehman bhai | G24: 7696 | H24: 2.42 | I24: =G24*H24 -> 18624.32 | K24: =K23+I24-J24 -> 139465.09
A25: WB | C25: 45423 | D25: Ref#1003V3 | E25: Purchasing | F25: Card Payment Waheed bhai | G25: 524.8 | H25: 2.42 | I25: =G25*H25 -> 1270.016 | K25: =K24+I25-J25 -> 140735.11
A26: WB | D26: Ref#1003V3 | E26: Exp | F26: Less GST $47.49 x106 | G26: =-47.49*106 -> -5033.94 | H26: 2.42 | J26: =5033.94*2.42 -> 12182.135 | K26: =K25+I26-J26 -> 128552.97
A27: AR | C27: 45419 | D27: Ref#1003V3 | E27: Sell | F27: Sold to Encell Shop 20pcs @1790 | J27: =1790*20 -> 35800 | K27: =K26+I27-J27 -> 92752.973
A28: AR | C28: 45420 | D28: Ref#1003V3 | E28: Sell | F28: Sell to AMGT V3 09pcs @1800 | J28: =9*1800 -> 16200 | K28: =K27+I28-J28 -> 76552.973
A29: AR | C29: 45420 | D29: Ref#1003V3 | E29: Sell | F29: Sold to Encell Shop 10pcs @1800 | J29: =10*1800 -> 18000 | K29: =K28+I29-J29 -> 58552.973
A30: AR | C30: 45427 | D30: Ref#1003V3 | E30: Sell | F30: Sold To AMGT V3 2pcs @1800 (09/05/2024) | J30: =2*1800 -> 3600 | K30: =K29+I30-J30 -> 54952.973
A31: AR | C31: 45427 | D31: Ref#1003V3 | E31: Sell | F31: Sold To AMGT V3 2pcs @1750 (09/05/2024) | J31: =2*1750 -> 3500 | K31: =K30+I31-J31 -> 51452.973
A32: AR | C32: 45427 | D32: Ref#1003V3 | E32: Sell | F32: Sold To AMGT V3 5pcs @1740 (13/05/2024) | J32: =5*1740 -> 8700 | K32: =K31+I32-J32 -> 42752.973
A33: AR | C33: 45427 | D33: Ref#1003V3 | E33: Sell | F33: Sold To AMGT V3 16pcs @1650 (13/05/2024) | J33: =16*1650 -> 26400 | K33: =K32+I33-J33 -> 16352.973
A34: AR | C34: 45427 | D34: Ref#1003V3 | E34: Sell | F34: Sold to Encell Shop 26pcs @1750 | J34: =26*1750 -> 45500 | K34: =K33+I34-J34 -> -29147.027
A35: AR | C35: 45427 | D35: Ref#1003V3 | E35: Sell | F35: Sold to Encell Shop 5pcs @1700 | J35: =5*1700 -> 8500 | K35: =K34+I35-J35 -> -37647.027
A36: AR | C36: 45427 | D36: Ref#1003V3 | E36: Sell | F36: Sold To AMGT V3 1pcs @1700 (15/05/2024) | J36: =1*1700 -> 1700 | K36: =K35+I36-J36 -> -39347.027
A37: AR | C37: 45427 | D37: Ref#1003V3 | E37: Sell | F37: Sold To AMGT V3 10pcs @1695 (15/05/2024) | J37: =10*1695 -> 16950 | K37: =K36+I37-J37 -> -56297.027
A38: …. | F38: Ref#1001 to 1003 (V2 27.Units & V3 106.Units) | I38: 56297.03 | K38: =K37+I38-J38 -> 0.0034
A39: AR | C39: 45440 | D39: V3 35pcs | E39: Exp | F39: V3 Import Charges 35pcs | I39: 1230 | K39: =K38+I39-J39 -> 1230.0034
A40: ??? | C40: 45440 | D40: V3 35pcs | E40: Purchasing | F40: 35 pcs Purchased @474.58 | G40: =474.58*35 -> 16610.3 | H40: 2.44 | I40: =G40*H40 -> 40529.132 | K40: =K39+I40-J40 -> 41759.135 | L40: WB
A41: WB | C41: 45440 | D41: V3 35pcs | E41: Exp | F41: Other Expense Paid by Waheed Bhai | G41: 126 | H41: 2.44 | I41: =G41*H41 -> 307.44 | K41: =K40+I41-J41 -> 42066.575
A42: AR | C42: 45440 | D42: V3 35pcs | E42: Exp | F42: Hamali Charges Paid by AR | I42: 30 | K42: =K41+I42-J42 -> 42096.575
A43: ??? | C43: 45443 | D43: V3 35pcs | E43: Exp | F43: Shipping Charges | G43: 1638.29 | H43: 2.44 | I43: =G43*H43 -> 3997.4276 | K43: =K42+I43-J43 -> 46094.003 | L43: AB
A44: AR | C44: 45447 | D44: V3 35pcs | E44: Exp | F44: Fahib Salary M/O May-2024 (15000 PKR) | I44: 194.81 | K44: =K43+I44-J44 -> 46288.813
A45: ??? | C45: 45471 | D45: V3 35pcs | E45: Exp | F45: Surcharge Include | G45: 23.01 | H45: 2.44 | I45: =G45*H45 -> 56.1444 | K45: =K44+I45-J45 -> 46344.957 | L45: AB
A46: AR | C46: 45442 | D46: V3 35pcs | E46: Sell | F46: Sell Encell Shop 2pcs | J46: 3240 | K46: =K45+I46-J46 -> 43104.957
A47: AR | C47: 45442 | D47: V3 35pcs | E47: Sell | F47: Sell Encell Shop 18pcs | J47: 29520 | K47: =K46+I47-J47 -> 13584.957
A48: AR | C48: 45442 | D48: V3 35pcs | E48: Sell | F48: Sell AMGT Office 15pcs | J48: 24300 | K48: =K47+I48-J48 -> -10715.043
K49: =K48+I49-J49 -> -10715.043
F50: Ref#1004 (V3 35.Units) | I50: 10715.04 | K50: =K49+I50-J50 -> -0.0026
A51: AR | C51: 45448 | D51: V3 60pcs | E51: Exp | F51: V3 Clearing Charges 60pcs (Paid by A/R) | G51: - | H51: - | I51: 1660 | K51: =K50+I51-J51 -> 1659.9974
A52: ??? | C52: 45448 | D52: V3 60pcs | E52: Purchasing | F52: 60 pcs Purchased @474.58 | G52: =474.58*60 -> 28474.8 | H52: 2.44 | I52: =G52*H52 -> 69478.512 | K52: =K51+I52-J52 -> 71138.509
A53: AR | C53: 45448 | D53: V3 60pcs | E53: Exp | F53: Hamali Charges Paid by Encell Shop | G53: - | H53: - | I53: 40 | K53: =K52+I53-J53 -> 71178.509
A54: WB | C54: 45448 | D54: V3 60pcs | E54: Exp | F54: Other Expense Paid By Waheed Bhai | G54: 360 | H54: 2.44 | I54: =G54*H54 -> 878.4 | K54: =K53+I54-J54 -> 72056.909
A55: ??? | C55: 45456 | D55: V3 60pcs | E55: Exp | F55: Shipping Invoice | G55: 2651.54 | H55: 2.44 | I55: =G55*H55 -> 6469.7576 | K55: =K54+I55-J55 -> 78526.667 | L55: AB
A56: AB | C56: 45471 | D56: V3 60pcs | E56: Exp | F56: Surcharge Include | G56: 23.01 | H56: 2.44 | I56: =G56*H56 -> 56.1444 | K56: =K55+I56-J56 -> 78582.811
A57: AR | C57: 45448 | D57: V3 60pcs | E57: Sell | F57: Sell Encell Shop 20pcs | J57: =1680*20 -> 33600 | K57: =K56+I57-J57 -> 44982.811
A58: AR | C58: 45449 | D58: V3 60pcs | E58: Sell | F58: Sell Encell Shop 30pcs | J58: =1680*30 -> 50400 | K58: =K57+I58-J58 -> -5417.1886
A59: AR | C59: 45453 | D59: V3 60pcs | E59: Sell | F59: Sell AMGT 2pcs | J59: 3400 | K59: =K58+I59-J59 -> -8817.1886
A60: AR | C60: 45455 | D60: V3 60pcs | E60: Sell | F60: Sell Encell Shop 2pcs | J60: =1670*2 -> 3340 | K60: =K59+I60-J60 -> -12157.189
A61: AR | C61: 45456 | D61: V3 60pcs | E61: Sell | F61: Sell to AMGT 6pcs | J61: 9990 | K61: =K60+I61-J61 -> -22147.189
F62: Ref#1005 (V3 60.Units) | I62: 22147.19 | K62: =K61+I62-J62 -> 0.0014
A63: ??? | C63: 45449 | D63: V3 47pcs | E63: Purchasing | F63: Purchased 40pcs @474.58 (GST 1890) | G63: =40*474.58 -> 18983.2 | H63: 2.44 | I63: =G63*H63 -> 46319.008 | K63: =K62+I63-J63 -> 46319.009
A64: ??? | C64: 45449 | D64: V3 47pcs | E64: Purchasing | F64: Purchased 5pcs @481.81 (GST 193) | G64: =5*481.81 -> 2409.05 | H64: 2.44 | I64: =G64*H64 -> 5878.082 | K64: =K63+I64-J64 -> 52197.091
A65: AR | C65: 45449 | D65: V3 47pcs | E65: Purchasing | F65: Purchased 2pcs @474.58 (GST 94.50) (wire Payment AR) | G65: =2*474.58 -> 949.16 | H65: 2.44 | I65: =G65*H65 -> 2315.9504 | K65: =K64+I65-J65 -> 54513.042
A66: WB | C66: 45449 | D66: V3 47pcs | E66: Exp | F66: Expense $40 Petrol Charges | G66: 40 | H66: 2.44 | I66: =G66*H66 -> 97.6 | K66: =K65+I66-J66 -> 54610.642
A67: WB | C67: 45453 | D67: V3 47pcs | E67: Exp | F67: Expense $50 Toll Charges | G67: 50 | H67: 2.44 | I67: =G67*H67 -> 122 | K67: =K66+I67-J67 -> 54732.642
A68: AR | C68: 45453 | D68: V3 47pcs | E68: Exp | F68: Clearing Charges Paid by A/R | G68: - | H68: - | I68: 1465 | K68: =K67+I68-J68 -> 56197.642
A69: AR | C69: 45453 | D69: V3 47pcs | E69: Exp | F69: Hamali Charges Paid by A/R | G69: - | H69: - | I69: 35 | K69: =K68+I69-J69 -> 56232.642
A70: ??? | C70: 45456 | D70: V3 47pcs | E70: Exp | F70: Shipping Invoice | G70: 2153.6 | H70: 2.44 | I70: =G70*H70 -> 5254.784 | K70: =K69+I70-J70 -> 61487.426 | L70: AB
A71: GST | C71: 45456 | D71: V3 47pcs | E71: Exp | F71: Shipping Invoice GST | G71: 24.36 | H71: 2.44 | I71: =G71*H71 -> 59.4384 | K71: =K70+I71-J71 -> 61546.864
A72: ??? | C72: 45471 | D72: V3 47pcs | E72: Exp | F72: Surcharge Include | G72: 23.01 | H72: 2.44 | I72: =G72*H72 -> 56.1444 | K72: =K71+I72-J72 -> 61603.009 | L72: AB
A73: AR | C73: 45453 | D73: V3 47pcs | E73: Sell | F73: Sell Encell Shop 35pcs | J73: 58800 | K73: =K72+I73-J73 -> 2803.0086
A74: AR | C74: 45456 | D74: V3 47pcs | E74: Sell | F74: Sell To AMGT 7pcs | J74: 11655 | K74: =K73+I74-J74 -> -8851.9914
A75: AR | C75: 45456 | D75: V3 47pcs | E75: Sell | F75: Sell Encell Shop 5pcs | J75: 8350 | K75: =K74+I75-J75 -> -17201.991
F76: Ref#1006 (V3 47.Units) | I76: 17202 | K76: =K75+I76-J76 -> 0.0086
A77: AB | C77: 45468 | D77: Ref# 1007 V3 | E77: Purchasing | F77: Ashfaq Shab Card 57.5 Units @474 | G77: =57.5*474 -> 27255 | H77: 2.44 | I77: =G77*H77 -> 66502.2 | K77: =K76+I77-J77 -> 66502.209
A78: AB | C78: 45468 | D78: Ref# 1007 V3 | E78: Purchasing | F78: Ashfaq Shab Card 24 Units @474 | G78: =24*474 -> 11376 | H78: 2.44 | I78: =G78*H78 -> 27757.44 | K78: =K77+I78-J78 -> 94259.649
A79: WB | C79: 45468 | D79: Ref# 1007 V3 | E79: Purchasing | F79: Waheed Bhai Card 12.5 Units @474 | G79: =12.5*474 -> 5925 | H79: 2.44 | I79: =G79*H79 -> 14457 | K79: =K78+I79-J79 -> 108716.65
A80: GST | D80: Ref# 1007 V3 | E80: Purchasing | F80: 94pcs Total GST @$48 | G80: 4512 | H80: 2.44 | I80: =G80*H80 -> 11009.28 | K80: =K79+I80-J80 -> 119725.93
A81: GST | D81: Ref# 1007 V3 | E81: Purchasing | F81: GST amount GST Ledger (12.5 units Waheed Bhai / 81.5 Units Business) | G81: -4512 | H81: 2.44 | I81: =G81*H81 -> -11009.28 | K81: =K80+I81-J81 -> 108716.65
A82: REFUND | C82: 45468 | D82: Ref# 1007 V3 | E82: Purchasing | F82: Refundable Charges 94Units @597-522.04 =74.96 | G82: =94*74.96 -> 7046.24 | H82: 2.44 | I82: =G82*H82 -> 17192.826 | K82: =K81+I82-J82 -> 125909.47
A83: REFUND | D83: Ref# 1007 V3 | E83: Purchasing | F83: Refundable Charges Adjustment (12.5 units Waheed Bhai / 81.5 Units Business) | G83: =94*74.96 -> 7046.24 | H83: 2.44 | I83: =G83*H83 -> 17192.826 | K83: =K82+I83-J83 -> 143102.3
A84: WB | C84: 45468 | D84: Ref# 1007 V3 | E84: Exp | F84: Other Expense Paid by Waheed Bhai ticket/car/petrol/toll/bus) | G84: 750 | H84: 2.44 | I84: =G84*H84 -> 1830 | K84: =K83+I84-J84 -> 144932.3
A85: WB | C85: 45468 | D85: Ref# 1007 V3 | E85: Exp | F85: Shipping Charges paid By Waheed Bhai | G85: 3687.51 | H85: 2.44 | I85: =G85*H85 -> 8997.5244 | K85: =K84+I85-J85 -> 153929.82
A86: AR | C86: 45469 | D86: Ref# 1007 V3 | E86: Exp | F86: Hamali Charges Paid by A/R | H86: - | I86: 25 | K86: =K85+I86-J86 -> 153954.82
A87: AR | C87: 45471 | D87: Ref# 1007 V3 | E87: Exp | F87: Hamali Charges Paid by A/R | H87: - | I87: 50 | K87: =K86+I87-J87 -> 154004.82
A88: AR | C88: 45471 | D88: Ref# 1007 V3 | E88: Exp | F88: Cargo Charges Paid by A/R | H88: - | I88: 100 | K88: =K87+I88-J88 -> 154104.82
A89: AR | C89: 45472 | D89: Ref# 1007 V3 | E89: Exp | F89: V3 Hamali Charges Paid by A/R (ali karachi Ledger) | I89: 60 | K89: =K88+I89-J89 -> 154164.82
A90: AR | C90: 45472 | D90: Ref# 1007 V3 | E90: Exp | F90: V3 Clearing Charges Paid by A/R (Ali karachi Ledger) | I90: 1350 | K90: =K89+I90-J90 -> 155514.82
A91: AR | C91: 45469 | D91: Ref# 1007 V3 | E91: Sell | F91: 26pcs Sell To Encell Shop @1580 | J91: =26*1580 -> 41080 | K91: =K90+I91-J91 -> 114434.82
A92: AR | C92: 45471 | D92: Ref# 1007 V3 | E92: Sell | F92: 20pcs Sell To Encell Shop @1575 | J92: 31500 | K92: =K91+I92-J92 -> 82934.824
A93: AR | C93: 45474 | D93: Ref# 1007 V3 | E93: Sell | F93: 48pcs Sell To Encell Shop @1530 | J93: =1530*48 -> 73440 | K93: =K92+I93-J93 -> 9494.8242
F94: Ref#1007 (V3 94.Units)
C97: Date | D97: Shipment | E97: Pur/Sell | F97: Details | G97: Dollar | H97: Rate | I97: Purchasing | J97: Sell | K97: Total AED
A98: AR | C98: 45474 | D98: Ref# 1008 V3 | E98: Exp | F98: V3 Hamali Charges Paid by A/R (Encell Shop) | I98: 60 | K98: =K94+I98-J98 -> 60
A99: AR | C99: 45474 | D99: Ref# 1008 V3 | E99: Exp | F99: V3 Clearing Charges Paid by A/R (Encell Shop) | I99: 1050 | K99: =K98+I99-J99 -> 1110
A100: AB/WB | C100: 45473 | D100: Ref# 1008 V3 | E100: Exp | F100: Petrol Expense (Ab + WB Card) | G100: 165 | H100: 2.44 | I100: =G100*H100 -> 402.6 | K100: =K99+I100-J100 -> 1512.6
A101: AB | C101: 45473 | D101: Ref# 1008 V3 | E101: Purchasing | F101: 4pcs Harvey Norman $500 | G101: =4*500 -> 2000 | H101: 2.44 | I101: =G101*H101 -> 4880 | K101: =K100+I101-J101 -> 6392.6
A102: AB | C102: 45473 | D102: Ref# 1008 V3 | E102: Purchasing | F102: 3 JB hi fi $500 | G102: =3*500 -> 1500 | H102: 2.44 | I102: =G102*H102 -> 3660 | K102: =K101+I102-J102 -> 10052.6
A103: WB | C103: 45473 | D103: Ref# 1008 V3 | E103: Purchasing | F103: 2 JB Hi fi $500 (WB Card) | G103: =2*500 -> 1000 | H103: 2.44 | I103: =G103*H103 -> 2440 | K103: =K102+I103-J103 -> 12492.6
A104: AB | C104: 45473 | D104: Ref# 1008 V3 | E104: Purchasing | F104: 3 JB Hi fi $522 | G104: =3*522 -> 1566 | H104: 2.44 | I104: =G104*H104 -> 3821.04 | K104: =K103+I104-J104 -> 16313.64
A105: AB | C105: 45473 | D105: Ref# 1008 V3 | E105: Purchasing | F105: 1 JB Hi fi $522 | G105: 522 | H105: 2.44 | I105: =G105*H105 -> 1273.68 | K105: =K104+I105-J105 -> 17587.32
...

Sheet Pending Work
C4: 45566 | D4: Purchased 100 Units $5000 Dollar Advance Payment
C5: 45591 | D5: Starlink V4 12Units Short ??? Msg To AR
C6: 45591 | D6: Purchasing Pending
C7: 45591 | D7: Cash Handover to AMGT Office
C8: 45591 | D8: 1400 $ Handover to AMGT Office
C9: 45591 | D9: 50 Australian Dollar to AMGT Office
C10: 45591 | D10: Australia Stock Confirmation Pending Msg Send to Waheed Bhai
C12: 45593 | D12: Purchasing Pending
C13: 45593 | D13: Extra Cash Pending By A/R 15297 Aed
C14: 45593 | D14: GST Pending
C15: 45593 | D15: Pending Collections..??
C17: 45596 | D17: Shipping Charges Pending ??
C18: 45596 | D18: Gift Card Balances
F23: Date | G23: Details | H23: V4 | I23: Mini | J23: Camera | K23: Charge 5 | L23: Essential 2 | M23: PS 5 | N23: IP 16PM 256 | O23: DJI Mavic | P23: Intax Wide | Q23: Intax Mini | R23: Xtreme 4 | S23: Xtreme 3
F25: 45579 | G25: Last Closing Units | H25: 73 | I25: 121 | J25: 1
F26: 45580 | G26: Purchased msg by A/R | H26: 55 | I26: 10
F27: 45582 | G27: Send to Dubai | H27: -55 | I27: -10
F28: 45584 | G28: Send to Dubai | H28: -42 | I28: -119
F29: 45584 | G29: Purchase 20 Units Mini $745 | H29: 0 | I29: 20
F30: 45588 | G30: Mini Purchased WB Card | I30: 8
F32: 45591 | G32: Charge.5 45Units $142 | K32: 45
F33: 45591 | G33: Flip Essential 2 14Units $68 | L33: 14
F34: 45591 | G34: PS5 10 Units $669 | M34: 10
F35: 45591 | G35: IP 16ProMax 256GB 1.Unit $2147 | N35: 1
F36: 45591 | G36: Starlink Mini 30 Units $745 | I36: 30
E37: Cancelled Purchased | F37: 45591 | G37: Charge.5 100 Units $145 | K37: =100-100 -> 0
E38: Cancelled Purchased | F38: 45591 | G38: Flip Essential 2 100 Units $68 | L38: =100-100 -> 0
F39: 45591 | G39: PS5 2 Units $675 | M39: 2
F40: 45591 | G40: Charge.5 100 Units $133.3 | K40: 100
F41: 45591 | G41: Charge.5 34 Units $133.3 | K41: 34
E42: Returned | F42: 45591 | G42: Starlink Mini 10 Units $768 (Returned)
F43: 45591 | G43: Instax Camera 7units $95 | J43: 7
F45: 45593 | G45: Starlink Mini 100 Units $750 | I45: 100
E46: 8 units Returned | F46: 45593 | G46: DJI MavicPro 10Units $2500 (8unit Returned) | O46: =10-8 -> 2
F47: 45593 | G47: PS5 2 Units $669 | M47: 2
F49: 45596 | G49: Send to Dubai Starlink V4 23 Units | H49: -23
F50: 45601 | G50: Instax Wide 400 8units $189 | P50: 8
F51: 45601 | G51: Instax Mini 99 10Units $230 | Q51: 10
F52: 45605 | G52: 20 Units V4 Purchase $500 | H52: 20
F53: 45607 | G53: Send to Dubai | H53: -26 | I53: -53 | J53: -7 | K53: -79 | L53: -14 | M53: -14 | O53: -2 | P53: -8 | Q53: -10
F54: 45610 | G54: Mini Purchase Returned (Ref# 28/10) | I54: -100
F56: 45608 | G56: Strarlink V4 39Units $549 WB Card | H56: 39
F57: 45609 | G57: Strarlink V4 10Units $549 WB Card | H57: 10
F58: 45610 | G58: Starlink Mini 120Units $548 WB Card | I58: 120
F59: 45610 | G59: Starlink Mini 6Units $579 WB Card | I59: 6
F61: 45611 | G61: JBL Charge 5 50Units $133.30 | K61: 50
F62: 45611 | G62: Starlink Mini 10 Units $598 | I62: 10
F63: 45611 | G63: Starlink V4 7Units $500 | H63: 7
F64: 45611 | G64: Starlink Mini 4 Units $579 | I64: 4
F65: 45611 | G65: Xtreme 4 4Units $269 | R65: 4
F66: 45611 | G66: Charge.5 100 Units $140-10% $126 | K66: 100
F68: 45612 | G68: Starlink Mini 12Units $598 | I68: 12
F69: 45612 | G69: JBL Charge 5 30Units $131 | K69: 30
F70: 45612 | G70: JBL Charge 5 10Units $131 | K70: 10
F72: 45613 | G72: Starlink Mini 13Units $598 WB | I72: 13
F73: 45613 | G73: Starlink Mini 14Units $619 WB | I73: 14
F74: 45613 | G74: Starlink Mini 4Units $618 WB | I74: 4
F75: 45613 | G75: Starlink Mini 4Units $598 WB | I75: 4
E76: Cancelled Purchased | F76: 45613 | G76: JBL Charge 5 200 Units $120 WB | K76: =200-200 -> 0
E77: Cancelled Purchased | F77: 45613 | G77: Xtreme 4 50Units $260 WB | R77: =50-50 -> 0
E78: 2 Cancelled Purchased | F78: 45613 | G78: Mavic Pro3 4units $2500 | O78: =4-2 -> 2
F79: 45613 | G79: JBL Charge 5 30 Units $126 WB | K79: 30
F80: 45614 | G80: Send to Dubai | H80: -57 | I80: -167 | K80: -200 | O80: -2 | R80: -4
F82: 45615 | G82: Starlink mini 10 Units $598 WB | I82: 10
F83: 45615 | G83: Starlink V4 9 Units $549 WB | H83: 9
F84: 45616 | G84: Starlink mini 10 Units $598 WB | I84: 10
F85: 45616 | G85: Starlink V4 14 Units $549 WB | H85: 14
F87: 45617 | G87: Starlink mini 4 Units $598 WB | I87: 4
F88: 45617 | G88: Starlink V4 6 Units $549 WB | H88: 6
F89: 45617 | G89: Starlink mini 1 Units $599 WB | I89: 1
F90: 45617 | G90: Starlink mini 1 Units $599 WB | I90: 1
F91: 45617 | G91: JBL Extreme 3 2units $180 WB | S91: 2
F93: 45618 | G93: Starlink Mini 5 units $599 | I93: 5
F94: 45618 | G94: Starlink V4 3 units $500 | H94: 3
F95: 45619 | G95: Starlink V4 2 units $549 | H95: 2
G97: (New Zealand Stock)
F98: 45621 | G98: Starlink Mini 3Units $649 | I98: 3
F99: 45621 | G99: Charge.5 2Units $145 | K99: 2
F100: 45621 | G100: PS5 2Units $692 | M100: 2
F101: 45621 | G101: PS5 10Units $692 | M101: 10
F102: 45621 | G102: PS5 2Units $692 | M102: 2
F103: 45621 | G103: Starlink Mini 1Unit $649 | I103: 1
F104: 45621 | G104: Starlink Mini 10Unit $649 | I104: 10
F105: 45621 | G105: Starlink V4 5Units $529 | H105: 5
F106: 45621 | G106: Starlink Mini 5Unit $644 | I106: 5
F107: 45621 | G107: Starlink V4 6Units $598 | H107: 6
F109: 45622 | G109: Send to Dubai | H109: -57 | I109: -39 | K109: -37 | S109: -2
G110: (New Zealand Stock)
F111: 45622 | G111: Starlink V4 10units $598 WB Card | H111: 10
F112: 45622 | G112: Starlink Mini 1unit $649 WB Card | I112: 1
F113: 45622 | G113: Starlink Mini 4unit $649 WB Card | I113: 4
F114: 45622 | G114: JBL Charge.5 25Units $128 WB Card | K114: 25
F115: 45622 | G115: Starlink Mini 2unit $649 WB Card | I115: 2
F117: 45622 | G117: Starlink Mini 1unit $649 WB Card | I117: 1
F118: 45622 | G118: Starlink V4 50units $598 WB Card | H118: 50
G119: (New Zealand Stock)
F120: 45623 | G120: Starlink Mini 46Units $644 WB Card | I120: 46
F121: 45623 | G121: Starlink V4 10Units $530 WB Card | H121: 10
F122: 45623 | G122: Starlink Mini 5Units $649 WB Card | I122: 5
F123: 45623 | G123: Starlink Mini 4Units $649 WB Card | I123: 4
...

Sheet Sheet2
E3: Pending Collection
D4: Date | E4: Details | F4: V4 | G4: Mini | H4: Starlink HP Kit | I4: Charge 5 | J4: Essential 2 | K4: MacBook M4
C8: ok | D8: 45612 | E8: JBL Charge 5 30Units $131 | I8: =30-27 -> 3
C11: ok | D11: 45617 | E11: Starlink mini 1 Units $599 WB | G11: 1
C12: ok
O13: Details | Q13: Unit | R13: $ Rate | S13: $ Total | T13: Deposit | U13: Balance | V13: AED Rate | W13: Total AED
D14: 45638 | E14: Starlink Mini 100Units $649 WB Card 5000 DDEPOSIT NZ | G14: 100 | O14: Starlink Mini 100Units $649 WB Card 5000 Deposit NZ | Q14: 100 | R14: 649 | S14: =Q14*R14 -> 64900 | T14: -5000 | U14: =S14+T14 -> 59900 | V14: 2.19 | W14: =U14*V14 -> 131181
C16: 32UNIT PAYMENT BALANCE | D16: 45644 | E16: JBL Charge 5 60Units $132 WB Card | I16: =60-28 -> 32 | O16: JBL Charge 5 32Units $132 WB Card | Q16: 32 | R16: 132 | S16: =Q16*R16 -> 4224 | T16: 0 | U16: =S16+T16 -> 4224 | V16: 2.375 | W16: =U16*V16 -> 10032
D18: 45652 | E18: JBL Charge 5 40units $140-10% WB Card $700 Deposit | I18: 40 | O18: JBL Charge 5 40units $140-10% WB Card $700 Deposit | Q18: 40 | R18: 126 | S18: =Q18*R18 -> 5040 | T18: -700 | U18: =S18+T18 -> 4340 | V18: 2.33 | W18: =U18*V18 -> 10112.2
D19: 45652 | E19: Apple MacBook Pro M4 3Unit $2968-10% WB Card 890$ D | K19: 3 | O19: Apple MacBook Pro M4 3Unit $2968-10% WB Card 890$ D | Q19: 3 | R19: 2671.2 | S19: =Q19*R19 -> 8013.6 | T19: -890 | U19: =S19+T19 -> 7123.6 | V19: 2.33 | W19: =U19*V19 -> 16597.988
C20: not paid | D20: 45652 | E20: JBL Charge 5 75units $128 WB Card | I20: 75 | O20: JBL Charge 5 75units $128 WB Card (Not Paid) | Q20: 75 | R20: 128 | S20: =Q20*R20 -> 9600 | T20: 0 | U20: =S20+T20 -> 9600 | V20: 2.33 | W20: =U20*V20 -> 22368
D21: 45652 | E21: JBL Charge5 60Units $140-10% WB Card $500 D | I21: 60 | O21: JBL Charge5 60Units $140-10% WB Card $500 D | Q21: 60 | R21: 126 | S21: =Q21*R21 -> 7560 | T21: -500 | U21: =S21+T21 -> 7060 | V21: 2.33 | W21: =U21*V21 -> 16449.8
W22: =SUM(W14:W21) -> 206740.99
E23: Remaining Units | F23: =SUM(F6:F22) -> 0 | G23: =SUM(G6:G22) -> 101 | H23: =SUM(H6:H22) -> 0 | I23: =SUM(I6:I22) -> 210 | J23: =SUM(J6:J22) -> 0 | K23: =SUM(K6:K22) -> 3
O27: Mac Book Pro 2Units $2968-10% WB Card | P27: 2
O28: Apple MacBook Pro M4 3Unit $2968-10% WB Card | P28: 3
O29: MacBook M4 1Unit $2968+$40-10% WB Card | P29: 1
O30: MacBook 2Units $2948-10% WB Card | P30: 2
O33: MacBook M3 1Unit $2158+$40 WB Card | P33: 1
O34: MacBook M3 1Unit $2158 WB Card | P34: 1

Sheet Ledgers
D2: AR | J2: Group | K2: AR Payments
C3: Date | D3: Details | E3: Payment | F3: Received | G3: Balance
B5: WB.P | C5: 45394 | D5: From A/R Laguna Payment | E5: =97774/77 -> 1269.7922 | G5: =G4+E5-F5 -> 1269.7922 | H5: ok
B6: WB.P | C6: 45394 | D6: From A/R Laguna Payment | E6: =164448/77 -> 2135.6883 | G6: =G5+E6-F6 -> 3405.4805 | H6: ok
B7: WB.P | C7: 45397 | D7: From A/R Paid to Waheed Bhai (agha m.aftab A/C) | E7: 30 | G7: =G6+E7-F7 -> 3435.4805 | H7: ok
B8: WB.P | C8: 45410 | D8: From A/R Laguna Payment | E8: =97774/77 -> 1269.7922 | G8: =G7+E8-F8 -> 4705.2727 | H8: ok
B9: WB.P | C9: 45410 | D9: From A/R Laguna Payment | E9: =164448/77 -> 2135.6883 | G9: =G8+E9-F9 -> 6840.961 | H9: ok
B10: Sasco | C10: 45412 | D10: From A/R by Sasco (9744.30 dollar) @2.44 | E10: 23870 | G10: =G9+E10-F10 -> 30710.961 | J10: ok
B11: Sasco | C11: 45397 | D11: Sasco Shipping Charges (1st Invoice) | E11: 660 | G11: =G10+E11-F11 -> 31370.961 | J11: ok
B12: Sasco | D12: Sasco Shipping Charges (2nd Invoice) | E12: 650 | G12: =G11+E12-F12 -> 32020.961 | J12: ok
B13: Sell | C13: 45420 | D13: Sell By A/R V2 20pcs @1450 | F13: 29000 | G13: =G12+E13-F13 -> 3020.961 | H13: ok
B14: Payment | C14: 45420 | D14: Paid to Ashfaq sahb V3 Purchasing | E14: 45000 | G14: =G13+E14-F14 -> 48020.961 | H14: ok
B15: Sell | C15: 45427 | D15: V2 Sold AMGT 5pcs @1190 (09/05/2024) | F15: 5950 | G15: =G14+E15-F15 -> 42070.961 | H15: ok
B16: Sell | C16: 45428 | D16: Sold To A/R 2pcs @1000 | F16: 2000 | G16: =G15+E16-F16 -> 40070.961 | H16: ok
B17: Payment | C17: 45419 | D17: V3 106pcs Import Charges (Paid By A/R Dubai) | E17: 4230 | G17: =G16+E17-F17 -> 44300.961 | H17: ok
B18: Payment | C18: 45420 | D18: Hamali Charges (by Amgt 09pcs sell) | E18: 10 | G18: =G17+E18-F18 -> 44310.961 | H18: ok
B19: Payment | C19: 45423 | D19: 7units Purchase A/R Card | E19: 8843.36 | G19: =G18+E19-F19 -> 53154.321 | H19: ok
B20: Payment | C20: 45423 | D20: Card Payment Abdul Rehman bhai | E20: 18624.32 | G20: =G19+E20-F20 -> 71778.641 | H20: ok
B21: WB.P | C21: 45420 | D21: Paid From A/R to Faisal Bhai Behalf of Waheed Bhai | E21: 3896.1 | G21: =G20+E21-F21 -> 75674.741 | H21: ok
B22: Sell | C22: 45419 | D22: Sold to Encell Shop 20pcs @1790 | F22: 35800 | G22: =G21+E22-F22 -> 39874.741 | H22: ok
B23: Sell | C23: 45420 | D23: Sell to AMGT V3 09pcs @1800 | F23: 16200 | G23: =G22+E23-F23 -> 23674.741 | H23: ok
B24: Sell | C24: 45420 | D24: Sold to Encell Shop 10pcs @1800 | F24: 18000 | G24: =G23+E24-F24 -> 5674.741 | H24: ok
B25: Payment | C25: 45427 | D25: Ashfaq Sahab Remaining Payment Returned V3 | E25: 1830 | G25: =G24+E25-F25 -> 7504.741 | H25: ok
B26: Sell | C26: 45427 | D26: Sold To AMGT V3 2pcs @1800 (09/05/2024) | F26: 3600 | G26: =G25+E26-F26 -> 3904.741 | H26: ok
B27: Sell | C27: 45427 | D27: Sold To AMGT V3 2pcs @1750 (09/05/2024) | F27: 3500 | G27: =G26+E27-F27 -> 404.74104 | H27: ok
B28: Sell | C28: 45427 | D28: Sold To AMGT V3 5pcs @1740 (13/05/2024) | F28: 8700 | G28: =G27+E28-F28 -> -8295.259 | H28: ok
B29: Sell | C29: 45427 | D29: Sold To AMGT V3 16pcs @1650 (13/05/2024) | F29: 26400 | G29: =G28+E29-F29 -> -34695.259 | H29: ok
B30: Sell | C30: 45427 | D30: Sold to Encell Shop 26pcs @1750 | F30: 45500 | G30: =G29+E30-F30 -> -80195.259 | H30: ok
B31: Sell | C31: 45427 | D31: Sold to Encell Shop 5pcs @1700 | F31: 8500 | G31: =G30+E31-F31 -> -88695.259 | H31: ok
B32: Sell | C32: 45427 | D32: Sold To AMGT V3 1pcs @1700 (15/05/2024) | F32: 1700 | G32: =G31+E32-F32 -> -90395.259 | H32: ok
B33: Sell | C33: 45427 | D33: Sold To AMGT V3 10pcs @1695 (15/05/2024) | F33: 16950 | G33: =G32+E33-F33 -> -107345.26 | H33: ok
B34: Sasco | C34: 45428 | D34: Send To australia By A/R (AUD 8782.5 @2.50) | E34: 22000 | G34: =G33+E34-F34 -> -85345.259 | J34: msg 22k/20k
B35: Sasco | C35: 45432 | D35: Send To australia By A/R (AUD 23152.5 @2.505) | E35: 58000 | G35: =G34+E35-F35 -> -27345.259 | J35: ok
B36: Payment | C36: 45440 | D36: Import Charges V3 35pcs | E36: 1230 | G36: =G35+E36-F36 -> -26115.259 | H36: ok
B37: Payment | C37: 45440 | D37: Hamali Charges Paid by AR | E37: 30 | G37: =G36+E37-F37 -> -26085.259 | H37: ok
B38: Payment | C38: 45444 | D38: Encell Shop Rent Paid by Wajahat | E38: 1333 | G38: =G37+E38-F38 -> -24752.259 | H38: ok
B39: Payment | C39: 45447 | D39: Fahib Salary M/O May-2024 (15000 PKR) | E39: 194.81 | G39: =G38+E39-F39 -> -24557.449 | H39: ok
B40: WB.P | C40: 45442 | D40: Online A/R A/C (Withdraw By Waheed Bhai) | E40: 1264.58 | G40: =G39+E40-F40 -> -23292.869 | H40: ok
B41: Sell | C41: 45442 | D41: Sell Encell Shop 2pcs | F41: 3240 | G41: =G40+E41-F41 -> -26532.869 | H41: ok
B42: Sell | C42: 45442 | D42: Sell Encell Shop 18pcs | F42: 29520 | G42: =G41+E42-F42 -> -56052.869 | H42: ok
B43: Sell | C43: 45442 | D43: Sell AMGT Office 15pcs | F43: 24300 | G43: =G42+E43-F43 -> -80352.869 | H43: ok
B44: Payment | C44: 45448 | D44: V3 Clearing Charges 60pcs (Paid by A/R) | E44: 1660 | G44: =G43+E44-F44 -> -78692.869 | H44: ok
B45: Payment | C45: 45448 | D45: Hamali Charges Paid by Encell Shop | E45: 40 | G45: =G44+E45-F45 -> -78652.869 | H45: ok
B46: Sell | C46: 45448 | D46: Sell Encell Shop 20pcs | F46: 33600 | G46: =G45+E46-F46 -> -112252.87 | H46: ok
B47: Sell | C47: 45449 | D47: Sell Encell Shop 30pcs | F47: 50400 | G47: =G46+E47-F47 -> -162652.87 | H47: ok
B48: Sell | C48: 45453 | D48: Sell AMGT 2pcs | F48: 3400 | G48: =G47+E48-F48 -> -166052.87 | H48: ok
B49: Payment | C49: 45451 | D49: Paid To Ashfaq Sahab Card Purchasing | E49: 40400 | G49: =G48+E49-F49 -> -125652.87 | H49: ok
B50: Payment | C50: 45448 | D50: Paid To Ashfaq Sahab Card Purchasing | E50: 31900 | G50: =G49+E50-F50 -> -93752.869 | H50: ok
B51: Payment | C51: 45449 | D51: Purchased 2pcs @474.58 (GST 94.50) (wire Payment AR) | E51: =Total!I65 -> 2315.9504 | G51: =G50+E51-F51 -> -91436.919 | H51: ok
B52: Payment | C52: 45453 | D52: Clearing Charges Paid by A/R | E52: 1465 | G52: =G51+E52-F52 -> -89971.919 | H52: ok
B53: Payment | C53: 45453 | D53: Hamali Charges Paid by A/R | E53: 35 | G53: =G52+E53-F53 -> -89936.919 | H53: ok
B54: Sell | C54: 45453 | D54: Sell Encell Shop 35pcs | F54: 58800 | G54: =G53+E54-F54 -> -148736.92 | H54: ok
B55: Sell | C55: 45456 | D55: Sell To AMGT 7pcs | F55: 11655 | G55: =G54+E55-F55 -> -160391.92 | H55: ok
B56: Sell | C56: 45456 | D56: Sell Encell Shop 5pcs | F56: 8350 | G56: =G55+E56-F56 -> -168741.92 | H56: ok
B57: Sell | C57: 45455 | D57: Sell Encell Shop 2pcs | F57: 3340 | G57: =G56+E57-F57 -> -172081.92 | H57: ok
B58: Payment | C58: 45455 | D58: Paid To Ashfaq Sahab Card Purchasing | E58: 60640 | G58: =G57+E58-F58 -> -111441.92 | H58: ok
B59: Sell | C59: 45456 | D59: Sell AMGT Office 6pcs | F59: 9990 | G59: =G58+E59-F59 -> -121431.92 | H59: ok
B60: Payment | C60: 45457 | D60: Paid To Ashfaq Sahab Card Purchasing | E60: 21320 | G60: =G59+E60-F60 -> -100111.92 | H60: ok
B61: Payment | C61: 45462 | D61: Paid To Ashfaq Sahab Card Purchasing | E61: 6000 | G61: =G60+E61-F61 -> -94111.919 | H61: ok
B62: Payment | C62: 45463 | D62: Paid To Ashfaq Sahab Card Purchasing | E62: 8350 | G62: =G61+E62-F62 -> -85761.919 | H62: ok
B63: WB.P | C63: 45463 | D63: ARY Laguna A/C (From Noman Bhai A/R To waheed Bhai) 200000PKR | E63: =200000/77 -> 2597.4026 | G63: =G62+E63-F63 -> -83164.516 | H63: ok
B64: WB.P | C64: 45463 | D64: ARY Laguna A/C (From Noman Bhai A/R To Waheed Bhai) 62,222PKR | E64: =62222/77 -> 808.07792 | G64: =G63+E64-F64 -> -82356.438 | H64: ok
B65: Payment | C65: 45469 | D65: Hamali Charges Paid by A/R | E65: 25 | G65: =G64+E65-F65 -> -82331.438 | H65: ok
B66: Payment | C66: 45471 | D66: Hamali Charges Paid by A/R | E66: 50 | G66: =G65+E66-F66 -> -82281.438 | H66: ok
B67: Payment | C67: 45471 | D67: Cargo Charges Paid by A/R | E67: 100 | G67: =G66+E67-F67 -> -82181.438 | H67: ok
B68: Payment | C68: 45472 | D68: V3 Hamali Charges Paid by A/R (ali karachi Ledger) | E68: 60 | G68: =G67+E68-F68 -> -82121.438 | H68: ok
B69: Payment | C69: 45472 | D69: V3 Clearing Charges Paid by A/R (Ali karachi Ledger) | E69: 1350 | G69: =G68+E69-F69 -> -80771.438 | H69: ok
B70: Payment | C70: 45469 | D70: Deposite Ashfaq Sahab Card | E70: 21000 | G70: =G69+E70-F70 -> -59771.438 | H70: ok
B71: Sell | C71: 45469 | D71: 26pcs Sell To Encell Shop @1580 | F71: =26*1580 -> 41080 | G71: =G70+E71-F71 -> -100851.44 | H71: ok
B72: Sell | C72: 45471 | D72: 20pcs Sell To Encell Shop @1575 | F72: 31500 | G72: =G71+E72-F72 -> -132351.44 | H72: ok
B73: WB.P | C73: 45471 | D73: Online Transaction By Waheed Bhai (AR Dubai A/C) | E73: 2726.09 | G73: =G72+E73-F73 -> -129625.35 | H73: ok
B74: WB.P | C74: 45471 | D74: Online Transaction By Waheed Bhai (AR Dubai A/C) | E74: 6895.35 | G74: =G73+E74-F74 -> -122730 | H74: ok
B75: WB.P | C75: 45471 | D75: Online Transaction By Waheed Bhai (AR Dubai A/C) | E75: 2719.57 | G75: =G74+E75-F75 -> -120010.43 | H75: ok
B76: WB.P | C76: 45471 | D76: Online ARY Laguna (Paid by A/R) 30,000/76 | E76: =30000/76 -> 394.73684 | G76: =G75+E76-F76 -> -119615.69 | H76: ok
B77: WB.P | C77: 45471 | D77: Online ARY Laguna (Paid by A/R) 97,774/76 | E77: =977774/76 -> 12865.447 | G77: =G76+E77-F77 -> -106750.24 | H77: ok
B78: WB.P | C78: 45471 | D78: Online ARY Laguna (Paid by A/R) 164,448/76 | E78: =164448/76 -> 2163.7895 | G78: =G77+E78-F78 -> -104586.45 | H78: ok
B79: Payment | C79: 45473 | D79: Deposite Ashfaq Sahab Card | E79: 10000 | G79: =G78+E79-F79 -> -94586.454 | H79: ok
B80: Payment | C80: 45473 | D80: Deposite Ashfaq Sahab Card | E80: 10000 | G80: =G79+E80-F80 -> -84586.454 | H80: ok
B81: Sell | C81: 45474 | D81: 48pcs Sell To Encell Shop @1530 | F81: =1530*48 -> 73440 | G81: =G80+E81-F81 -> -158026.45 | H81: ok
B82: Payment | C82: 45474 | D82: Deposite Ashfaq Sahab Card | E82: 73200 | G82: =G81+E82-F82 -> -84826.454 | H82: ok
B83: WB.P | C83: 45474 | D83: Online A/R Meezan A/C (Nadeem Ghani A/C waheed Bhai Payment 250,000/76) | E83: =250000/76 -> 3289.4737 | G83: =G82+E83-F83 -> -81536.981 | H83: ok
B84: WB.P | C84: 45475 | D84: Online A/R Meezan A/C (Agha M.Aftab A/C waheed Bhai Payment 40000/76) | E84: =40000/76 -> 526.31579 | G84: =G83+E84-F84 -> -81010.665 | H84: ok
B85: WB.P | C85: 45475 | D85: Online A/R Meezan A/C (Usama Bin Anees A/C waheed Bhai Payment 60000/76) | E85: =60000/76 -> 789.47368 | G85: =G84+E85-F85 -> -80221.191 | H85: ok
B86: Payment | C86: 45478 | D86: Fahib Salary M/O June-2024 (15000 PKR) | E86: =15000/76.5 -> 196.07843 | G86: =G85+E86-F86 -> -80025.113 | H86: ok
B87: WB.P | C87: 45479 | D87: Paid to Waheed Bhai (AR Card Charged) | E87: 59.38 | G87: =G86+E87-F87 -> -79965.733 | H87: ok
B88: WB.P | C88: 45479 | D88: Paid to Waheed Bhai (AR Card Charged) | E88: 10.62 | G88: =G87+E88-F88 -> -79955.113 | H88: ok
B89: WB.P | C89: 45479 | D89: Payment To Waheed Bhai (Online Amina Hameed Abbasi A/C) | E89: =14000/76 -> 184.21053 | G89: =G88+E89-F89 -> -79770.902 | H89: ok
B90: Payment | C90: 45479 | D90: Deposite Ashfaq Sahab Card | E90: 50000 | G90: =G89+E90-F90 -> -29770.902 | H90: ok
B91: Sasco | C91: 45479 | D91: Send To Australia by Sasco (Add Waheed Bhai Ledger) @2.53 | E91: 87500 | G91: =G90+E91-F91 -> 57729.098 | J91: ok
B92: WB.P | C92: 45484 | D92: Payment to Waheed bhai (Online meezan A/C) 200,000 PKR | E92: =200000/76 -> 2631.5789 | G92: =G91+E92-F92 -> 60360.677 | H92: ok
B93: Payment | C93: 45474 | D93: V3 Hamali Charges Paid by A/R (Encell Shop) | E93: 60 | G93: =G92+E93-F93 -> 60420.677 | H93: ok
B94: Payment | C94: 45474 | D94: V3 Clearing Charges Paid by A/R (Encell Shop) | E94: 1050 | G94: =G93+E94-F94 -> 61470.677 | H94: ok
B95: Payment | C95: 45471 | D95: Shipping Charges Paid (AR Card) | E95: =Total!I108 -> 6644.3152 | G95: =G94+E95-F95 -> 68114.992 | H95: ok
B96: Payment | C96: 45474 | D96: hamali | E96: 20 | G96: =G95+E96-F96 -> 68134.992 | H96: ok
B97: Sell | C97: 45474 | D97: 24pcs Sell To Encell Shop @1530 | F97: =1530*24 -> 36720 | G97: =G96+E97-F97 -> 31414.992 | H97: ok
B98: Sell | C98: 45478 | D98: 31pcs Sell To Encell Shop @1500 | F98: =31*1500 -> 46500 | G98: =G97+E98-F98 -> -15085.008 | H98: ok
B99: Sell | C99: 45482 | D99: 3pcs Sell To Encell Shop @1425 (1/2) | F99: =3*1425 -> 4275 | G99: =G98+E99-F99 -> -19360.008 | H99: ok
B100: Payment | C100: 45502 | D100: 3pcs @$359 (ARB Card) | E100: =Total!I118 -> 2627.88 | G100: =G99+E100-F100 -> -16732.128 | H100: ok
B101: Sell | C101: 45491 | D101: Sell to Encell Shop 42pcs @1220 | F101: =42*1220 -> 51240 | G101: =G100+E101-F101 -> -67972.128 | H101: ok
B102: Payment | C102: 45481 | D102: freeZone charges Paid by A/R (From Encell Shop) | E102: 1860 | G102: =G101+E102-F102 -> -66112.128 | H102: ok
...

Sheet Refund & GC
C4: Date | D4: Invoice | E4: Shipment Details | F4: Amount
B6: AR Card | C6: 45549 | D6: Ref#001 | E6: 2unit IP 16PM 256GB Returned @2147 | F6: =2147*2 -> 4294
B7: AR Card | C7: 45549 | D7: Ref#001 | E7: 1unit IP 16PM 512GB Returned @2497 | F7: =2497*1 -> 2497
B9: AB Card | C9: 45549 | D9: Ref#002 | E9: total Shipment Returned $1000 Advance | F9: 1000
B11: AB Card | C11: 45550 | D11: Ref#003 | E11: 3.unit 16PM 512Gb Returned | F11: 3500
B12: AB Card | C12: 45550 | D12: Ref#003 | E12: 3.unit 16PM 512Gb Returned | F12: 3500
B13: AB Card | C13: 45550 | D13: Ref#003 | E13: 6.unit 16PM 512Gb Returned | F13: 7491
E14: Total Refund Amount | F14: =SUM(F6:F13) -> 22282
B16: WB | C16: 45560 | E16: Refund To WB Card | F16: -7000
B18: WB | C18: 45565 | E18: Refund To WB Card | F18: -1000
C19: 45565 | E19: 2nd Gift Card | F19: -6791
E22: Balance | F22: =SUM(F14:F21) -> 7491
B32: AB Card | C32: 45550 | D32: Ref#004 | E32: 4.unit 16PM 512Gb Returned Add Gift Card | F32: =2497*4 -> 9988
E34: Gift Card Balance | F34: 9988
D36: 45558 | E36: Starlink Mini 2Unit $759 | F36: =2*759 -> 1518
D37: 45558 | E37: Starlink V4 2Unit $297 | F37: =297*2 -> 594
D38: 45558 | E38: Starlink Mini 2Unit $759 | F38: =2*759 -> 1518
D39: 45558 | E39: Starlink Mini 1Unit $299 | F39: 299
D40: 45558 | E40: Less: WB Card | F40: -361
D41: 45559 | E41: V4 1.unit Gift Card $299 | F41: 299
D42: 45559 | E42: Mini 1.unit Gift Card $796 | F42: 796
D43: 45559 | E43: V4 1.unit Gift Card $299 | F43: 299
D44: 45559 | E44: Mini 1.unit Gift Card $796 | F44: 796
D45: 45559 | E45: V4 1.unit Gift Card $299 | F45: 299
D46: 45560 | E46: V4 6Units Gift Card $299 | F46: =6*299 -> 1794
D47: 45560 | E47: Mini 1Unit Gift Card $796 | F47: 796
D48: 45563 | E48: Starlink V4 6Units Gift Card $299 | F48: =299*6 -> 1794
D49: 45563 | E49: Gift Card Purchased $250 | F49: 250
E52: Total | F52: =SUM(F36:F51) -> 10691
E54: Net Balance GC | F54: =F34-F52 -> -703
E57: 2nd Gift Card JB HiFi | F57: 6791
D60: 45565 | E60: 2unit V4 $299 | F60: =2*299 -> 598
D61: 45566 | E61: 2unit V4 $299 | F61: =2*299 -> 598
D62: 45567 | E62: 2unit V4 $299 | F62: =2*299 -> 598
D63: 45568 | E63: Starlink V4 4Unit GC Card $298 | F63: =298*4 -> 1192
D64: 45569 | E64: Starlink V4 4units Gift Card Jbhifi $299 | F64: =299*4 -> 1196
D65: 45570 | E65: Starlink V4 2units Gift Card Jbhifi $299 | F65: =299*2 -> 598
E73: Total | F73: =SUM(F59:F72) -> 4780
E75: Net Balance GC | F75: =F57-F73 -> 2011
E78: 3rd Gift Card Harvey Norman | F78: =298*15 -> 4470
C81: Online File | D81: 45567 | E81: 5Units V4 @298 | F81: =5*298 -> 1490
D82: 45567 | E82: 2Units V4 @298 | F82: =2*298 -> 596
C83: Online File | D83: 45567 | E83: 3Units V4 @298 | F83: =3*298 -> 894
E93: Total | F93: =SUM(F80:F92) -> 2980
E95: Net Balance GC | F95: =F78-F93 -> 1490
E98: 4th Gift Card 26/10/2024 Purchasing
D100: 45591 | E100: Total Gift Card Amount | F100: $6952.4

Sheet Prchasing Entry
D2: Date | E2: Shipment | F2: Details | G2: Units | H2: Card | J2: Amount | R2: AUD
N3: Purchase | O3: Send | P3: Pending | Q3: Available
E4: Ref# 1021 | F4: Last Remaining Units Mini | G4: 19 | K4: Mini | M4: Total Mini | N4: 265 | O4: 144 | P4: =5 -> 5 | Q4: =N4-O4-P4 -> 116 | R4: 93555 | S4: 2.55 | T4: =R4*S4 -> 238565.25
M5: Total V4 | N5: 450 | O5: 377 | P5: =2+2+1+1+23+2 -> 31 | Q5: =N5-O5-P5 -> 42 | R5: 12562 | S5: 2.55 | T5: =R5*S5 -> 32033.1
A6: WB Msg | C6: Received | D6: 45548 | E6: Ref# 1022 | F6: Starlink mini 10 units @799 (WB Card) | G6: 10 | H6: WB | J6: =799*10 -> 7990 | K6: Mini | Q6: 3
A8: AR Msg | C8: Received | D8: 45549 | E8: Ref# 1024 | F8: Starlink V4 3units $230 ARB Card | G8: 3 | H8: ARB | J8: =230*3 -> 690 | K8: V4
A9: AR Msg | C9: Received | D9: 45549 | E9: Ref# 1024 | F9: JB HiFi V4 3Units $230 AB Card | G9: 3 | H9: AB | J9: =230*3 -> 690 | K9: V4
A10: AR Msg | C10: Received | D10: 45549 | E10: Ref# 1024 | F10: BCF V4 6Units $297 ARB Card | G10: 6 | H10: ARB | J10: =297*6 -> 1782 | K10: V4
A11: AR Msg | C11: Received | D11: 45549 | E11: Ref# 1024 | F11: Bunnings V4 3units $298 AB Card | G11: 3 | H11: AB | J11: =298*3 -> 894 | K11: V4
A12: AR Msg | C12: PD | D12: 45549 | E12: Ref# 1024 | F12: BCF V4 10Units $297 ARB Card | G12: 10 | H12: ARB | J12: =297*10 -> 2970 | K12: V4
A13: AR Msg | C13: Received | D13: 45549 | E13: Ref# 1024 | F13: OfficeWorks 1Unit $297 ARB Card | G13: 1 | H13: ARB | J13: 297 | K13: V4
A14: AR Msg | C14: Received | D14: 45549 | E14: Ref# 1024 | F14: Starlink V4 2Units $298 AB Card | G14: 2 | H14: AB | J14: =298*2 -> 596 | K14: V4
A15: AR Msg | C15: Received | D15: 45549 | E15: Ref# 1024 | F15: OfficeWorks 1Unit $297 WB Card | G15: 1 | H15: WB | J15: 297 | K15: V4
A16: AR Msg | C16: Received | D16: 45549 | E16: Ref# 1024 | F16: Starlink V4 1Unit $298 WB Card | G16: 1 | H16: WB | J16: 298 | K16: V4
A17: AR Msg | C17: Received | D17: 45549 | E17: Ref# 1024 | F17: Bunnings V4 1unit $298 WB Card | G17: 1 | H17: WB | J17: 298 | K17: V4
A18: AR Msg | C18: Received | D18: 45549 | E18: Ref# 1024 | F18: Starlink V4 3Units $230 WB Card | G18: 3 | H18: WB | J18: =230*3 -> 690 | K18: V4
A20: WB Msg | C20: Received | D20: 45550 | E20: Ref# 1025 | F20: Starlink V4 AB Card 8units $299 | G20: 8 | H20: AB | J20: =8*299 -> 2392 | K20: V4
A21: WB Msg | C21: Received | D21: 45550 | E21: Ref# 1025 | F21: Starlink V4 AB Card 9units $298 | G21: 9 | H21: AB | J21: =9*298 -> 2682 | K21: V4
A22: WB Msg | C22: Received | D22: 45550 | E22: Ref# 1025 | F22: Starlink V4 WB Card 8units $298 | G22: 8 | H22: WB | J22: =8*298 -> 2384 | K22: V4
A23: WB Msg | C23: Received | D23: 45550 | E23: Ref# 1025 | F23: Starlink V4 WB Card 3units $299 | G23: 3 | H23: WB | J23: =3*299 -> 897 | K23: V4
A24: WB Msg | C24: Received | D24: 45550 | E24: Ref# 1025 | F24: Starlink V4 WB Card 4unit $297 | G24: 4 | H24: WB | J24: =4*297 -> 1188 | K24: V4
A25: WB Msg | C25: Received | D25: 45550 | E25: Ref# 1025 | F25: Starlink V4 WB Card 5units $298 | G25: 5 | H25: WB | J25: =5*298 -> 1490 | K25: V4
A27: WB Msg | C27: Received | D27: 45551 | E27: Ref# 1026 | F27: Starlink AB Card 6units $299 | G27: 6 | H27: AB | J27: =299*6 -> 1794 | K27: V4
A28: WB Msg | C28: Received | D28: 45551 | E28: Ref# 1026 | F28: Starlink AB Card 12units $298 | G28: 12 | H28: AB | J28: =298*12 -> 3576 | K28: V4
A29: WB Msg | C29: Received | D29: 45551 | E29: Ref# 1026 | F29: Starlink AB Card 5units $297 | G29: 5 | H29: AB | J29: =297*5 -> 1485 | K29: V4
A30: WB Msg | C30: Received | D30: 45551 | E30: Ref# 1026 | F30: Starlink WB Card 7units $297 | G30: 7 | H30: WB | J30: =297*7 -> 2079 | K30: V4
A31: WB Msg | C31: Received | D31: 45551 | E31: Ref# 1026 | F31: Starlink WB Card 2units $299 | G31: 2 | H31: WB | J31: =299*2 -> 598 | K31: V4
A32: WB Msg | C32: P.D | D32: 45551 | E32: Ref# 1026 | F32: Starlink Mini AB Card 2units $759 +$6 | G32: 2 | H32: AB | J32: =765*2 -> 1530 | K32: Mini
A33: WB Msg | C33: P.D | D33: 45551 | E33: Ref# 1026 | F33: Starlink Mini WB Card 2units $798 | G33: 2 | H33: WB | J33: =798*2 -> 1596 | K33: Mini
A35: WB Msg | C35: Received | D35: 45552 | E35: Ref# 1027 | F35: Starlink V4 AB Card 7units $299 | G35: 7 | H35: AB | J35: =299*7 -> 2093 | K35: V4
A36: WB Msg | C36: PD | D36: 45552 | E36: Ref# 1027 | F36: Starlink V4 WB Card 1unit $298 | G36: 1 | H36: WB | J36: =298*1 -> 298 | K36: V4
A37: WB Msg | C37: Received | D37: 45552 | E37: Ref# 1027 | F37: Starlink V4 WB Card 1unit $312 | G37: 1 | H37: WB | J37: =1*312 -> 312 | K37: V4
A38: WB Msg | C38: Received | D38: 45552 | E38: Ref# 1027 | F38: Starlink V4 WB Card 3unit $297 | G38: 3 | H38: WB | J38: =297*3 -> 891 | K38: V4
A39: WB Msg | C39: PD 1unit | D39: 45552 | E39: Ref# 1027 | F39: Starlink V4 ARB Card 2unit $298 | G39: 2 | H39: ARB | J39: =298*2 -> 596 | K39: V4
A41: WB Msg | C41: Received | D41: 45553 | E41: Ref# 1028 | F41: Starlink V4 AB Card 9units $298 | G41: 9 | H41: AB | J41: =298*9 -> 2682 | K41: V4
A42: WB Msg | C42: Received | D42: 45553 | E42: Ref# 1028 | F42: Starlink V4 WB Card 51units $298 | G42: 51 | H42: WB | J42: =298*51 -> 15198 | K42: V4
A43: WB Msg | C43: Received | D43: 45553 | E43: Ref# 1028 | F43: Starlink Mini WB Card 10units $755 | G43: 10 | H43: WB | J43: =755*10 -> 7550 | K43: Mini
A44: WB Msg | C44: Received | D44: 45553 | E44: Ref# 1028 | F44: Starlink Mini WB Card 54units $790 | G44: 54 | H44: WB | J44: =790*54 -> 42660 | K44: Mini
A45: AR Msg | C45: Received | D45: 45553 | E45: Ref# 1028 | F45: Starlink V4 ARB Card 1unit $297 | G45: 1 | H45: ARB | J45: =297*1 -> 297 | K45: V4
A46: AR Msg | C46: Received | D46: 45553 | E46: Ref# 1028 | F46: Starlink V4 ARB Card 1unit $298 | G46: 1 | H46: ARB | J46: 298 | K46: V4
A48: WB Msg | C48: Received | D48: 45554 | E48: Ref# 1029 | F48: Starlink V4 WB Card 2units $299 | G48: 2 | H48: WB | J48: =299*2 -> 598 | K48: V4
A49: WB Msg | C49: Received | D49: 45554 | E49: Ref# 1029 | F49: Starlink V4 ARB Card 1unit $299 | G49: 1 | H49: ARB | J49: 299 | K49: V4
A50: WB Msg | C50: Received | D50: 45554 | E50: Ref# 1029 | F50: Starlink V4 WB Card 1unit $297 | G50: 1 | H50: WB | J50: 297 | K50: V4
A51: WB Msg | C51: Received | D51: 45554 | E51: Ref# 1029 | F51: Starlink V4 ARB Card 1unit $297 | G51: 1 | H51: ARB | J51: 297 | K51: V4
A52: WB Msg | C52: PD | D52: 45554 | E52: Ref# 1029 | F52: Starlink Mini WB Card 7Units $790 | G52: 7 | H52: WB | J52: =7*790 -> 5530 | K52: Mini
A54: WB Msg | C54: Received | D54: 45556 | E54: Ref# 1030 | F54: Starlink Mini 30 Units $799 | G54: 30 | H54: ARB/WB | J54: =30*799 -> 23970 | K54: Mini | M54: DIB Bank
A56: WB Msg | C56: Received | D56: 45558 | E56: Ref# 1031 | F56: V4 3units ARB Card $297 | G56: 3 | H56: ARB | J56: =297*3 -> 891 | K56: V4
A57: WB Msg | C57: Received | D57: 45558 | E57: Ref# 1031 | F57: V4 1units ARB Card $298 | G57: 1 | H57: ARB | J57: 298 | K57: V4
A58: WB Msg | C58: Received | D58: 45558 | E58: Ref# 1031 | F58: Mini 2 Units Gift Card $759 | G58: 2 | H58: GC | J58: =759*2 -> 1518 | K58: Mini
A59: WB Msg | C59: PD | D59: 45558 | E59: Ref# 1031 | F59: Mini 2 Units Gift Card $759 ($361 WB Card) | G59: 2 | H59: GC | J59: =759*2 -> 1518 | K59: Mini
A60: WB Msg | C60: Received | D60: 45558 | E60: Ref# 1031 | F60: V4 2units Gift Card $297 | G60: 2 | H60: GC | J60: =297*2 -> 594 | K60: V4
A61: WB Msg | C61: Received | D61: 45558 | E61: Ref# 1031 | F61: V4 1units Gift Card $299 | G61: 1 | H61: GC | J61: 299 | K61: V4
A62: WB Msg | C62: Received | D62: 45558 | E62: Ref# 1031 | F62: V4 5Units WB Card $298 | G62: 5 | H62: WB | J62: =298*5 -> 1490 | K62: V4
A63: WB Msg | C63: Received | D63: 45558 | E63: Ref# 1031 | F63: V4 3Units WB Card $297 | G63: 3 | H63: WB | J63: =297*3 -> 891 | K63: V4
A64: WB Msg | C64: Received | D64: 45558 | E64: Ref# 1031 | F64: Mini 1Unit WB Card $745 | G64: 1 | H64: WB | J64: 745 | K64: Mini
A66: WB Msg | C66: Received | D66: 45559 | E66: Ref# 1032 | F66: V4 1.unit WB Card $299 | G66: 1 | H66: WB | J66: 299 | K66: V4
A67: WB Msg | C67: Received | D67: 45559 | E67: Ref# 1032 | F67: V4 1.unit Gift Card $299 | G67: 1 | H67: GC | J67: 299 | K67: V4
A68: WB Msg | C68: Received | D68: 45559 | E68: Ref# 1032 | F68: Mini 1.unit Gift Card $796 | G68: 1 | H68: GC | J68: 796 | K68: Mini
A69: WB Msg | C69: Received | D69: 45559 | E69: Ref# 1032 | F69: V4 1.unit Gift Card $299 | G69: 1 | H69: GC | J69: 299 | K69: V4
A70: WB Msg | C70: Received | D70: 45559 | E70: Ref# 1032 | F70: Mini 1.unit Gift Card $796 | G70: 1 | H70: GC | J70: 796 | K70: Mini
A71: WB Msg | C71: Received | D71: 45559 | E71: Ref# 1032 | F71: V4 5.units WB Card $298 | G71: 5 | H71: WB | J71: =298*5 -> 1490 | K71: V4
A72: WB Msg | C72: Received | D72: 45559 | E72: Ref# 1032 | F72: V4 1.unit Gift Card $299 | G72: 1 | H72: GC | J72: 299 | K72: V4
A73: WB Msg | C73: PD | D73: 45559 | E73: Ref# 1032 | F73: Mini 10.unit WB Card $758 | G73: 10 | H73: WB | J73: =758*10 -> 7580 | K73: Mini
A74: WB Msg | C74: PD | D74: 45559 | E74: Ref# 1032 | F74: Mini 10.unit WB Card $750 ($2060 Balance amount) | G74: 10 | H74: WB | J74: =750*10 -> 7500 | K74: Mini
A75: WB Msg | C75: Received | D75: 45559 | E75: Ref# 1032 | F75: V4 10.units WB Card $298 | G75: 10 | H75: WB | J75: =298*10 -> 2980 | K75: V4
A77: WB Msg | C77: Received | D77: 45560 | E77: Ref# 1033 | F77: V4 2Units WB Card $297 | G77: 2 | H77: WB | J77: =2*297 -> 594 | K77: V4
A78: WB Msg | C78: Received | D78: 45560 | E78: Ref# 1033 | F78: V4 6Units Gift Card $299 | G78: 6 | H78: GC | J78: =6*299 -> 1794 | K78: V4
A79: WB Msg | C79: Received | D79: 45560 | E79: Ref# 1033 | F79: Mini 1Unit Gift Card $796 | G79: 1 | H79: GC | J79: 796 | K79: Mini
A80: AR Msg | C80: Received | D80: 45560 | E80: Ref# 1033 | F80: V4 1Unit ARB Card $318 | G80: 1 | H80: ARB | J80: 318 | K80: V4
A81: AR Msg | C81: Received | D81: 45560 | E81: Ref# 1033 | F81: V4 1Unit ARB Card $309 | G81: 1 | H81: ARB | J81: 309 | K81: V4
A82: AR Msg | C82: Received | D82: 45560 | E82: Ref# 1033 | F82: V4 1Unit ARB Card $309 | G82: 1 | H82: ARB | J82: 309 | K82: V4
A83: AR Msg | C83: Received | D83: 45560 | E83: Ref# 1033 | F83: V4 1Unit ARB Card $307 | G83: 1 | H83: ARB | J83: 307 | K83: V4
A85: WB Msg | C85: PD | D85: 45561 | E85: Ref# 1034 | F85: V4 3Units WB Card $297 | G85: 3 | H85: WB | J85: =3*297 -> 891 | K85: V4
A86: WB Msg | C86: PD | D86: 45561 | E86: Ref# 1034 | F86: V4 1Unit WB Card $298 | G86: 1 | H86: WB | J86: 298 | K86: V4
A87: WB Msg | C87: PD | D87: 45561 | E87: Ref# 1034 | F87: V4 1Unit WB Card $307 | G87: 1 | H87: WB | J87: 307 | K87: V4
A88: AR Msg | C88: PD | D88: 45561 | E88: Ref# 1034 | F88: V4 1Unit ARB Card $307 | G88: 1 | H88: ARB | J88: 307 | K88: V4
A90: Online File | C90: PD | D90: 45562 | E90: Ref# 1035 | F90: Starlink V4 3Units WB Card $297 | G90: 3 | H90: WB | J90: =3*297 -> 891 | K90: V4
A91: WB Msg | C91: PD | D91: 45563 | E91: Ref# 1035 | F91: Starlink V4 6Units Gift Card $299 | G91: 6 | H91: GC | J91: =6*299 -> 1794 | K91: V4
A92: WB Msg | C92: PD | D92: 45563 | E92: Ref# 1035 | F92: Starlink V4 5Units WB Card $297 | G92: 5 | H92: WB | J92: =5*297 -> 1485 | K92: V4
A94: AR Msg | C94: PD | D94: 45563 | E94: Ref# 1036 | F94: Starlink V4 100 Units $298 | G94: 100 | H94: WB | J94: =298*100 -> 29800 | K94: V4
A96: WB Msg | D96: 45563 | E96: Ref# 1037 | F96: Starlink V4 9units WB Card $297 | G96: 9 | H96: WB | J96: =297*9 -> 2673 | K96: V4
A97: WB Msg | D97: 45563 | E97: Ref# 1037 | F97: Starlink V4 1units ARB Card $297 | G97: 1 | H97: ARB | J97: 297 | K97: V4
A98: WB Msg | D98: 45563 | E98: Ref# 1037 | F98: Starlink V4 2units WB Card $298 | G98: 2 | H98: WB | J98: =298*2 -> 596 | K98: V4
A99: WB Msg | D99: 45563 | E99: Ref# 1037 | F99: Starlink V4 4units WB Card $297 | G99: 4 | H99: WB | J99: =297*2 -> 594 | K99: V4
A100: Online File | D100: 45563 | E100: Ref# 1037 | F100: Starlink V4 1units WB Card $297 | G100: 1 | H100: WB | J100: 297 | K100: V4
A103: AR Msg | D103: 45565 | E103: Ref# 1039 | F103: DJI Mavic 3Pro 2Unit WB Card $2550 | G103: 2 | H103: WB | J103: =2550*2 -> 5100 | K103: DJI
A104: AR Msg | D104: 45565 | E104: Ref# 1039 | F104: Harvey V4 1Unit WB Card $298 | G104: 1 | H104: WB | J104: 298 | K104: V4
A105: AR Msg | D105: 45565 | E105: Ref# 1039 | F105: Harvey V4 1Unit WB Card $298 | G105: 1 | H105: WB | J105: 298 | K105: V4
A106: AR Msg | D106: 45565 | E106: Ref# 1039 | F106: JB Hifi V4 1unit ARB Card $299 | G106: 1 | H106: ARB | J106: 299 | K106: V4
A107: AR Msg | D107: 45565 | E107: Ref# 1039 | F107: JB Hifi V4 1unit WB Card $299 | G107: 1 | H107: WB | J107: 299 | K107: V4
A108: AR Msg | D108: 45565 | E108: Ref# 1039 | F108: JB Hifi V4 2unit WB Card $299 | G108: 2 | H108: WB | J108: =299*2 -> 598 | K108: V4
A109: AR Msg | D109: 45565 | E109: Ref# 1039 | F109: JB Hifi V4 1unit WB Card $299 | G109: 1 | H109: WB | J109: 299 | K109: V4
A110: AR Msg | D110: 45565 | E110: Ref# 1039 | F110: JB Hifi V4 1unit ARB Card $299 | G110: 1 | H110: ARB | J110: 299 | K110: V4
A111: AR Msg | D111: 45565 | E111: Ref# 1039 | F111: JB Hifi V4 3unit WB Card $299 | G111: 3 | H111: WB | J111: =299*3 -> 897 | K111: V4
A112: AR Msg | D112: 45565 | E112: Ref# 1039 | F112: JB Hifi V4 2unit Gift Card $299 | G112: 2 | H112: GC | J112: =299*2 -> 598 | K112: V4
A113: AR Msg | D113: 45565 | E113: Ref# 1039 | F113: Officeworks 1unit ARB Card $298 | G113: 1 | H113: ARB | J113: 298 | K113: V4
A114: AR Msg | D114: 45565 | E114: Ref# 1039 | F114: Bunnings 1unit ARB Card $297 | G114: 1 | H114: ARB | J114: 297 | K114: V4
A116: WB Msg | D116: 45566 | E116: Ref# 1041 | F116: Starlink Mini 12 Units $750 WB Card | G116: 12 | H116: WB | J116: =12*750 -> 9000 | K116: Mini
A117: WB Msg | D117: 45566 | E117: Ref# 1041 | F117: Starlink V4 2Units $299 GC Card | G117: 2 | H117: GC | J117: =299*2 -> 598 | K117: V4
A119: WB Msg | D119: 45567 | E119: Ref# 1042 | F119: Starlink V4 2Units GC Card JBhifi $299 | G119: 2 | H119: GC | J119: =2*299 -> 598 | K119: V4
...

Sheet Sell Sheet
C2: DATE | E2: Details | F2: Units | G2: Rate | H2: Amount
C3: 45562 | E3: Sell v4 50units | F3: 50 | G3: 1170 | H3: =F3*G3 -> 58500
C4: 45562 | E4: Sell Mini 1Unit | F4: 1 | G4: 2250 | H4: =F4*G4 -> 2250
C5: 45562 | E5: Sell Mini 50 Units | F5: 50 | G5: 2230 | H5: =F5*G5 -> 111500
C6: 45562 | E6: Sell v4 30units | F6: 30 | G6: 1175 | H6: =F6*G6 -> 35250
C8: 45566 | E8: Sell Mini 33units | F8: 33 | G8: 2200 | H8: =F8*G8 -> 72600
C9: 45566 | E9: Sell v4 44units | F9: 44 | G9: 1180 | H9: =F9*G9 -> 51920
C10: 45566 | E10: Sell v4 40units | F10: 40 | G10: 1180 | H10: =F10*G10 -> 47200
C12: 45576 | E12: Starlink V4 Sell By Faisal Bhai | F12: 104 | G12: 1230 | H12: =F12*G12 -> 127920
C13: 45576 | E13: Starlink V4 Sell By Faisal Bhai | F13: 109 | G13: 1235 | H13: =F13*G13 -> 134615
C14: 45576 | E14: Starlink Mini Sell By Faisal Bhai | F14: 5 | G14: 2200 | H14: =F14*G14 -> 11000
C15: 45576 | E15: Starlink Mini Sell By Faisal Bhai | F15: 10 | G15: 2180 | H15: =F15*G15 -> 21800
C16: 45576 | E16: Starlink Mini Sell By Faisal Bhai | F16: 2 | G16: 2140 | H16: =F16*G16 -> 4280
... C20: 45576 | E20: Starlink Mini Sell By Faisal Bhai | F20: 15 | G20: 2200 | H20: =F20*G20 -> 33000
E54: Total Sell | F54: =SUM(F3:F53) -> 521
C57: Date | E57: Details | F57: Rate | G57: Units | H57: Total
C58: 45474 | E58: Starlink V3 Sell to Encell Shop | F58: 1530 | G58: 48 | H58: =F58*G58 -> 73440
C59: 45474 | E59: Starlink V3 Sell to Encell Shop | F59: 1530 | G59: 24 | H59: =F59*G59 -> 36720
C60: 45478 | E60: Starlink V3 Sell to Encell Shop | F60: 1500 | G60: 31 | H60: =F60*G60 -> 46500
C61: 45482 | E61: Starlink V3 Sell to Encell Shop | F61: 1425 | G61: 23 | H61: =F61*G61 -> 32775
C62: 45482 | E62: Starlink V3 Sell to Encell Shop | F62: 1470 | G62: 5 | H62: =F62*G62 -> 7350
C63: 45484 | E63: Starlink V3 Sell to Encell Shop | F63: 1425 | G63: 10 | H63: =F63*G63 -> 14250
C64: 45484 | E64: Starlink V3 Sell to Encell Shop | F64: 1370 | G64: 20 | H64: =F64*G64 -> 27400
C65: 45484 | E65: Starlink V3 Sell to Encell Shop | F65: 1390 | G65: 37 | H65: =F65*G65 -> 51430
C66: 45491 | E66: Starlink V3 Sell to Encell Shop | F66: 1240 | G66: 30 | H66: =F66*G66 -> 37200
C67: 45491 | E67: Starlink V3 Sell to Encell Shop | F67: 1230 | G67: 22 | H67: =F67*G67 -> 27060
C68: 45491 | E68: Starlink V3 Sell to Encell Shop | F68: 1220 | G68: 43 | H68: =F68*G68 -> 52460
C69: 45497 | E69: Starlink V3 Sell to Encell Shop | F69: 1180 | G69: 8 | H69: =F69*G69 -> 9440
... C93: 45553 | E93: Starlink V4 Sell By Rabi | F93: 1170 | G93: 10 | H93: =F93*G93 -> 11700
C94: 45553 | E94: Starlink V4 Sell By Rabi | F94: 1170 | G94: 5 | H94: =F94*G94 -> 5850 | K94: Starlink Mini | L94: 74 Units
C95: 45562 | E95: Starlink V4 Sell By Faisal Bhai | F95: 1170 | G95: 50 | H95: =F95*G95 -> 58500 | K95: Starlink V4 | L95: 1,272 Units
C96: 45562 | E96: Starlink Mini Sell By Faisal Bhai | F96: 2250 | G96: 1 | H96: =F96*G96 -> 2250
C97: 45562 | E97: Starlink Mini Sell By Faisal Bhai | F97: 2230 | G97: 50 | H97: =F97*G97 -> 111500
C98: 45562 | E98: Starlink V4 Sell By Faisal Bhai | F98: 1175 | G98: 30 | H98: =F98*G98 -> 35250
G100: =SUM(G58:G99) -> 1346 | H100: =SUM(H58:H99) -> 1726535

Sheet AB CArd
A4: AB | C4: 45423 | D4: Ref#1003V3 | E4: Purchasing | F4: 46Units Purchase Ashfaq Sahab Card | G4: 24013.84 | H4: 2.42 | I4: =G4*H4 -> 58113.493 | K4: =K3+I4-J4 -> 58113.493 | M4: 46
A5: AB | C5: 45423 | D5: Ref#1003V3 | E5: Purchasing | F5: Card Payment Ashfaq Sahab | G5: 18944 | H5: 2.42 | I5: =G5*H5 -> 45844.48 | K5: =K4+I5-J5 -> 103957.97 | M5: 36
A6: AB | C6: 45468 | D6: Ref# 1007 V3 | E6: Purchasing | F6: Ashfaq Shab Card 57.5 Units @474 | G6: =57.5*474 -> 27255 | H6: 2.44 | I6: =G6*H6 -> 66502.2 | K6: =K5+I6-J6 -> 170460.17
A7: AB | C7: 45468 | D7: Ref# 1007 V3 | E7: Purchasing | F7: Ashfaq Shab Card 24 Units @474 | G7: =24*474 -> 11376 | H7: 2.44 | I7: =G7*H7 -> 27757.44 | K7: =K6+I7-J7 -> 198217.61
A8: AB/WB | C8: 45473 | D8: Ref# 1008 V3 | E8: Purchasing | F8: Petrol Expense (Ab + WB Card) | G8: 165 | H8: 2.44 | I8: =G8*H8 -> 402.6 | K8: =K7+I8-J8 -> 198620.21
A9: AB | C9: 45473 | D9: Ref# 1008 V3 | E9: Purchasing | F9: 4pcs Harvey Norman $500 | G9: =4*500 -> 2000 | H9: 2.44 | I9: =G9*H9 -> 4880 | K9: =K8+I9-J9 -> 203500.21
A10: AB | C10: 45473 | D10: Ref# 1008 V3 | E10: Purchasing | F10: 3 JB hi fi $500 | G10: =3*500 -> 1500 | H10: 2.44 | I10: =G10*H10 -> 3660 | K10: =K9+I10-J10 -> 207160.21
A11: AB | C11: 45473 | D11: Ref# 1008 V3 | E11: Purchasing | F11: 3 JB Hi fi $522 | G11: =3*522 -> 1566 | H11: 2.44 | I11: =G11*H11 -> 3821.04 | K11: =K10+I11-J11 -> 210981.25
A12: AB | C12: 45473 | D12: Ref# 1008 V3 | E12: Purchasing | F12: 1 JB Hi fi $522 (Pending ) | G12: 522 | H12: 2.44 | I12: =G12*H12 -> 1273.68 | K12: =K11+I12-J12 -> 212254.93
A13: AB | C13: 45473 | D13: Ref# 1008 V3 | E13: Purchasing | F13: 46 Bunnings $522 | G13: =46*522 -> 24012 | H13: 2.44 | I13: =G13*H13 -> 58589.28 | K13: =K12+I13-J13 -> 270844.21
A14: Refund | C14: 45473 | D14: Ref# 1008 V3 | E14: Purchasing | F14: Refundable Amount 46 Pcs @75 | G14: =46*75 -> 3450 | H14: 2.44 | I14: =G14*H14 -> 8418 | K14: =K13+I14-J14 -> 279262.21
A15: WB/AB | C15: 45502 | D15: Ref# 1009 V3 | E15: Purchasing | F15: 28pcs @$359 (1960 WB + 8092 AB) | G15: =28*350 -> 9800 | H15: 2.44 | I15: =G15*H15 -> 23912 | K15: =K14+I15-J15 -> 303174.21
A16: AB | C16: 45488 | D16: Ref# 1009 V3 | E16: Purchasing | F16: 11pcs Purchased (AB Card) @831.21 Aed | I16: =831.21*11 -> 9143.31 | K16: =K15+I16-J16 -> 312317.52
A17: AB | C17: 45477 | D17: Ref# 1010 V3 | E17: Purchasing | F17: Ticket Charges (Ashfaq Sahab Card ) | G17: 773 | H17: 2.44 | I17: =G17*H17 -> 1886.12 | K17: =K16+I17-J17 -> 314203.64
A18: AB | C18: 45477 | D18: Ref# 1010 V3 | E18: Purchasing | F18: Shipping Charges + Surcharge (Ashfaq Sahab Card) | G18: 5100 | H18: 2.44 | I18: =G18*H18 -> 12444 | K18: =K17+I18-J18 -> 326647.64
A19: WB/AB | C19: 45477 | D19: Ref# 1010 V3 | E19: Purchasing | F19: 92 pcs Purchased $359 (32078 Ashfaq Sahab Card / $290+$710 Waheed Bhai Card) | G19: =359*92 -> 33028 | H19: 2.44 | I19: =G19*H19 -> 80588.32 | K19: =K18+I19-J19 -> 407235.96
C20: 45491 | D20: Ref# 1012 V3 | E20: Purchasing | F20: 49units purchased @357 AB | G20: =357*49 -> 17493 | H20: 2.525 | I20: =G20*H20 -> 44169.825 | K20: =K19+I20-J20 -> 451405.79
C21: 45497 | D21: Ref# 1015 V3 | E21: Purchasing | F21: 74units @357 AB | G21: =357*74 -> 26418 | H21: 2.52 | I21: =G21*H21 -> 66573.36 | K21: =K20+I21-J21 -> 517979.15
C22: 45502 | D22: Ref# 1017 V3 | E22: Purchasing | F22: Sydney 6units AB Card @358 | G22: =358*6 -> 2148 | H22: 2.52 | I22: =G22*H22 -> 5412.96 | K22: =K21+I22-J22 -> 523392.11
I24: =SUM(I4:I23) -> 523392.11
I26: -4882.38
I27: -4676.61
I28: -4676.61
I29: -1408.31
I30: -5101.73
I31: =SUM(I24:I30) -> 502646.47
I34: 513906.11 | J34: =I34-I31 -> 11259.642
D38: Date | E38: Shipment | F38: Details | G38: Sell | H38: Cash Payment | I38: Balance
D40: 45420 | E40: Ref#1001V2 | F40: Sell By A/R V2 20pcs @1450 | G40: =20*1450 -> 29000 | I40: =I39+G40-H40 -> 29000 | J40: ok
D41: 45427 | E41: Ref#1002 V2 | F41: V2 Sold AMGT 5pcs @1190 (09/05/2024) | G41: =5*1190 -> 5950 | I41: =I40+G41-H41 -> 34950 | J41: ok
D42: 45428 | E42: Ref#1002 V2 | F42: Sold To A/R 2pcs @1000 | G42: =2*1000 -> 2000 | I42: =I41+G42-H42 -> 36950 | J42: ok
D43: 45419 | E43: Ref#1003V3 | F43: Sold to Encell Shop 20pcs @1790 | G43: =1790*20 -> 35800 | I43: =I42+G43-H43 -> 72750 | J43: ok
D44: 45420 | E44: Ref#1003V3 | F44: Sell to AMGT V3 09pcs @1800 | G44: =9*1800 -> 16200 | I44: =I43+G44-H44 -> 88950 | J44: ok
D45: 45420 | E45: Ref#1003V3 | F45: Sold to Encell Shop 10pcs @1800 | G45: =10*1800 -> 18000 | I45: =I44+G45-H45 -> 106950 | J45: ok
D46: 45427 | E46: Ref#1003V3 | F46: Sold To AMGT V3 2pcs @1800 (09/05/2024) | G46: =2*1800 -> 3600 | I46: =I45+G46-H46 -> 110550 | J46: ok
D47: 45427 | E47: Ref#1003V3 | F47: Sold To AMGT V3 2pcs @1750 (09/05/2024) | G47: =2*1750 -> 3500 | I47: =I46+G47-H47 -> 114050 | J47: ok
D48: 45427 | E48: Ref#1003V3 | F48: Sold To AMGT V3 5pcs @1740 (13/05/2024) | G48: =5*1740 -> 8700 | I48: =I47+G48-H48 -> 122750 | J48: ok
D49: 45427 | E49: Ref#1003V3 | F49: Sold To AMGT V3 16pcs @1650 (13/05/2024) | G49: =16*1650 -> 26400 | I49: =I48+G49-H49 -> 149150 | J49: ok
D50: 45427 | E50: Ref#1003V3 | F50: Sold to Encell Shop 26pcs @1750 | G50: =26*1750 -> 45500 | I50: =I49+G50-H50 -> 194650 | J50: ok
D51: 45427 | E51: Ref#1003V3 | F51: Sold to Encell Shop 5pcs @1700 | G51: =5*1700 -> 8500 | I51: =I50+G51-H51 -> 203150 | J51: ok
D52: 45427 | E52: Ref#1003V3 | F52: Sold To AMGT V3 1pcs @1700 (15/05/2024) | G52: =1*1700 -> 1700 | I52: =I51+G52-H52 -> 204850 | J52: ok
D53: 45427 | E53: Ref#1003V3 | F53: Sold To AMGT V3 10pcs @1695 (15/05/2024) | G53: =10*1695 -> 16950 | I53: =I52+G53-H53 -> 221800 | J53: ok
D54: 45442 | E54: V3 35pcs | F54: Sell Encell Shop 2pcs | G54: 3240 | I54: =I53+G54-H54 -> 225040 | J54: ok
D55: 45442 | E55: V3 35pcs | F55: Sell Encell Shop 18pcs | G55: 29520 | I55: =I54+G55-H55 -> 254560 | J55: ok
D56: 45442 | E56: V3 35pcs | F56: Sell AMGT Office 15pcs | G56: 24300 | I56: =I55+G56-H56 -> 278860 | J56: ok
D57: 45448 | E57: V3 60pcs | F57: Sell Encell Shop 20pcs | G57: =1680*20 -> 33600 | I57: =I56+G57-H57 -> 312460 | J57: ok
D58: 45449 | E58: V3 60pcs | F58: Sell Encell Shop 30pcs | G58: =1680*30 -> 50400 | I58: =I57+G58-H58 -> 362860 | J58: ok
D59: 45453 | E59: V3 60pcs | F59: Sell AMGT 2pcs | G59: 3400 | I59: =I58+G59-H59 -> 366260 | J59: ok
D60: 45455 | E60: V3 60pcs | F60: Sell Encell Shop 2pcs | G60: =1670*2 -> 3340 | I60: =I59+G60-H60 -> 369600 | J60: ok
D61: 45456 | E61: V3 60pcs | F61: Sell to AMGT 6pcs | G61: 9990 | I61: =I60+G61-H61 -> 379590 | J61: ok
D62: 45453 | E62: V3 47pcs | F62: Sell Encell Shop 35pcs | G62: 58800 | I62: =I61+G62-H62 -> 438390 | J62: ok
D63: 45456 | E63: V3 47pcs | F63: Sell To AMGT 7pcs | G63: 11655 | I63: =I62+G63-H63 -> 450045 | J63: ok
D64: 45456 | E64: V3 47pcs | F64: Sell Encell Shop 5pcs | G64: 8350 | I64: =I63+G64-H64 -> 458395 | J64: ok
D65: 45469 | E65: Ref# 1007 V3 | F65: 26pcs Sell To Encell Shop @1580 | G65: =26*1580 -> 41080 | I65: =I64+G65-H65 -> 499475 | J65: ok
D66: 45471 | E66: Ref# 1007 V3 | F66: 20pcs Sell To Encell Shop @1575 | G66: 31500 | I66: =I65+G66-H66 -> 530975 | J66: ok
D67: 45474 | E67: Ref# 1007 V3 | F67: 48pcs Sell To Encell Shop @1530 | G67: =1530*48 -> 73440 | I67: =I66+G67-H67 -> 604415 | J67: ok
D68: 45474 | E68: Ref# 1008 V3 | F68: 24pcs Sell To Encell Shop @1530 | G68: =1530*24 -> 36720 | I68: =I67+G68-H68 -> 641135 | J68: ok
D69: 45478 | E69: Ref# 1008 V3 | F69: 31pcs Sell To Encell Shop @1500 | G69: =31*1500 -> 46500 | I69: =I68+G69-H69 -> 687635 | J69: ok
D70: 45482 | E70: Ref# 1008 V3 | F70: 3pcs Sell To Encell Shop @1425 (1/2) | G70: =3*1425 -> 4275 | I70: =I69+G70-H70 -> 691910 | J70: ok
D71: 45491 | E71: Ref# 1009 V3 | F71: Sell to Encell Shop 42pcs @1220 | G71: =42*1220 -> 51240 | I71: =I70+G71-H71 -> 743150 | J71: ok
D72: 45482 | E72: Ref# 1010 V3 | F72: 20pcs Sell To Encell Shop @1425 (2/2) | G72: =1425*20 -> 28500 | I72: =I71+G72-H72 -> 771650 | J72: ok
D73: 45482 | E73: Ref# 1010 V3 | F73: 5pcs Sell To Encell Shop @1470 | G73: =5*1470 -> 7350 | I73: =I72+G73-H73 -> 779000 | J73: ok
D74: 45484 | E74: Ref# 1010 V3 | F74: 10pcs Sell To Encell Shop @1425 | G74: =10*1425 -> 14250 | I74: =I73+G74-H74 -> 793250 | J74: ok
D75: 45484 | E75: Ref# 1010 V3 | F75: 20pcs Sell To Encell Shop @1370 | G75: =1370*20 -> 27400 | I75: =I74+G75-H75 -> 820650 | J75: ok
D76: 45484 | E76: Ref# 1010 V3 | F76: 37pcs Sell To Encell Shop @1390 | G76: =37*1390 -> 51430 | I76: =I75+G76-H76 -> 872080 | J76: ok
D77: 45491 | E77: Ref# 1011 V3 | F77: Sell to Encell Shop 1pcs @1220 | G77: =1*1220 -> 1220 | I77: =I76+G77-H77 -> 873300 | J77: ok
D78: 45491 | E78: Ref# 1011 V3 | F78: Sell to Encell Shop 30pcs @1240 | G78: =30*1240 -> 37200 | I78: =I77+G78-H78 -> 910500 | J78: ok
D79: 45491 | E79: Ref# 1011 V3 | F79: Sell to Encell Shop 22pcs @1230 | G79: =22*1230 -> 27060 | I79: =I78+G79-H79 -> 937560 | J79: ok
D80: 45497 | E80: Ref# 1011 V3 | F80: Sell to Encell Shop 1pcs @1180 | G80: =1*1180 -> 1180 | I80: =I79+G80-H80 -> 938740 | J80: ok
D81: 45497 | E81: Ref# 1012 V3 | F81: Sell to Encell Shop 7pcs @1180 | G81: =7*1180 -> 8260 | I81: =I80+G81-H81 -> 947000 | J81: ok
D82: 45497 | E82: Ref# 1012 V3 | F82: Sell to Encell Shop 20pcs @1180 | G82: =20*1180 -> 23600 | I82: =I81+G82-H82 -> 970600 | J82: ok
D83: 45497 | E83: Ref# 1012 V3 | F83: Sell to Encell Shop 28pcs @1175 | G83: =28*1175 -> 32900 | I83: =I82+G83-H83 -> 1003500 | J83: ok
D84: 45504 | E84: Ref# 1014 V3 | F84: Cash Sell SI0080 130Units @1160 | G84: =130*1160 -> 150800 | I84: =I83+G84-H84 -> 1154300 | J84: ok
D85: 45499 | E85: Ref# 1015 V3 | F85: Sell To Faisal Bhai 30Units @1180 | G85: =1180*30 -> 35400 | I85: =I84+G85-H85 -> 1189700 | J85: ok
D86: 45502 | E86: Ref# 1015 V3 | F86: Sell To Encell Shop 26Units @1165 | G86: =26*1165 -> 30290 | I86: =I85+G86-H86 -> 1219990 | J86: ok
D87: 45504 | E87: Ref# 1015 V3 | F87: Cash Sell SI0080 20Units @1160 | G87: =20*1160 -> 23200 | I87: =I86+G87-H87 -> 1243190 | J87: ok
D88: 45506 | E88: Ref# 1014 V3 | F88: Sell To Encell Shop 15Units @1170 | G88: =1170*15 -> 17550 | I88: =I87+G88-H88 -> 1260740
I89: =I88+G89-H89 -> 1260740
I90: =I89+G90-H90 -> 1260740
I91: =I90+G91-H91 -> 1260740
I92: =I91+G92-H92 -> 1260740
D93: 45394 | F93: From A/R Laguna Payment | H93: =97774/77 -> 1269.7922 | I93: =I92+G93-H93 -> 1259470.2 | J93: ok
D94: 45394 | F94: From A/R Laguna Payment | H94: =164448/77 -> 2135.6883 | I94: =I93+G94-H94 -> 1257334.5 | J94: ok
D95: 45397 | F95: From A/R Paid to Waheed Bhai (agha m.aftab A/C) | H95: 30 | I95: =I94+G95-H95 -> 1257304.5 | J95: ok
D96: 45410 | F96: From A/R Laguna Payment | H96: =97774/77 -> 1269.7922 | I96: =I95+G96-H96 -> 1256034.7 | J96: ok
D97: 45410 | F97: From A/R Laguna Payment | H97: =164448/77 -> 2135.6883 | I97: =I96+G97-H97 -> 1253899 | J97: ok
D98: 45419 | F98: sasco Shipping Charges | H98: 660 | I98: =I97+G98-H98 -> 1253239 | J98: ok
D99: 45419 | F99: sasco Shipping Charges | H99: 650 | I99: =I98+G99-H99 -> 1252589 | J99: ok
D100: 45419 | F100: Payment Send To waheed bhai $9744.30 | H100: 23870 | I100: =I99+G100-H100 -> 1228719 | J100: ok
D101: 45420 | F101: Hamali Charges | H101: 10 | I101: =I100+G101-H101 -> 1228709 | J101: ok
D102: 45420 | F102: Paid to Ashfaq sahb V3 Purchasing | H102: 45000 | I102: =I101+G102-H102 -> 1183709 | J102: ok
D103: 45420 | F103: v3 Import Charges | H103: 4230 | I103: =I102+G103-H103 -> 1179479 | J103: ok
D104: 45420 | F104: Paid From A/R to Faisal Bhai Behalf of Waheed Bhai | H104: 3896.1 | I104: =I103+G104-H104 -> 1175582.9 | J104: ok
D105: 45423 | F105: 7units Purchase A/R Card | H105: 8843.36 | I105: =I104+G105-H105 -> 1166739.6 | J105: ok
D106: 45423 | F106: Card Payment Abdul Rehman bhai | H106: 18624.32 | I106: =I105+G106-H106 -> 1148115.3 | J106: ok
D107: 45427 | F107: Ashfaq Sahab Remaining Payment Returned V3 | H107: 1830 | I107: =I106+G107-H107 -> 1146285.3 | J107: ok
D108: 45427 | F108: Send To australia By A/R (AUD 8782.5 @2.28) | H108: 20000 | I108: =I107+G108-H108 -> 1126285.3 | J108: ok
D109: 45432 | F109: Send To australia By A/R (AUD 23152.5 @2.505) | H109: 58000 | I109: =I108+G109-H109 -> 1068285.3 | J109: ok
... D125: 45463 | F125: Deposite Ashafaq Sahab Card Payment (Paid to Waseem Bhai) | H125: 8350 | I125: =I124+G125-H125 -> 890106.92 | J125: ok
D126: 45463 | F126: ARY Laguna A/C (From Noman Bhai A/R To waheed Bhai) 200000PKR | H126: =200000/77 -> 2597.4026 | I126: =I125+G126-H126 -> 887509.52 | J126: ok
...

Sheet Starlink Stock
C2: Date | D2: Shipment | F2: Details | G2: Australia Qnty | J2: Dubai Balance Stock
C3: 45536 | F3: Old Balance | G3: 462
C4: 45539 | D4: Ref# 1019 V3 | E4: Purchased | F4: Received In Dubai Flat307 | G4: -400 | J4: 400
C5: 45539 | D5: Ref# 1019 V3 | E5: Ship | F5: Sold by A/R 04/09 to 07/09 | G5: 0 | J5: -400
C7: 45540 | D7: Ref# 1020 V4 | E7: Purchased | F7: Purchased | G7: 40
C8: 45547 | D8: Ref# 1021 | E8: Purchased | F8: Purchased Starlink Mini | G8: 42
C9: 45547 | D9: Ref# 1017 V3 | E9: Ship | F9: Old pcs 60 Send to Dubai | G9: -60 | J9: 60
C10: 45547 | D10: Ref# 1020 V4 | E10: Ship | F10: 40 units Send to dubai | G10: -40 | J10: 40
C11: 45547 | D11: Ref# 1021 | E11: Ship | F11: 23 units mini Send to Dubai | G11: -23 | J11: 23
C12: 45547 | D12: Ref# 1008 V3 | E12: - | F12: 1unit Returned AB Card | G12: -1 | J12: 0
C13: 45547 | D13: Ref# 1017 V3 | E13: - | F13: 1unit Missing Australia | G13: -1 | J13: 0
C14: 45548 | D14: Ref# 1022 | E14: Purchased | F14: Purchased Starlink Mini | G14: 10 | J14: 0
C15: 45548 | D15: Ref# 1021 | E15: Sell | F15: Sell Starlink Mini by A/R | J15: -23
C16: 45553 | D16: Ref# 1017 V3 | E16: Sell | F16: 30units Sell By Rabi @1175 | J16: -30
C17: 45553 | D17: Ref# 1017 V3 | E17: Sell | F17: 20units Sell By Rabi @1170 | J17: -20
C18: 45553 | D18: Ref# 1017 V3 | E18: Sell | F18: 10units Sell By Rabi @1170 | J18: -10
C19: 45549 | D19: Ref# 1020 V4 | E19: Sell | F19: 30Units Sell to Rabi @1165 | J19: -30
C20: 45553 | D20: Ref# 1020 V4 | E20: Sell | F20: 5Units Sell to Rabi @1170 | J20: -5
A21: Done | C21: 45553 | D21: Ref# 1020 V4 | E21: Sell | F21: 5Units Sell to Encell Shop @1170 | J21: -5
C23: 45549 | D23: Ref# 1024 V4 | E23: Purchased | F23: Starlink V4 Purchased | G23: 34
C24: 45550 | D24: Ref# 1025 V4 | E24: Purchased | F24: Starlink V4 Purchased | G24: 37
C25: 45551 | D25: Ref# 1026 V4 | E25: Purchased | F25: Starlink V4 Purchased | G25: 32
C26: 45551 | D26: Ref# 1026 Mini | E26: Purchased | F26: Starlink Mini Purchased | G26: 4
C27: 45552 | D27: Ref# 1027 V4 | E27: Purchased | F27: Starlink V4 Purchased | G27: 14
C28: 45553 | D28: Ref# 1028 V4 | E28: Purchased | F28: Starlink V4 Purchased | G28: 60
C29: 45553 | D29: Ref# 1028 Mini | E29: Purchased | F29: Starlink Mini Purchased | G29: 64
C30: 45554 | D30: Ref# 1029 V4 | E30: Purchased | F30: Starlink V4 Purchased | G30: 5
C31: 45554 | D31: Ref# 1029 Mini | E31: Purchased | F31: Starlink Mini Purchased | G31: 7
C32: 45556 | D32: Ref# 1030 Mini | E32: Purchased | F32: Starlink Mini Purchased | G32: 30
C33: 45558 | D33: Ref# 1031 V4 | E33: Purchased | F33: Starlink V4 Purchased | G33: 15
C34: 45558 | D34: Ref# 1031 Mini | E34: Purchased | F34: Starlink Mini Purchased | G34: 5
... C38: 45560 | D38: Ref# 1033 Mini | E38: Purchased | F38: Starlink Mini Purchased | G38: 1
C39: 45560 | E39: Ship | F39: Send to Dubai (V4 164Units Mini 84Units) | G39: =-164-84 -> -248 | J39: 248
C40: 45561 | D40: Ref# 1034 V4 | E40: Purchased | F40: Starlink V4 Purchased | G40: 6
C41: 45562 | E41: Sell | F41: Sell v4 50units | J41: -50
C42: 45562 | E42: Sell | F42: Sell Mini 1Unit | J42: -1
C43: 45562 | E43: Sell | F43: Sell Mini 50 Units | J43: -50
C44: 45562 | E44: Sell | F44: Sell v4 30units | J44: -30
C45: 45562 | D45: Ref# 1035 V4 | E45: Purchased | F45: Starlink V4 Purchased | G45: 14
C46: 45562 | D46: Ref# 1036 V4 | E46: Purchased | F46: Starlink V4 Purchased | G46: 100
C47: 45563 | D47: Ref# 1037 V4 | E47: Purchased | F47: Starlink V4 Purchased | G47: 14
C50: 45565 | E50: Ship | F50: Send to Dubai (V4 104Unit, 48Mini, 2Drone) | G50: -154 | J50: 154
C51: 45566 | E51: Sell | F51: Sell Mini 33units | J51: -33
C52: 45566 | E52: Sell | F52: Sell v4 44units | J52: -44
C53: 45566 | E53: Sell | F53: Sell v4 40units | J53: -40
C55: 45568 | F55: Send to Dubai (109 Units V4, 12Mini, 1Printer | G55: -122 | J55: 122
C57: 45578 | F57: Send to Dubai (20 units IP 16PM 2unit JBL)
G60: =SUM(G3:G59) -> 0 | J60: =SUM(J4:J59) -> 276
F62: Pending Stock
C63: Date | D63: Shipment | F63: Details | G63: Qty
C65: 45549 | D65: Ref# 1024 V4 | E65: Purchased | F65: Starlink V4 Pending | G65: 10
C66: 45551 | D66: Ref# 1026 Mini | E66: Purchased | F66: Starlink Mini Purchased | G66: 4
C67: 45552 | D67: Ref# 1027 V4 | E67: Purchased | F67: Starlink V4 Purchased | G67: 2
C68: 45554 | D68: Ref# 1029 Mini | E68: Purchased | F68: Starlink Mini Purchased | G68: 7
C69: 45558 | D69: Ref# 1031 Mini | E69: Purchased | F69: Starlink Mini Purchased | G69: 2
C70: 45559 | D70: Ref# 1032 Mini | E70: Purchased | F70: Starlink Mini Purchased | G70: 20
F73: Total Pending Stock | G73: =SUM(G65:G72) -> 45

Sheet Purchasing From July
C3: Date | D3: Shipment | E3: Details | F3: Units | G3: Per.Unit | H3: Amount | J3: GST
C4: 45473 | D4: Ref# 1008 V3 | E4: 59 Units Purchased V3 | F4: 59 | G4: =H4/F4 -> 518.64407 | H4: 30600 | J4: 3210 | K4: 1 unit Returned
C6: 45473 | D6: Ref# 1009 V3 | E6: 42 Units Purchased V3 | F6: 42 | G6: =H6/F6 -> 348.19643 | H6: 14624.25 | J6: 1370
A8: ok | C8: 45477 | D8: Ref# 1010 V3 | E8: 92 Units Purchased V3 | F8: 92 | G8: =H8/F8 -> 359 | H8: =359*92 -> 33028 | J8: 3002.65
A10: ok | C10: 45488 | D10: Ref# 1011 V3 | E10: 54 Units Purchased V3 | F10: 54 | G10: =H10/F10 -> 358.96296 | H10: 19384 | J10: 1763
A12: ok | C12: 45491 | D12: Ref# 1012 V3 | E12: 56 Units Purchased V3 | F12: 56 | G12: =H12/F12 -> 357 | H12: 19992 | J12: 1818
A14: ok | C14: 45491 | D14: Ref# 1013 V3 | E14: 250 Units Purchased V3 | F14: 250 | G14: =H14/F14 -> 357 | H14: =357*250 -> 89250 | J14: 8113
A16: ok | C16: 45495 | D16: Ref# 1014 V3 | E16: 113 Units Purchased V3 | F16: 113 | G16: =H16/F16 -> 357 | H16: 40341 | J16: 3667 | K16: Returned
A18: ok | C18: 45497 | D18: Ref# 1015 V3 | E18: 76 Units Purchased V3 | F18: 76 | G18: =H18/F18 -> 357 | H18: 27132 | J18: 2480
A20: ok | C20: 45501 | D20: Ref# 1016 V3 | E20: 37 Units Purchased V3 | F20: 37 | G20: =H20/F20 -> 359 | H20: 13283 | J20: 1207 | K20: Returned
A22: ok | C22: 45502 | D22: Ref# 1017 V3 | E22: 61 Units Purchased V3 | F22: 61 | G22: =H22/F22 -> 358.90164 | H22: 21893 | J22: =1795+196 -> 1991
A24: ok | C24: 45517 | D24: Ref# 1019 V3 | E24: 400 Units Purchased V3 | F24: 400 | G24: =H24/F24 -> 357 | H24: 142800 | J24: 12981
E26: Total GST M/O JULY & AUG | F26: =SUM(F4:F25) -> 1240 | J26: =SUM(J4:J25) -> 41602.65
C28: Date | D28: Shipment | E28: Details | F28: Units | H28: Amount | J28: GST
C29: 45540 | D29: Ref# 1020 V4 | E29: 40 units @358 WB | F29: 40 | G29: =H29/F29 -> 358 | H29: =358*40 -> 14320 | J29: 1301.82
C31: 45549 | D31: Ref#1024 V4 | E31: 34 Units Purchased | F31: 34 | G31: =H31/F31 -> 279.47059 | H31: 9502 | J31: 950.2
C33: 45550 | D33: Ref#1025 V4 | E33: 37 Units Purchased | F33: 37 | G33: =H33/F33 -> 298.18919 | H33: 11033 | J33: 1103.3
C35: 45551 | D35: Ref#1026 V4 | E35: 34 Units Purchased | F35: 34 | G35: =H35/F35 -> 280.35294 | H35: 9532 | J35: 953.2
C37: 45552 | D37: Ref#1027 V4 | E37: 14 Units Purchased | F37: 14 | G37: =H37/F37 -> 299.28571 | H37: 4190 | J37: 419
C39: 45553 | D39: Ref#1028 V4 | E39: 62 Units Purchased | F39: 62 | G39: =H39/F39 -> 297.98387 | H39: 18475 | J39: 1847.5
C41: 45554 | D41: Ref#1029 V4 | E41: 5 Units Purchased | F41: 5 | G41: =H41/F41 -> 298.2 | H41: 1491 | J41: 149.1
C43: 45558 | D43: Ref#1031 V4 | E43: 15 Units Purchased | F43: 15 | G43: =H43/F43 -> 297.53333 | H43: 4463 | J43: 446.3
C45: 45559 | D45: Ref#1032 V4 | E45: 19 Units Purchased | F45: 19 | G45: =H45/F45 -> 298.21053 | H45: 5666 | J45: 566.6
C47: 45560 | D47: Ref#1033 V4 | E47: 12 Units Purchased | F47: 11 | G47: =H47/F47 -> 302.18182 | H47: 3324 | J47: 332.4
C49: 45561 | D49: Ref#1034 V4 | E49: 6 Units Purchased | F49: 6 | G49: =H49/F49 -> 300.5 | H49: 1803 | J49: 180.3
C51: 45562 | D51: Ref#1035 V4 | E51: 14 Units Purchased | F51: 14 | G51: =H51/F51 -> 297.85714 | H51: 4170 | J51: 417
C53: 45562 | D53: Ref#1036 V4 | E53: 100 Units Purchased | F53: 100 | G53: =H53/F53 -> 298 | H53: 29800 | J53: 2709
C55: 45563 | D55: Ref#1037 V4 | E55: 14 Units Purchased | F55: 14 | G55: =H55/F55 -> 297.14286 | H55: 4160 | J55: 416
C57: 45564 | D57: Ref#1038 V4 | E57: 3 Units Purchased | F57: 0 | G57: =H57/F57 -> #DIV/0! | H57: 893
C59: 45565 | D59: Ref#1039 V4 | E59: 15 Units Purchased | F59: 15 | G59: =H59/F59 -> 298.66667 | H59: 4480 | J59: 448
E60: Total GST M/O SEP | F60: =SUM(F29:F59) -> 420 | J60: =SUM(J29:J59) -> 12239.72
C63: Date | D63: Shipment | E63: Details | F63: Units | H63: Amount | J63: GST
C64: 45547 | D64: Ref# 1021 Mini | E64: 42 Units Purchased | F64: 42 | G64: =H64/F64 -> 770.83333 | H64: 32375 | J64: 2251.78
C66: 45548 | D66: Ref# 1022 Mini | E66: Starlink mini 10 units @799 (WB Card) | F66: 10 | G66: =H66/F66 -> 799 | H66: =799*10 -> 7990 | J66: 799
C68: 45551 | D68: Ref#1026 Mini | E68: 4 Units Purchased | F68: 4 | G68: =H68/F68 -> 781.5 | H68: 3126 | J68: 312.6
C70: 45553 | D70: Ref#1028 Mini | E70: 64 Units Purchased | F70: 64 | G70: =H70/F70 -> 784.53125 | H70: 50210 | J70: 5021
C72: 45554 | D72: Ref#1029 Mini | E72: 7 Units Purchased | F72: 7 | G72: =H72/F72 -> 790 | H72: 5530 | J72: 553
C74: 45556 | D74: Ref#1030 Mini | E74: 30 Units Purchased | F74: 30 | G74: =H74/F74 -> 799 | H74: 23970 | J74: 2154
C76: 45558 | D76: Ref#1031 Mini | E76: 5 Units Purchased | F76: 5 | G76: =H76/F76 -> 756.2 | H76: 3781 | J76: 378.1
C78: 45559 | D78: Ref#1032 Mini | E78: 22 Units Purchased | F78: 22 | G78: =H78/F78 -> 757.81818 | H78: 16672 | J78: 1667.2
C80: 45560 | D80: Ref#1033 Mini | E80: 1 Units Purchased | F80: 1 | G80: =H80/F80 -> 796 | H80: 796 | J80: 79.6
E82: Total GST M/O SEP | F82: =SUM(F64:F81) -> 185 | J82: =SUM(J64:J81) -> 13216.28
C84: 45549 | D84: Ref#1023 IP | E84: IPHONE 16 ProMax Purchased | F84: 33 | H84: 74639 | J84: 7463.9
C86: 45565 | D86: DJI | E86: DJI Mavic 3Pro 2Unit WB Card $2550 | F86: 2 | H86: =2550*2 -> 5100 | J86: 510

Sheet GST Charges
D5: Date | E5: Shipment | F5: GST | G5: Ledger
D6: 45397 | E6: V2 16pcs Shipment invoice | F6: 577.45 | G6: Waheed bhai
D7: 45397 | E7: V2 11pcs Shipment invoice | F7: 397 | G7: Waheed bhai
D8: 45397 | E8: 1st shipping invoice | F8: 29.09 | G8: Waheed bhai
D9: 45439 | E9: V3 106pcs GST $47.49 each | F9: 5033.94 | G9: Waheed bhai
E10: GST V2 Shipping Invoice $37.12 | F10: 37.12 | G10: Waheed bhai
D11: 45472 | E11: Ref#1007 12.5 units GST Charges | F11: =4512/94*12.5 -> 600 | G11: Waheed bhai
D12: 45502 | E12: Received And Adjust Waheed Bhai Ledger
E13: Total | F13: =SUM(F6:F12) -> 6674.6
D18: Date | E18: Shipment | F18: GST | G18: Ledger
D19: 45440 | E19: Ref#1004 35 pcs GST Charges | F19: 1665.3 | G19: Business
E20: 35pcs Shipping Charges GST | F20: 16.49 | G20: Business
D21: 45449 | E21: Ref#1005 60pcs V3 Starlink GST | F21: 2847.5 | G21: Business
E22: 60pcs Shipping Charges GST | F22: 27.72 | G22: Business
D23: 45450 | E23: Ref#1006 47pcs V3 Starlink GST | F23: 2177.5 | G23: Business
E24: 47pcs Shipping Charges GST | F24: 24.36 | G24: Business
D25: 45472 | E25: Ref#1007 92Units GST Charges | F25: 4512 | G25: Business
D26: 45488 | E26: Ref#1010 92units GST | F26: 3002.65 | G26: Business
D27: 45502 | E27: Received And Adjust Waheed Bhai Ledger | F27: -13673.52 | G27: Business
D30: Date | E30: Shipment | F30: GST | G30: Ledger
D31: 45509 | E31: Ref#1008 59units GST | F31: 3210 | G31: Business
D32: 45491 | E32: Ref#1009 42units GST | F32: 1370 | G32: Business
D33: 45488 | E33: Ref#1011 54units GST | F33: 1763 | G33: Business
D34: 45491 | E34: Ref#1012 56Units | F34: 1818 | G34: Business
D35: 45491 | E35: Ref#1013 250Units | F35: 8113 | G35: Business
E36: 250units Shipping Charges GST | F36: 150 | G36: Business
D37: 45495 | E37: Ref#1014 113Units GST | F37: 1130 | G37: Business
D38: 45509 | E38: Ref#1015 76Units | F38: 2480 | G38: Business
E39: 76units Shipping Charges GST | F39: 55 | G39: Business
D40: 45508 | E40: Ref#1016 37Units GST | F40: 1207 | G40: Business
D41: 45509 | E41: Ref#1017 55Units | F41: 1795 | G41: Business
D42: 45509 | E42: Ref#1017 6Units | F42: 196 | G42: Business
E44: Total | F44: =SUM(F19:F43) -> 23887
D48: Date | E48: Shipment | F48: Refundable | G48: Ledger
D49: 45468 | E49: Ref#1007 81.5pcs Refundable Charges | F49: 6109.24 | G49: Business
D50: 45473 | E50: 46pcs Refundable Charges $75 | F50: =46*75 -> 3450 | G50: Business
E51: Total | F51: =SUM(F49:F50) -> 9559.24
D55: Date | E55: Shipment | F55: Refundable | G55: Ledger
D56: 45468 | E56: Refundable Charges Ref#1007 12.5Units @597-522.04 =74.96 | F56: =74.96*12.5 -> 937 | G56: Waheed bhai
E57: Total | F57: =SUM(F56) -> 937
D60: Date | E60: Shipment | F60: GST | G60: Ledger
D61: 45517 | E61: Ref#1019 400Units | F61: 12984 | G61: Business
E62: 400units Shipping Charges GST | F62: 179.44 | G62: Business
D63: 45544 | E63: Ref#1020 40Units GST | F63: 1301.82 | G63: Business
D64: 45544 | E64: Ref#1021 31Units GST | F64: 2251.78 | G64: Business
D65: 45548 | E65: Ref#1022 10Units GST | F65: 799 | G65: Business
D66: 45549 | E66: Ref#1023 IP 16 33Units GST | F66: 7463.9 | G66: Business
D67: 45549 | E67: Ref#1024 34.Units GST | F67: 950.2 | G67: Business
D68: 45550 | E68: Ref#1025 37.Units GST | F68: 1103.3 | G68: Business
D69: 45551 | E69: Ref#1026 36.Units GST | F69: 1265.8 | G69: Business
D70: 45552 | E70: Ref#1027 14.Units GST | F70: 419 | G70: Business
D71: 45553 | E71: Ref#1028 124.Units GST | F71: 6809 | G71: Business
D72: 45554 | E72: Ref#1029 12.Units GST | F72: 702.1 | G72: Business
D73: 45556 | E73: Ref#1030 30.Units GST | F73: 2154 | G73: Business
D74: 45558 | E74: Ref#1031 20.Units GST | F74: 824.4 | G74: Business
... D76: 45560 | E76: Ref#1033 9.Units GST | F76: 318.4 | G76: Business
E78: Total | F78: =SUM(F61:F77) -> 41759.94
D86: Date | E86: Shipment | F86: Units | G86: GST | H86: Ledger
D87: 45397 | E87: Ref#1001 16Units | F87: 16 | G87: 577.45 | H87: Business
D88: 45397 | E88: Ref#1002 11Units | F88: 11 | G88: 397 | H88: Business
D89: 45439 | E89: Ref#1003 106Units | F89: 106 | G89: 5033.94 | H89: Business
D90: 45440 | E90: Ref#1004 35Units | F90: 35 | G90: 1665.3 | H90: Business
D91: 45449 | E91: Ref#1005 60Units | F91: 60 | G91: 2847.5 | H91: Business
D92: 45450 | E92: Ref#1006 47Units | F92: 47 | G92: 2177.5 | H92: Business
D93: 45472 | E93: Ref#1007 94Units | F93: 94 | G93: 4512 | H93: Business
D95: Date | E95: Shipment | F95: Units | G95: GST | H95: Ledger
C96: ok | D96: 45478 | E96: Ref#1008 59units | F96: 59 | G96: 3210 | H96: Business | I96: 1 Unit Returned
C97: ok | D97: 45491 | E97: Ref#1009 42units | F97: 42 | G97: 1370 | H97: Business
C98: ok | D98: 45488 | E98: Ref#1010 92units | F98: 92 | G98: 3002.65 | H98: Business | I98: GST Received
C99: ok | D99: 45488 | E99: Ref#1011 54units | F99: 54 | G99: 1763 | H99: Business
C100: ok | D100: 45491 | E100: Ref#1012 56Units | F100: 56 | G100: 1818 | H100: Business
C101: ok | D101: 45491 | E101: Ref#1013 250Units | F101: 250 | G101: 8113 | H101: Business
C102: ok | D102: 45495 | E102: Ref#1014 113Units | F102: 113 | G102: 1130 | H102: Business | I102: Shipment Returned
C103: ok | D103: 45497 | E103: Ref#1015 76Units | F103: 76 | G103: 2480 | H103: Business
C104: ok | D104: 45509 | E104: Ref#1016 37Units | F104: 37 | G104: 1207 | H104: Business | I104: Shipment Returned
C105: ok | D105: 45509 | E105: Ref#1017 61Units | F105: 61 | G105: =1795+196 -> 1991 | H105: Business
C106: ok | D106: 45517 | E106: Ref#1019 400Units | F106: 400 | G106: 12984 | H106: Business
D107: 45544 | E107: Ref#1020 40Units | F107: 40 | G107: 1301.82 | H107: Business
D108: 45544 | E108: Ref#1021 31Units | F108: 31 | G108: 2251.78 | H108: Business
D109: 45548 | E109: Ref#1022 10Units | F109: 10 | G109: 799 | H109: Business
D110: 45549 | E110: Ref#1023 33Units IP 16PM Shipment | F110: 33 | G110: 7463.9 | H110: Business
D111: 45549 | E111: Ref#1024 34.Units | F111: 34 | G111: 950.2 | H111: Business
D112: 45550 | E112: Ref#1025 37.Units | F112: 37 | G112: 1103.3 | H112: Business
D113: 45551 | E113: Ref#1026 36.Units | F113: 36 | G113: 1265.8 | H113: Business
D114: 45552 | E114: Ref#1027 14.Units | F114: 14 | G114: 419 | H114: Business
D115: 45553 | E115: Ref#1028 126.Units | F115: 126 | G115: 6868.5 | H115: Business
D116: 45554 | E116: Ref#1029 12.Units | F116: 12 | G116: 702.1 | H116: Business
D117: 45556 | E117: Ref#1030 30.Units | F117: 30 | G117: 2154 | H117: Business
D118: 45558 | E118: Ref#1031 20.Units | F118: 20 | G118: 824.4 | H118: Business
... D121: 45561 | E121: Ref#1034 6.Units | F121: 6 | G121: 180.3 | H121: Business
E124: Total | F124: =SUM(F96:F123) -> 1723 | G124: =SUM(G96:G123) -> 68028.95
D132: 45502 | E132: Received And Adjust Waheed Bhai Ledger | G132: -13673.52 | H132: Business
D135: 45549 | E135: Ref#1023 IP 16 33Units GST | F135: 33 | G135: 7463.9 | H135: Business
D140: Date | E140: Details | F140: Units
D141: 45474 | E141: 24pcs Sell To Encell Shop @1530 | F141: 24
D142: 45478 | E142: 31pcs Sell To Encell Shop @1500 | F142: 31
D143: 45482 | E143: 3pcs Sell To Encell Shop @1425 (1/2) | F143: 3
D144: 45482 | E144: 20pcs Sell To Encell Shop @1425 (2/2) | F144: 20
D145: 45482 | E145: 5pcs Sell To Encell Shop @1470 | F145: 5
D146: 45484 | E146: 10pcs Sell To Encell Shop @1425 | F146: 10
...

Sheet Expense Sheet
D4: Date | E4: Card No | F4: Units | G4: Amount AUD | N4: AB CARD | O4: 6012
E5: Invoice No.1 | N5: AB CARD | O5: 6866
D6: 45457 | E6: 6866 | F6: 3units | G6: 1791
D7: 45457 | E7: 6866 | F7: 3units | G7: =597*3 -> 1791
D8: 45459 | E8: 6866 | F8: 4units | G8: 2388
D9: 45457 | E9: 6866 | F9: 4units | G9: 2388
D10: 45457 | E10: 6866 | F10: 2units | G10: =597*2 -> 1194
D11: 45448 | E11: 6866 | F11: 4units | G11: =522*4 -> 2088
D12: 45458 | E12: 6866 | F12: 19units | G12: =19*597 -> 11343
D13: 45458 | E13: 6866 | F13: 6units | G13: =6*597 -> 3582
E14: Invoice No.2
D15: 45459 | E15: 6866 | F15: 7units | G15: =7*597 -> 4179
D16: 45459 | E16: 6866 | F16: 8units | G16: =8*597 -> 4776
D17: 45459 | E17: 6866 | F17: 7units | G17: 4179
D18: 45460 | E18: 6866 | F18: 8units | G18: =8*597 -> 4776
D19: 45458 | E19: 6866 | F19: 9units | G19: =9*597 -> 5373
D20: 45459 | E20: 6866 | F20: 12units | G20: =12*597 -> 7164
E21: Invoice No.3
D22: 45460 | E22: 6012 | F22: 4units | G22: =4*597 -> 2388
D23: 45459 | E23: 6012 | F23: 4units | G23: =4*597 -> 2388
D24: 45460 | E24: 6012 | F24: 4units | G24: =4*597 -> 2388
D25: 45459 | E25: 6012 | F25: 5units | G25: =5*597 -> 2985
D26: 45459 | E26: 6012 | F26: 8units | G26: =8*597 -> 4776
D27: 45449 | E27: 6866 | F27: 8units | G27: =8*522.03 -> 4176.24
D28: 45460 | E28: 6866 | F28: 11units | G28: 6866
D29: 45449 | E29: 6866 | F29: 7units | G29: =7*522.03 -> 3654.21
E31: Total | G31: =SUM(G6:G30) -> 86633.45
D33: Date | E33: Card No | F33: Units | G33: Amount AUD
D34: 45460 | E34: 070 | F34: 5units | G34: 2686
G35: =SUM(G34:G34) -> 2686
D39: Date | E39: Card No | F39: Amount AUD
D40: 45517 | E40: 6012 | F40: 5613.73
D41: 45517 | E41: 6012 | F41: 5613.73
D42: 45517 | E42: 6012 | F42: 4210.3
D43: 45517 | E43: 6012 | F43: 7017.17
D44: 45517 | E44: 6012 | F44: 11227.46
F46: =SUM(F40:F45) -> 33682.39
D48: Date | E48: Card No | F48: Amount AUD
D49: 45517 | E49: 6866 | F49: 4897.37
D50: 45517 | E50: 6866 | F50: 8401.52
D51: 45517 | E51: 6866 | F51: 4200.76
D52: 45517 | E52: 6866 | F52: 4200.76
D53: 45517 | E53: 6866 | F53: 5601.01
D54: 45517 | E54: 6866 | F54: 5601.01
D55: 45517 | E55: 6866 | F55: 9801.77
D56: 45517 | E56: 6866 | F56: 9801.77
D57: 45517 | E57: 6866 | F57: 2800.5
D58: 45517 | E58: 6866 | F58: 8571.21
D59: 45517 | E59: 6866 | F59: 9795.67
D60: 45517 | E60: 6866 | F60: 11202.02
... D65: 45517 | E65: 6866 | F65: 26604.8
F67: =SUM(F49:F66) -> 168191.57
C71: Date | D71: Shipment | E71: Details | F71: Expense $ | G71: Rate | H71: Expense Aed | I71: Total
C72: 45397 | D72: Ref#1001V2 | E72: 1st Shipping Invoice V2 $1516.06 | F72: 1516.06 | G72: 2.42 | H72: =F72*G72 -> 3668.8652
C73: 45397 | D73: Ref#1002 V2 | E73: Sasco Shipping Charges (1st Invoice) | H73: 660
D74: Ref#1002 V2 | E74: Sasco Shipping Charges (2nd Invoice) | H74: 650
C75: 45419 | D75: Ref#1003V3 | E75: V3 106pcs Import Charges (Paid By A/R Dubai) | H75: 4230
C76: 45420 | D76: Ref#1003V3 | E76: Hamali Charges (by Amgt 09pcs sell) | H76: 10
C77: 45423 | D77: Ref#1003V3 | E77: Car Petrol | F77: 58 | G77: 2.42 | H77: =F77*G77 -> 140.36
C78: 45423 | D78: Ref#1003V3 | E78: Van Petrol | F78: 28 | G78: 2.42 | H78: =F78*G78 -> 67.76
C79: 45423 | D79: Ref#1003V3 | E79: Van Hire | F79: 101 | G79: 2.42 | H79: =F79*G79 -> 244.42
C80: 45423 | D80: Ref#1003V3 | E80: Shipping Charges | F80: 4327.63 | G80: 2.42 | H80: =F80*G80 -> 10472.865
C81: 45440 | D81: Ref#1004V3 | E81: V3 Import Charges 35pcs | H81: 1230
C82: 45440 | D82: V3 35pcs | E82: Other Expense Paid by Waheed Bhai | F82: 126 | G82: 2.44 | H82: =F82*G82 -> 307.44
C83: 45440 | D83: V3 35pcs | E83: Hamali Charges Paid by AR | H83: 30
C84: 45443 | D84: V3 35pcs | E84: Shipping Charges | F84: 1638.29 | G84: 2.44 | H84: =F84*G84 -> 3997.4276
C85: 45447 | D85: V3 35pcs | E85: Fahib Salary M/O May-2024 (15000 PKR) | H85: 194.81
C86: 45471 | D86: V3 35pcs | E86: Surcharge Include | F86: 23.01 | G86: 2.44 | H86: =F86*G86 -> 56.1444
C87: 45448 | D87: V3 60pcs | E87: V3 Clearing Charges 60pcs (Paid by A/R) | F87: - | G87: - | H87: 1660
C88: 45448 | D88: V3 60pcs | E88: Hamali Charges Paid by Encell Shop | F88: - | G88: - | H88: 40
C89: 45448 | D89: V3 60pcs | E89: Other Expense Paid By Waheed Bhai | F89: 360 | G89: 2.44 | H89: =F89*G89 -> 878.4
C90: 45456 | D90: V3 60pcs | E90: Shipping Invoice | F90: 2651.54 | G90: 2.44 | H90: =F90*G90 -> 6469.7576
C91: 45471 | D91: V3 60pcs | E91: Surcharge Include | F91: 23.01 | G91: 2.44 | H91: =F91*G91 -> 56.1444
C92: 45449 | D92: V3 47pcs | E92: Expense $40 Petrol Charges | F92: 40 | G92: 2.44 | H92: =F92*G92 -> 97.6
C93: 45453 | D93: V3 47pcs | E93: Expense $50 Toll Charges | F93: 50 | G93: 2.44 | H93: =F93*G93 -> 122
C94: 45453 | D94: V3 47pcs | E94: Clearing Charges Paid by A/R | F94: - | G94: - | H94: 1465
C95: 45453 | D95: V3 47pcs | E95: Hamali Charges Paid by A/R | F95: - | G95: - | H95: 35
C96: 45456 | D96: V3 47pcs | E96: Shipping Invoice | F96: 2153.6 | G96: 2.44 | H96: =F96*G96 -> 5254.784
C97: 45471 | D97: V3 47pcs | E97: Surcharge Include | F97: 23.01 | G97: 2.44 | H97: =F97*G97 -> 56.1444
C98: 45468 | D98: Ref# 1007 V3 | E98: Other Expense Paid by Waheed Bhai ticket/car/petrol/toll/bus) | F98: 750 | G98: 2.44 | H98: =F98*G98 -> 1830
C99: 45468 | D99: Ref# 1007 V3 | E99: Shipping Charges paid By Waheed Bhai | F99: 3687.51 | G99: 2.44 | H99: =F99*G99 -> 8997.5244
C100: 45469 | D100: Ref# 1007 V3 | E100: Hamali Charges Paid by A/R | G100: - | H100: 25
C101: 45471 | D101: Ref# 1007 V3 | E101: Hamali Charges Paid by A/R | G101: - | H101: 50
C102: 45471 | D102: Ref# 1007 V3 | E102: Cargo Charges Paid by A/R | G102: - | H102: 100
C103: 45472 | D103: Ref# 1007 V3 | E103: V3 Hamali Charges Paid by A/R (ali karachi Ledger) | H103: 60
C104: 45472 | D104: Ref# 1007 V3 | E104: V3 Clearing Charges Paid by A/R (Ali karachi Ledger) | H104: 1350
C105: 45474 | D105: Ref# 1008 V3 | E105: V3 Hamali Charges Paid by A/R (Encell Shop) | H105: 60
C106: 45474 | D106: Ref# 1008 V3 | E106: V3 Clearing Charges Paid by A/R (Encell Shop) | H106: 1050
C107: 45473 | D107: Ref# 1008 V3 | E107: Petrol Expense (Ab + WB Card) | F107: 165 | G107: 2.44 | H107: =F107*G107 -> 402.6
C108: 45471 | D108: Ref# 1008 V3 | E108: Shipping Charges Paid (AR Card) | F108: 2723.08 | G108: 2.44 | H108: =F108*G108 -> 6644.3152
C109: 45502 | D109: Ref# 1009 V3 | E109: Petrol Exp (WB Card) | F109: 80 | G109: 2.44 | H109: =F109*G109 -> 195.2
C110: 45488 | D110: Ref# 1009 V3 | E110: Total 42 pcs Shipping Charges (WB) | F110: 2082 | G110: 2.44 | H110: =F110*G110 -> 5080.08
C111: 45477 | D111: Ref# 1010 V3 | E111: Uber (Waheed Bhai Card) | F111: 89 | G111: 2.44 | H111: =F111*G111 -> 217.16
C112: 45477 | D112: Ref# 1010 V3 | E112: Ticket Charges (Ashfaq Sahab Card ) | F112: 773 | G112: 2.44 | H112: =F112*G112 -> 1886.12
C113: 45477 | D113: Ref# 1010 V3 | E113: Food Exp (Waheed Bhai Card) | F113: 86 | G113: 2.44 | H113: =F113*G113 -> 209.84
C114: 45477 | D114: Ref# 1010 V3 | E114: Van Hire Charges (Waheed Bhai Card) | F114: 209 | G114: 2.44 | H114: =F114*G114 -> 509.96
C115: 45477 | D115: Ref# 1010 V3 | E115: Petrol Exp (Waheed Bhai Card) | F115: 76 | G115: 2.44 | H115: =F115*G115 -> 185.44
C116: 45477 | D116: Ref# 1010 V3 | E116: Shipping Charges + Surcharge (Ashfaq Sahab Card) | F116: 5100 | G116: 2.44 | H116: =F116*G116 -> 12444
C117: 45477 | D117: Ref# 1010 V3 | E117: Fahib Salary M/O June-2024 (15000 PKR) | H117: =15000/76.5 -> 196.07843
C118: 45481 | D118: Ref# 1010 V3 | E118: freeZone charges Paid by A/R (From Encell Shop) | H118: 1860
...

Sheet Sheet1
D3: Date | E3: Invoice | F3: Model | G3: Qty | H3: Price | I3: Total $ | J3: Rate | K3: Per Unit Aed | L3: Total Aed | N3: Invoice | O3: Party | P3: Sell Per Unit | Q3: Total Per Unit
C4: AR Card | D4: 45549 | E4: Ref#001 | F4: IP 16ProMax 256GB | G4: 2 | H4: 2147 | I4: =G4*H4 -> 4294 | J4: 2.53 | K4: =H4*J4 -> 5431.91 | L4: =K4*G4 -> 10863.82
C5: AR Card | D5: 45549 | E5: Ref#001 | F5: IP 16ProMax 512GB | G5: 3 | H5: 2497 | I5: =G5*H5 -> 7491 | J5: 2.53 | K5: =H5*J5 -> 6317.41 | L5: =K5*G5 -> 18952.23
C7: WB Card | D7: 45550 | E7: Ref#002 | F7: IP 16ProMax 512GB | G7: 1 | H7: 2497 | I7: =G7*H7 -> 2497 | J7: 2.53 | K7: =H7*J7 -> 6317.41 | L7: =K7*G7 -> 6317.41
C8: AB Card | D8: 45550 | E8: Ref#002 | F8: IP 16ProMax 512GB | G8: 2 | H8: 2497 | I8: =G8*H8 -> 4994 | J8: 2.53 | K8: =H8*J8 -> 6317.41 | L8: =K8*G8 -> 12634.82
C10: AB Card | D10: 45551 | E10: Ref#003 | F10: IP 16ProMax 1TB | G10: 3 | H10: 2847 | I10: =G10*H10 -> 8541 | J10: 2.53 | K10: =H10*J10 -> 7202.91 | L10: =K10*G10 -> 21608.73
C11: AB Card | D11: 45551 | E11: Ref#003 | F11: IP 16Pro 256GB | G11: 3 | H11: 1997 | I11: =G11*H11 -> 5991 | J11: 2.53 | K11: =H11*J11 -> 5052.41 | L11: =K11*G11 -> 15157.23
C13: WB Card | D13: 45556 | E13: Ref#005 | F13: IP 16ProMax 256GB | G13: 11 | H13: 2149 | I13: =G13*H13 -> 23639 | J13: 2.53 | K13: =H13*J13 -> 5436.97 | L13: =K13*G13 -> 59806.67
C14: NB Card | D14: 45556 | E14: Ref#005 | F14: IP 16ProMax 256GB | G14: 8 | H14: 2149 | I14: =G14*H14 -> 17192 | J14: 2.53 | K14: =H14*J14 -> 5436.97 | L14: =K14*G14 -> 43495.76
F16: Total Purchasing | I16: =SUM(I4:I15) -> 74639 | L16: =SUM(L4:L15) -> 188836.67
F17: Less GST 10% | I17: -7463.9 | L17: -18883.67
F19: Shipping Charges $700 | L19: =700*2.53 -> 1771
F20: Clearing Charges | L20: 1155
F21: NET PURCHASING | L21: =SUM(L16:L20) -> 172879
F23: Sell To AMGT 33 Units | L23: -195520
F25: Profit Amount | L25: 22641
C29: AMGT | D29: 45556 | F29: 2 Unit IP 16 ProMax 256GB | G29: 4298 | H29: 2940.69 | I29: 3.674 | J29: =H29*I29 -> 10804.095
D30: 45556 | F30: 2 Unit IP 16 ProMax 256GB | G30: 4298 | H30: 2940.69 | I30: 3.674 | J30: =H30*I30 -> 10804.095
D31: 45556 | F31: 2 Unit IP 16 ProMax 256GB | G31: 4298 | H31: 2940.69 | I31: 3.674 | J31: =H31*I31 -> 10804.095
D32: 45556 | F32: 2 Unit IP 16 ProMax 256GB | G32: 4298 | H32: 2940.69 | I32: 3.674 | J32: =H32*I32 -> 10804.095
D33: 45556 | F33: 2 Unit IP 16 ProMax 1TB | G33: 5698 | H33: 3954.41 | I33: 3.674 | J33: =H33*I33 -> 14528.502
D34: 45574 | F34: 2 Unit IP 16 ProMax 256GB | G34: 4298 | H34: 2899.86 | I34: 3.674 | J34: =H34*I34 -> 10654.086
D35: 45574 | F35: 2 Unit IP 16 ProMax 256GB | G35: 4298 | H35: 2899.86 | I35: 3.674 | J35: =H35*I35 -> 10654.086
D36: 45574 | F36: 2 Unit IP 16 ProMax 256GB | G36: 4298 | H36: 2899.86 | I36: 3.674 | J36: =H36*I36 -> 10654.086
D37: 45574 | F37: 2 Unit IP 16 ProMax 256GB | G37: 4298 | H37: 2899.86 | I37: 3.674 | J37: =H37*I37 -> 10654.086
D38: 45574 | F38: 2 Unit IP 16 ProMax 256GB | G38: 4298 | H38: 2899.86 | I38: 3.674 | J38: =H38*I38 -> 10654.086
D39: 45574 | F39: 2 Unit IP 16 ProMax 256GB | G39: 4298 | H39: 2899.86 | I39: 3.674 | J39: =H39*I39 -> 10654.086
D40: 45574 | F40: 2 Unit IP 16 ProMax 256GB | G40: 4298 | H40: 2899.86 | I40: 3.674 | J40: =H40*I40 -> 10654.086
G42: =SUM(G29:G41) -> 52976 | H42: =SUM(H29:H41) -> 36016.19 | J42: =SUM(J29:J41) -> 132323.48
C45: WB Card | D45: 45556 | F45: 4 Unit IP 16 ProMax 1TB $2849 | G45: =2849*4 -> 11396 | H45: 2.55 | I45: =G45*H45 -> 29059.8 | J45: 29059.8
F46: 25 Unit IP 16 ProMax 256GB $2149 | G46: =2149*25 -> 53725 | H46: 2.55 | I46: =G46*H46 -> 136998.75 | J46: 136998.75
I47: =SUM(I45:I46) -> 166058.55

Sheet Sheet3
B4: Prchasing
C5: Unit | D5: Rate | E5: Amount | H5: Total Purchase | I5: =E14 -> 639025
B6: V4 | C6: 204 | D6: 1210 | E6: =C6*D6 -> 246840 | H6: Total Sell | I6: =E42 -> 914485
B7: V4 | C7: 42 | D7: 1160 | E7: =C7*D7 -> 48720
B8: V4 | C8: 183 | D8: 1225 | E8: =C8*D8 -> 224175 | H8: Balance | I8: =I6-I5 -> 275460
C9: =SUM(C6:C8) -> 429
B11: Mini | C11: 37 | D11: 2120 | E11: =C11*D11 -> 78440
B12: Mini | C12: 19 | D12: 2150 | E12: =C12*D12 -> 40850 | H12: v4 Balance | I12: =104+109+429 -> 642 | J12: =593 -> 593 | K12: =I12-J12 -> 49
C13: =SUM(C11:C12) -> 56 | H13: Mini Balance | I13: =56+48+12 -> 116 | J13: =84 -> 84 | K13: =I13-J13 -> 32
C14: Total Purchase | E14: =SUM(E6:E13) -> 639025
B17: Sell
C18: Unit | D18: Rate | E18: Amount
B19: V4 | C19: 104 | D19: 1230 | E19: =C19*D19 -> 127920
C20: 204 | D20: 1230 | E20: =C20*D20 -> 250920
C21: 150 | D21: 1235 | E21: =C21*D21 -> 185250
C22: 10 | D22: 1250 | E22: =C22*D22 -> 12500
C23: 20 | D23: 1235 | E23: =C23*D23 -> 24700
C24: 1 | D24: 1235 | E24: =C24*D24 -> 1235
C25: 50 | D25: 1240 | E25: =C25*D25 -> 62000
C26: 8 | D26: 1235 | E26: =C26*D26 -> 9880
C27: 5 | D27: 1250 | E27: =C27*D27 -> 6250
C28: 30 | D28: 1245 | E28: =C28*D28 -> 37350
C29: 1 | D29: 1250 | E29: =C29*D29 -> 1250
C30: 10 | D30: 1250 | E30: =C30*D30 -> 12500
C31: =SUM(C19:C30) -> 593
B32: Mini | C32: 5 | D32: 2200 | E32: =C32*D32 -> 11000
C33: 10 | D33: 2180 | E33: =C33*D33 -> 21800
C34: 2 | D34: 2140 | E34: =C34*D34 -> 4280
C35: 15 | D35: 2100 | E35: =C35*D35 -> 31500
C36: 3 | D36: 2150 | E36: =C36*D36 -> 6450
C37: 10 | D37: 2200 | E37: =C37*D37 -> 22000
C38: 19 | D38: 2200 | E38: =C38*D38 -> 41800
C39: 10 | D39: 2200 | E39: =C39*D39 -> 22000
C40: 10 | D40: 2190 | E40: =C40*D40 -> 21900
C41: =SUM(C32:C40) -> 84
C42: Total Sell | E42: =SUM(E19:E41) -> 914485
E48: Date | F48: Units | G48: Invoice Amount | H48: GST
E50: 45477 | F50: 92 units Shipping +surchage | G50: 5100
E51: 45488 | F51: 42 unit Shipping | G51: 2082
E52: 45493 | F52: 56 Unit Shipping | G52: 2556 | H52: 55
E53: 45502 | F53: 270 units Shipping | G53: 8412.26 | H53: 150
D55: ok | E55: 45539 | F55: 400 units Shipping | G55: 12011.8 | H55: 179.44
D56: ok | E56: 45544 | F56: 23 Unit Shipping | G56: 874.8 | H56: 38.8
D57: ok | E57: 45547 | F57: 100 Unit Shipping
E58: 45560 | F58: 248 Units Shipping
E59: 45565 | F59: 154 Units Shipping
