Workbook

Sheet Balance Sheet
H2: Pending Item & Work
C4: Karachi Cash | D4: =#REF! -> #REF!
C5: Karachi Expense | D5: =#REF! -> #REF!
H6: 1900 dollar Handover to Waheed Bhai Ar Received 500 Exp 1400 Pending
C7: Dubai Cash | D7: =#REF! -> #REF! | H7: Taha Bhai Payable 24,079 PKR
C8: Dubai Expense | D8: =#REF! -> #REF!
C10: Meezan Bank Karachi | D10: 0 | G10: 45567 | H10: Canada Phone Purchasing & Sell Pending
C11: Dubai Bank A/C | D11: =#REF! -> #REF! | H11: AMGT 2units Pending Invoice
H12: meezan Entries Pending
H13: Taha Payment Balance 5387 PKR
H14: 7000 Ahsan CBA Aed Balance PKR Paid
H15: Qari Abdullah 10,000 Balance
H17: Mudassir Bhai 3 unit Purchased (Imei Pending)
H18: Mudassir Bhai Stock USA Office ???
C19: PARTY NAME | D19: BALANCE
C21: NAME | D21: BALANCES (PKR)
B22: ok | C22: Mudassir A/R | D22: ='Customer Ledger'!F511 -> 116642
B23: ok | C23: EuroNext Shop | D23: ='Customer Ledger'!F721 -> -901922.5
B24: ok | C24: Danish | D24: ='Customer Ledger'!F762 -> 560000
C25: Raaz | D25: ='Customer Ledger'!F569 -> -2500
B26: ok | C26: Daniyal | D26: ='Customer Ledger'!F554 -> 336350
C27: IRFAN | D27: ='Customer Ledger'!F398 -> 45000
C28: Waleed | D28: ='Customer Ledger'!F529 -> 100000
C29: RAZI | D29: ='Customer Ledger'!F386 -> 100000
C30: NAME | D30: BALANCES (AED)
C31: Machine Cargo Payment | D31: ='Customer Ledger'!F362 -> 4350
C32: Muhammad Usman | D32: ='Vendor Ledger'!F27 -> -5416.23
C33: ABDUL MAJID BHAI | D33: ='Customer Ledger'!F302 -> -32370
C34: ='Customer Ledger'!C210 -> Umer Gujranwala | D34: ='Customer Ledger'!F219 -> 100
C35: Salman (Al-Badar) | D35: ='Customer Ledger'!F372 -> 11314.38 | E35: $8820

Sheet Customer Ledger
A3: Customer Name : | C3: Saad & Wajahat Encell Shop
B5: Date | C5: Particular | D5: Dr | E5: Cr | F5: Balance
B7: 45405 | C7: Bill No SI0001 | D7: =Sell.Invoice!F23 -> 11550 | F7: =F6+D7-E7 -> 11550
B8: 45405 | C8: Bill No SI0002 | D8: =Sell.Invoice!F43 -> 9100 | F8: =F7+D8-E8 -> 20650
B9: 45405 | C9: Bill No SI0003 | D9: =Sell.Invoice!F63 -> 25500 | F9: =F8+D9-E9 -> 46150
B10: 45405 | C10: Bill No SI0004 | D10: =Sell.Invoice!F90 -> 15850 | F10: =F9+D10-E10 -> 62000
B11: 45405 | C11: Bill No SI0005 | D11: 11500 | F11: =F10+D11-E11 -> 73500
B12: 45405 | C12: Cash Received From Wajahat | E12: 19700 | F12: =F11+D12-E12 -> 53800
B13: 45406 | C13: Cash Received From Wajahat | E13: 10000 | F13: =F12+D13-E13 -> 43800
B14: 45407 | C14: Cash Received From Wajahat | E14: 30000 | F14: =F13+D14-E14 -> 13800
B15: 45408 | C15: Cash Received From Wajahat | E15: 50 | F15: =F14+D15-E15 -> 13750
B16: 45409 | C16: Discount | E16: 800 | F16: =F15+D16-E16 -> 12950
B17: 45415 | C17: Bill No SI0007 | D17: 111200 | F17: =F16+D17-E17 -> 124150
B18: 45418 | C18: Cash Received From Saad | E18: 40000 | F18: =F17+D18-E18 -> 84150
B19: 45418 | C19: IP 11 24pcs Discount 65x24 | E19: 1560 | F19: =F18+D19-E19 -> 82590
B20: 45418 | C20: IP 11ProMax 38pcs Discount 38x20 | E20: 760 | F20: =F19+D20-E20 -> 81830
B21: 45418 | C21: Cash Received From Wajahat (Machine Cargo Charges ) | E21: 4170 | F21: =F20+D21-E21 -> 77660
B22: 45418 | C22: Bill No SR0008 | E22: 6390 | F22: =F21+D22-E22 -> 71270
B23: 45418 | C23: Bill No SI0009 | D23: 2100 | F23: =F22+D23-E23 -> 73370
B24: 45419 | C24: Cash Received From Saad | E24: 1000 | F24: =F23+D24-E24 -> 72370
B25: 45419 | C25: Bill No SI0010 (V3) | D25: 35800 | F25: =F24+D25-E25 -> 108170
B26: 45420 | C26: Bill No SI0012 (V3) | D26: 18000 | F26: =F25+D26-E26 -> 126170
B27: 45420 | C27: Cash Received From Wajahat | E27: 53800 | F27: =F26+D27-E27 -> 72370
B28: 45420 | C28: Cash Received From Wajahat | E28: 10000 | F28: =F27+D28-E28 -> 62370
B29: 45423 | C29: Bill No SI0013 | D29: 36720 | F29: =F28+D29-E29 -> 99090
B30: 45426 | C30: Cash From Saad | E30: 50000 | F30: =F29+D30-E30 -> 49090
B31: 45426 | C31: Cash From Saad | E31: 1300 | F31: =F30+D31-E31 -> 47790
B32: 45429 | C32: Bill No SI0014 | D32: 5670 | F32: =F31+D32-E32 -> 53460
B33: 45430 | C33: Bill No SI0015 | D33: 16300 | F33: =F32+D33-E33 -> 69760
B34: 45430 | C34: Bill No SI0017 (V3 Invoice 14/05/2024) | D34: 54000 | F34: =F33+D34-E34 -> 123760
B35: 45432 | C35: Cash Received From Saad | E35: 54000 | F35: =F34+D35-E35 -> 69760
B36: 45432 | C36: Bill No SR0018 | E36: 1650 | F36: =F35+D36-E36 -> 68110
B37: 45432 | C37: Cash Received From Saad | E37: 30000 | F37: =F36+D37-E37 -> 38110
B38: 45435 | C38: Paid to Razi (Cargo Charges) | E38: 180 | F38: =F37+D38-E38 -> 37930
B39: 45436 | C39: Bill No SR0019 | E39: 2100 | F39: =F38+D39-E39 -> 35830
B40: 45437 | C40: Bill No SI0020 | D40: 22700 | F40: =F39+D40-E40 -> 58530
B41: 45440 | C41: Cash Received From Wajahat (V3 import Charges + hamali charges) | E41: 1260 | F41: =F40+D41-E41 -> 57270
B42: 45441 | C42: Bill No SI0022 | D42: 34960 | F42: =F41+D42-E42 -> 92230
B43: 45441 | C43: Cash Received By A/R | E43: 34960 | F43: =F42+D43-E43 -> 57270
B44: 45442 | C44: Cash Received From Saad | E44: 35000 | F44: =F43+D44-E44 -> 22270
B45: 45444 | C45: Bill No SI0026 | D45: 1200 | F45: =F44+D45-E45 -> 23470
B46: 45444 | C46: Cash Received From Wajahat (Encell Shop Rent) | E46: 1333 | F46: =F45+D46-E46 -> 22137
B47: 45448 | C47: Cash Received From Saad | E47: 10000 | F47: =F46+D47-E47 -> 12137
B48: 45448 | C48: Bill No SI0030 | D48: 33600 | F48: =F47+D48-E48 -> 45737
B49: 45448 | C49: Cash Received From Saad | E49: 33600 | F49: =F48+D49-E49 -> 12137
B50: 45449 | C50: Bill No SI0031 | D50: 50400 | F50: =F49+D50-E50 -> 62537
B51: 45449 | C51: Cash Received From Saad | E51: 50400 | F51: =F50+D51-E51 -> 12137
B52: 45453 | C52: Cash Received From Saad | E52: 6030 | F52: =F51+D52-E52 -> 6107
B53: 45453 | C53: Bill No SI0034 | D53: 58800 | F53: =F52+D53-E53 -> 64907
B54: 45453 | C54: Starlink v3 47pcs Clearing charges | E54: 1465 | F54: =F53+D54-E54 -> 63442
B55: 45453 | C55: hamali charges | E55: 35 | F55: =F54+D55-E55 -> 63407
B56: 45453 | C56: Bill No SI0035 | D56: 21320 | F56: =F55+D56-E56 -> 84727
B57: 45454 | C57: Bill No SI0037 | D57: 19110 | F57: =F56+D57-E57 -> 103837
B58: 45455 | C58: Bill No SI0039 (Starlink V3) | D58: 3340 | F58: =F57+D58-E58 -> 107177
B59: 45455 | C59: Paid to Waseem Bhai Amgt By Saad | E59: 60640 | F59: =F58+D59-E59 -> 46537
B60: 45456 | C60: Bill No SI0040 (Starlink V3) | D60: 8350 | F60: =F59+D60-E60 -> 54887
B61: 45456 | C61: Payment From Saad | E61: 25980 | F61: =F60+D61-E61 -> 28907
B62: 45463 | C62: Bill No SI0044 | D62: 4800 | F62: =F61+D62-E62 -> 33707
B63: 45463 | C63: Payment From Saad (Suadi Riyal For AR) | E63: 10622 | F63: =F62+D63-E63 -> 23085
B64: 45463 | C64: Paid to Waseem Bhai Amgt By Saad | E64: 8350 | F64: =F63+D64-E64 -> 14735
B65: 45465 | C65: Bill No SI0046 | D65: 3060 | F65: =F64+D65-E65 -> 17795
B66: 45465 | C66: Bill No SI0047 | D66: 12670 | F66: =F65+D66-E66 -> 30465
B67: 45465 | C67: From Razi | D67: 2390 | F67: =F66+D67-E67 -> 32855
B68: 45465 | C68: Payment From Saad | E68: 24000 | F68: =F67+D68-E68 -> 8855
B69: 45467 | C69: Payment From Saad (online A/R A/C 76000 PKR) | E69: 1000 | F69: =F68+D69-E69 -> 7855
B70: 45469 | C70: Bill No SI0049 (V3 Bill) | D70: 41080 | F70: =F69+D70-E70 -> 48935
B71: 45469 | C71: Bill No SI0050 | D71: 5010 | F71: =F70+D71-E71 -> 53945
B72: 45469 | C72: Hamali Charges Paid | E72: 25 | F72: =F71+D72-E72 -> 53920
B73: 45469 | C73: Payment From Saad (V3 Payment) | E73: 41000 | F73: =F72+D73-E73 -> 12920
B74: 45469 | C74: Payment From Saad (paid to Tabish) | E74: 2000 | F74: =F73+D74-E74 -> 10920
B75: 45471 | C75: Bill No SI0051 (V3 Bill) | D75: 31500 | F75: =F74+D75-E75 -> 42420
B76: 45471 | C76: Payment From Saad (V3 Payment) | E76: 31350 | F76: =F75+D76-E76 -> 11070
B77: 45471 | C77: Cargo Charges Paid | E77: 100 | F77: =F76+D77-E77 -> 10970
B78: 45471 | C78: Hamali Charges Paid | E78: 50 | F78: =F77+D78-E78 -> 10920
B79: 45471 | C79: Bill No SI0052 | D79: 2720 | F79: =F78+D79-E79 -> 13640
B80: 45471 | C80: Payment From Saad | E80: 2720 | F80: =F79+D80-E80 -> 10920
B81: 45472 | C81: Bill No SI0053 | D81: 9800 | F81: =F80+D81-E81 -> 20720
B82: 45472 | C82: Cash From Saad | E82: 55 | F82: =F81+D82-E82 -> 20665
B83: 45474 | C83: Cash From Saad | E83: 10000 | F83: =F82+D83-E83 -> 10665
B84: 45474 | C84: Bill No SI0057 (13ProMax) | D84: 54175 | F84: =F83+D84-E84 -> 64840
B85: 45474 | C85: Bill No SI0058 (V3) | D85: 110160 | F85: =F84+D85-E85 -> 175000
B86: 45474 | C86: Payment From Saad (V3) | E86: 73200 | F86: =F85+D86-E86 -> 101800
B87: 45474 | C87: Cargo Charges Paid (V3) | E87: 1050 | F87: =F86+D87-E87 -> 100750
B88: 45474 | C88: Hamali Charges (V3) | E88: 60 | F88: =F87+D88-E88 -> 100690
B89: 45474 | C89: Payment From Saad (V3) | E89: 1525 | F89: =F88+D89-E89 -> 99165
B90: 45475 | C90: Payment From Saad (V3) | E90: 38250 | F90: =F89+D90-E90 -> 60915
B91: 45477 | C91: Bill No SI0060 | D91: 7500 | F91: =F90+D91-E91 -> 68415
B92: 45478 | C92: Bill No SI0062 | D92: 46500 | F92: =F91+D92-E92 -> 114915
B93: 45478 | C93: Bill No SI0063 | D93: 2660 | F93: =F92+D93-E93 -> 117575
B94: 45478 | C94: Cash From Wajahat | E94: 46500 | F94: =F93+D94-E94 -> 71075
B95: 45479 | C95: Cash From Saad | E95: 50000 | F95: =F94+D95-E95 -> 21075
B96: 45479 | C96: Cash From Saad | E96: 10000 | F96: =F95+D96-E96 -> 11075
B97: 45480 | C97: Bill No SI0064 | D97: 29380 | F97: =F96+D97-E97 -> 40455
B98: 45481 | C98: Cash From Saad | E98: 1333 | F98: =F97+D98-E98 -> 39122
B99: 45481 | C99: Cash From Wajahat | E99: 1860 | F99: =F98+D99-E99 -> 37262
B100: 45482 | C100: Bill No SI0065 (V3) | D100: 40125 | F100: =F99+D100-E100 -> 77387
B101: 45482 | C101: Cash From Saad (V3) | E101: 40075 | F101: =F100+D101-E101 -> 37312
B102: 45482 | C102: Cash From Saad (V3) | E102: 50 | F102: =F101+D102-E102 -> 37262
B103: 45484 | C103: Bill No SI0067 (V3) | D103: 93080 | F103: =F102+D103-E103 -> 130342
B104: 45484 | C104: Cash From Saad (V3) | E104: 92910 | F104: =F103+D104-E104 -> 37432
...

Sheet final closing
D4: 45484 | E4: From Encell Shop (V3) | F4: 93080 | H4: =H3+F4-G4 -> 93080
D5: 45484 | E5: V3 Expense | G5: 100 | H5: =H4+F5-G5 -> 92980
D6: 45484 | E6: Irfan Customer (Discount By AR) | G6: 70 | H6: =H5+F6-G6 -> 92910
D7: 45485 | E7: Payment From Razi | F7: 10360 | H7: =H6+F7-G7 -> 103270
D8: 45485 | E8: Payment From Umar | F8: 1500 | H8: =H7+F8-G8 -> 104770
D9: 45485 | E9: Encell Shop Paid by Saad | F9: 40000 | H9: =H8+F9-G9 -> 144770
D10: 45485 | E10: Cash paid to Gatezone (12pcs Purchased) | G10: 24430 | H10: =H9+F10-G10 -> 120340
D11: 45486 | E11: Cash Paid to Faisal Bhai | G11: 3000 | H11: =H10+F11-G11 -> 117340
D12: 45487 | E12: Paid to Sasco (Payment Transfer Charges V3) | G12: 90 | H12: =H11+F12-G12 -> 117250
D13: 45487 | E13: From Encell Shop | F13: 180 | H13: =H12+F13-G13 -> 117430
D14: 45487 | E14: From Encell Shop | F14: 40 | H14: =H13+F14-G14 -> 117470
D15: 45487 | E15: From Encell Shop | F15: 1150 | H15: =H14+F15-G15 -> 118620
D16: 45487 | E16: 13 pro Max Camera repairing | G16: 180 | H16: =H15+F16-G16 -> 118440
D17: 45487 | E17: AR hamali Charges | G17: 20 | H17: =H16+F17-G17 -> 118420
D18: 45487 | E18: starlink hamali charges | G18: 20 | H18: =H17+F18-G18 -> 118400
D19: 45487 | E19: starlink cargo charges | G19: 1150 | H19: =H18+F19-G19 -> 117250
D20: 45491 | E20: From Encell Shop | F20: 51000 | H20: =H19+F20-G20 -> 168250
D21: 45491 | E21: Send To Australia | G21: 51000 | H21: =H20+F21-G21 -> 117250
D22: 45491 | E22: From Encell Shop | F22: 950 | H22: =H21+F22-G22 -> 118200
D23: 45491 | E23: starlink cargo charges | G23: 950 | H23: =H22+F23-G23 -> 117250
D24: 45491 | E24: From Encell Shop | F24: 20 | H24: =H23+F24-G24 -> 117270
D25: 45491 | E25: starlink hamali charges | G25: 20 | H25: =H24+F25-G25 -> 117250
D26: 45491 | E26: From Encell Shop | F26: 30 | H26: =H25+F26-G26 -> 117280
D27: 45491 | E27: From Encell Shop | F27: 50000 | H27: =H26+F27-G27 -> 167280
D28: 45491 | E28: Deposit A/R Card | G28: 30000 | H28: =H27+F28-G28 -> 137280
D29: 45491 | E29: Deposit Ashfaq Sahab Card | G29: 20000 | H29: =H28+F29-G29 -> 117280
D30: 45493 | E30: Cash From Encell Shop (Handover To Faisal Bhai ) | F30: 14000 | H30: =H29+F30-G30 -> 131280
D31: 45493 | E31: AR Card Deposit | G31: 30000 | H31: =H30+F31-G31 -> 101280
D32: 45494 | E32: AR Card Deposit | G32: 20000 | H32: =H31+F32-G32 -> 81280
D33: 45495 | E33: Paid to Faisal Bhai by Wajahat | G33: 3000 | H33: =H32+F33-G33 -> 78280
E34: Faheem | G34: 400 | H34: =H33+F34-G34 -> 77880
H35: =H34+F35-G35 -> 77880
D41: Cash In Hand | E41: =#REF! -> #REF!
D42: Cash At meezan Bank | E42: 0
D43: Cash at ENBD Card | E43: 18604
D44: Cash at Dubai Islamic Bank | E44: ='AR Bank Accounts'!#REF!-25000 -> #REF!
D45: Receivable PKR | E45: 4747428
D46: Receivable Aed | E46: 25732
D47: Stock Value | E47: 63968
D49: Payable PKR | E49: -2226667
D50: Payable AED | E50: -29416
D57: Meezan Bank | E57: =19607/77 -> 254.63636
D58: Dubai islamic Bank | E58: 49838.83
D59: ENBD A/C | E59: 705.63
E61: 0
D63: Karachi Party Balances | E63: =-903547/77 -> -11734.377
D64: Dubai Party Balances | E64: -73521
D66: Stock Value | E66: 139705
D68: Net | E68: =SUM(E57:E67) -> 105248.72
E69: -31312
E71: =SUM(E68:E70) -> 73936.72
E72: PKR | F72: AED
C73: Stock | D73: Stock Value | F73: 55213
C75: Payment
D76: Cash at Meezan A/C | E76: 1321220.9 | F76: =E76/77.5 -> 17048.011
D77: Cash at DIB A/C | F77: 33764.8
D78: Cash at ENBD A/C | F78: 1837
D79: Cash in karachi Office | E79: 90500 | F79: =E79/77.5 -> 1167.7419
C82: Receivable | D82: Danish | E82: 560000 | F82: =560000/77.5 -> 7225.8065
D83: Daniyal Karachi | E83: 200000 | F83: =200000/77.5 -> 2580.6452
D84: Machine Payment | F84: 4350
D85: umer Gujranwala | F85: 100
D86: Salman (Al-badar) | F86: 11314
D87: Mudassir bhai | E87: 114413 | F87: =E87/77.5 -> 1476.2968
F88: =SUM(F73:F86) -> 134601
C89: Payables
D90: EuroNext Shop | E90: 901922 | F90: =901922/77.5 -> 11637.703
D91: AMGT | F91: 14000
D92: Abdul Majid Bhai | F92: 32370
F93: =SUM(F90:F92) -> 58007.703
D95: Net Profit | F95: =F88-F93 -> 76593.301
B98: 45631 | E98: PKR | F98: AED
C99: Stock | D99: Stock Value | F99: 28299
C101: Payment
D102: Cash at Meezan A/C | E102: 1602631.9 | F102: =E102/77.5 -> 20679.121
D103: Cash at DIB A/C | F103: 33764.8
D104: Cash at ENBD A/C | F104: 1827
D105: Cash in karachi Office | E105: 2108731 | F105: =E105/77.5 -> 27209.432
C108: Receivable | D108: Danish | E108: 560000 | F108: =560000/77.5 -> 7225.8065
D109: Daniyal Karachi | E109: 200000 | F109: =200000/77.5 -> 2580.6452
D110: Machine Payment | F110: 4350
D111: umer Gujranwala | F111: 100
D112: Salman (Al-badar) | F112: 11314
D113: Mudassir bhai | E113: 114413 | F113: =E113/77.5 -> 1476.2968
F114: =SUM(F99:F113) -> 138826.1
C115: Payables
D116: EuroNext Shop | E116: 901922 | F116: =901922/77.5 -> 11637.703
D117: AMGT | F117: 14000
D118: Abdul Majid Bhai | F118: 32370
F119: =SUM(F116:F118) -> 58007.703
D121: Net Profit | F121: =F114-F119 -> 80818.398
K170: CLOSING STOCK
I171: 45580 | J171: in USA | K171: Old 3Units 15ProMax | L171: 3 | N171: =577000/77.5 -> 7445.1613
I172: 45580 | J172: in USA | K172: 4unit 15Promax 256GB @188,000 | L172: 4 | N172: =752000/77.5 -> 9703.2258 | Q172: =188000*4 -> 752000
I173: 45580 | J173: in USA | K173: 1unit Watch Ultra @175,000 | L173: 1 | N173: =175000/77.5 -> 2258.0645
I174: 45580 | J174: in USA | K174: 3Units IP 16Plus @160000 | L174: 3 | N174: =480000/77.5 -> 6193.5484 | Q174: =160000*3 -> 480000
I176: 45580 | J176: In Dubai | K176: IP 15ProMax 256 | L176: 1 | N176: 2623
I177: 45580 | J177: In Dubai | K177: IP 15ProMax 512 | L177: 1 | N177: 4428
I178: 45580 | J178: In Dubai | K178: IP 15Pro 128GB | L178: 1 | N178: 3186
I179: 45580 | J179: In Dubai | K179: IP 14Plus 128GB | L179: 1 | N179: 1450
...

Sheet Vendor Ledger
A3: Vendor Name : | C3: Muhammad Usman
B5: Date | C5: Particular | D5: Dr | E5: Cr | F5: Balance
B7: 45405 | C7: Bill No PI0001 | E7: =Pur.Invoice!F21 -> 18375 | F7: =F6+D7-E7 -> -18375
B8: 45405 | C8: Bill No PI0002 | E8: =Pur.Invoice!F43 -> 23650 | F8: =F7+D8-E8 -> -42025
B9: 45405 | C9: Bill No PI0003 | E9: =Pur.Invoice!F74 -> 9999.99 | F9: =F8+D9-E9 -> -52024.99
B10: 45405 | C10: Bill No PI0004 | E10: =Pur.Invoice!F123 -> 31000 | F10: =F9+D10-E10 -> -83024.99
B11: 45406 | C11: From A/R Meezan A/C 15lacs | D11: 19607.84 | F11: =F10+D11-E11 -> -63417.15
B12: 45406 | C12: From EuroNext Meezan A/C 2.5lacs | D12: 3267.97 | F12: =F11+D12-E12 -> -60149.18
B13: 45406 | C13: From EuroNext Meezan A/C 2.5lacs | D13: 3267.97 | F13: =F12+D13-E13 -> -56881.21
B14: 45419 | C14: Paid By A/R | D14: 26000 | F14: =F13+D14-E14 -> -30881.21
B15: 45421 | C15: adjustment By A/R | D15: 30001.21 | F15: =F14+D15-E15 -> -880
F16: =F15+D16-E16 -> -880
C17: Paid By A/R For New Shipment | D17: 50000 | F17: =F16+D17-E17 -> 49120
B18: 45453 | C18: Shipment Clearing Charges | D18: 760 | E18: 760 | F18: =F17+D18-E18 -> 49120
B19: 45453 | C19: Bill No PI0003 | E19: 129728.22 | F19: =F18+D19-E19 -> -80608.22 | G19: Updated 02/07/2024 | H19: 2 iphone 15 kit discount $10
B20: 45456 | C20: From Encell Shop | D20: 50000 | F20: =F19+D20-E20 -> -30608.22 | H20: 1 iphone 15pm kit discount $30
B21: 45474 | C21: 5pcs Returned Invoice PR0022 | D21: 13887.72 | F21: =F20+D21-E21 -> -16720.5 | H21: Watch ultra Purchased
B22: 45497 | C22: 24pcs Returned PR0029 | D22: 1304.27 | F22: =F21+D22-E22 -> -15416.23
B23: 45500 | C23: Payment By Wajahat | D23: 10000 | F23: =F22+D23-E23 -> -5416.23
F24: =F23+D24-E24 -> -5416.23
F25: =F24+D25-E25 -> -5416.23
F26: =F25+D26-E26 -> -5416.23
C27: TOTAL BALANCE | F27: =F26+D27-E27 -> -5416.23
A30: Vendor Name : | C30: ALI KARACHI
B32: Date | C32: Particular | D32: Dr | E32: Cr | F32: Balance
C34: Old Balance | D34: 94813.52 | F34: =F33+D34-E34 -> 94813.52
B35: 45405 | C35: Bill No PI0005 | E35: 154324 | F35: =F34+D35-E35 -> -59510.48
B36: 45420 | C36: Payment By A/R To AMGT | D36: 40000 | F36: =F35+D36-E36 -> -19510.48
B37: 45420 | C37: Payment By A/R To AMGT | D37: 20000 | F37: =F36+D37-E37 -> 489.52
B38: 45420 | C38: Payment By A/R To AMGT | D38: 10000 | F38: =F37+D38-E38 -> 10489.52
B39: 45412 | C39: Unlocking Mar-2024 | E39: 534.86 | F39: =F38+D39-E39 -> 9954.66
C40: Hamali Charges | E40: 40 | F40: =F39+D40-E40 -> 9914.66
B41: 45423 | C41: Payment | D41: 3455 | F41: =F40+D41-E41 -> 13369.66
B42: 45426 | C42: Bill No PI0006 | E42: 56288 | F42: =F41+D42-E42 -> -42918.34
B43: 45427 | C43: Cash Payment From Encell Shop | D43: 50000 | F43: =F42+D43-E43 -> 7081.66
B44: 45427 | C44: Hamali Charges | E44: 10 | F44: =F43+D44-E44 -> 7071.66
B45: 45442 | C45: Paid by A/R | D45: 35000 | F45: =F44+D45-E45 -> 42071.66
B46: 45442 | C46: Cash ??? | E46: 4903 | F46: =F45+D46-E46 -> 37168.66
B47: 45443 | C47: Unlocking May-2024 | E47: 527.77 | F47: =F46+D47-E47 -> 36640.89
B48: 45447 | C48: Bill No PI0012 | E48: 44886 | F48: =F47+D48-E48 -> -8245.11 | G48: 1632
B49: 45448 | C49: Shipping And Custome Charges | E49: 1938.51 | F49: =F48+D49-E49 -> -10183.62
B50: 45448 | C50: Cash Payment From Encell Shop | D50: 10000 | F50: =F49+D50-E50 -> -183.62
B51: 45453 | C51: Cash ??? | D51: 760 | F51: =F50+D51-E51 -> 576.38
B52: 45453 | C52: Paid to Waseem Amgt | D52: 3000 | F52: =F51+D52-E52 -> 3576.38
B53: 45454 | C53: Bill No PI0018 | E53: 55588 | F53: =F52+D53-E53 -> -52011.62 | G53: 1991.69
B54: 45454 | C54: Invoice ??? | E54: 315.51 | F54: =F53+D54-E54 -> -52327.13
B55: 45458 | C55: Cash (Encell Shop Riyal payment) | D55: 10622 | F55: =F54+D55-E55 -> -41705.13
B56: 45465 | C56: Cash (Encell Shop) | D56: 24000 | F56: =F55+D56-E56 -> -17705.13
B57: 45467 | C57: Invoice??? | E57: 34125 | F57: =F56+D57-E57 -> -51830.13
B58: 45469 | C58: Paid by A/R | D58: 20000 | F58: =F57+D58-E58 -> -31830.13
B59: 45468 | C59: V3 Hamali Charges | E59: 60 | F59: =F58+D59-E59 -> -31890.13
B60: 45468 | C60: V3 Clearing Charges | E60: 1350 | F60: =F59+D60-E60 -> -33240.13
B61: 45472 | C61: Cash By A/R | D61: 4950 | F61: =F60+D61-E61 -> -28290.13
B62: 45472 | C62: Cash By A/R | D62: 10700 | F62: =F61+D62-E62 -> -17590.13
B63: 45472 | C63: Cash By A/R | D63: 10000 | F63: =F62+D63-E63 -> -7590.13
B64: 45475 | C64: Cash By A/R | D64: 7600 | F64: =F63+D64-E64 -> 9.87
F65: =F64+D65-E65 -> 9.87
C66: TOTAL BALANCE | F66: =F65+D66-E66 -> 9.87
A69: Vendor Name : | C69: SHOAIB
B71: Date | C71: Particular | D71: Dr | E71: Cr | F71: Balance
B73: 45429 | C73: Bill No PI0007 | E73: 8350 | F73: =F72+D73-E73 -> -8350
B74: 45444 | C74: Bill No SI0027 | D74: 4950 | F74: =F73+D74-E74 -> -3400
B75: 45479 | C75: Cash by A/R | D75: 10000 | F75: =F74+D75-E75 -> 6600
B76: 45498 | C76: Adjustment Euronext Bill (11593) | E76: 6600 | F76: =F75+D76-E76 -> 0
F77: =F76+D77-E77 -> 0
F78: =F77+D78-E78 -> 0
C79: TOTAL BALANCE | F79: =F78+D79-E79 -> 0
A83: Vendor Name : | C83: RAZI
B85: Date | C85: Particular | D85: Dr | E85: Cr | F85: Balance
B87: 45448 | C87: Bill No PI0013 | E87: 6150 | F87: =F86+D87-E87 -> -6150
B88: 45455 | C88: Paid to Razi By A/R | D88: 6150 | F88: =F87+D88-E88 -> 0
F89: =F88+D89-E89 -> 0
F90: =F89+D90-E90 -> 0
F91: =F90+D91-E91 -> 0
F92: =F91+D92-E92 -> 0
C93: TOTAL BALANCE | F93: =F92+D93-E93 -> 0
A97: Vendor Name : | C97: GATEZONE
B99: Date | C99: Particular | D99: Dr | E99: Cr | F99: Balance
B101: 45488 | C101: Bill No PI0024 | E101: 24900 | F101: =F100+D101-E101 -> -24900
B102: 45488 | C102: Cash Paid by AR | D102: 24430 | F102: =F101+D102-E102 -> -470
B103: 45502 | C103: Discount By A/R | D103: 470 | F103: =F102+D103-E103 -> 0
B104: 45497 | C104: Bill No PI0027 | E104: 13560 | F104: =F103+D104-E104 -> -13560
B105: 45497 | C105: Cash Paid by Faisal Bhai | D105: 13560 | F105: =F104+D105-E105 -> 0
F106: =F105+D106-E106 -> 0
C107: TOTAL BALANCE | F107: =F106+D107-E107 -> 0
A110: Vendor Name : | C110: AR Wireless Canada
B112: Date | C112: Particular | D112: Dr | E112: Cr | F112: Balance
B114: 45516 | C114: Paid to Razi Canada Purchasing | D114: 5050 | F114: =F113+D114-E114 -> 5050
B115: 45516 | C115: Expense | E115: 50 | F115: =F114+D115-E115 -> 5000
B116: 45517 | C116: PI0035 28Units | E116: 75465 | F116: =F115+D116-E116 -> -70465
B117: 45517 | C117: Wire Charges | E117: 200 | F117: =F116+D117-E117 -> -70665
B118: 45517 | C118: Cash Handling Charges | E118: 110 | F118: =F117+D118-E118 -> -70775
B119: 45517 | C119: Payment From Encell Shop | D119: 70775 | F119: =F118+D119-E119 -> 0
B120: 45519 | C120: Hamali Charges | D120: 20 | E120: 20 | F120: =F119+D120-E120 -> 0
B121: 45519 | C121: Taxi Charges | D121: 70 | E121: 70 | F121: =F120+D121-E121 -> 0
F122: =F121+D122-E122 -> 0
B123: 45527 | C123: PI0036 13Units | E123: =Pur.Invoice!F1078 -> 45306 | F123: =F122+D123-E123 -> -45306
B124: 45531 | C124: Payment from Sultan 11480 CAD | D124: =11480*2.7 -> 30996 | F124: =F123+D124-E124 -> -14310 | I124: AED
B125: 45531 | C125: Abdul Majid Bhai 3100 CAD | D125: =3100*2.7 -> 8370 | F125: =F124+D125-E125 -> -5940 | I125: 8100
B126: 45531 | C126: Abdul Majid Bhai 2200 CAD | D126: =2200*2.7 -> 5940 | F126: =F125+D126-E126 -> 3.6379788e-12
...

Sheet IMEI Record
B2: Vendor Name | C2: Ali Karachi
B3: Date | C3: 45409
B4: Bill # | C4: PI0005
C5: Model | D5: Imei
C7: iPhone 13 Pro Max | D7: 359272538672231
C8: iPhone 13 Pro Max | D8: 358226363284224
C9: iPhone 13 Pro Max | D9: 352206206248129
C10: iPhone 13 Pro Max | D10: 352569487339366
C11: iPhone 13 Pro Max | D11: 352569482118625
C12: iPhone 11 Pro | D12: 353243103508718
C13: iPhone 11 Pro Max | D13: 353901105081428
C14: iPhone 11 Pro Max | D14: 353898100810571
C15: iPhone 11 Pro Max | D15: 353906102600203
C17: iPhone 13 Pro Max | D17: 358677238942364
C18: iPhone 13 Pro Max | D18: 356370168789391
... C149: iPhone 13 Pro Max | D149: 350419539067031
B151: Vendor Name | C151: Ali Karachi
B152: Date | C152: 45426
B153: Bill # | C153: PI0006
C154: Model | D154: Imei
B157: Invoice 1 | C157: Apple / iPhone 13 Pro Max / A2484 / 256GB / Gold / ATT / LOCKED / TPS B+ | D157: 350419531801221
C158: Apple / iPhone 13 Pro Max / A2484 / 256GB / Gold / ATT / LOCKED / TPS B+ | D158: 350879908057279
C159: Apple / iPhone 13 Pro Max / A2484 / 256GB / Gold / ATT / LOCKED / TPS B+ | D159: 353282623901839
C160: Apple / iPhone 13 / A2482 / 128GB / Midnight / Other / LOCKED / TPS B+ | D160: 357774339917303
C161: Apple / iPhone 13 Pro Max / A2484 / 256GB / Sierra Blue / Other / LOCKED / TPS B+ | D161: 350566102429814
C162: Apple / iPhone 13 Pro Max / A2484 / 256GB / Sierra Blue / Other / LOCKED / TPS B+ | D162: 353210482274550
C163: Apple / iPhone 13 / A2482 / 128GB / Green / Other / LOCKED / TPS B+ | D163: 350555046945225
C164: Apple / iPhone 13 / A2482 / 128GB / Green / Other / LOCKED / TPS B+ | D164: 354455405036508
C165: Apple / iPhone 13 / A2482 / 128GB / Green / Other / LOCKED / TPS B+ | D165: 359175929817986
C166: Apple / iPhone 11 Pro Max / A2161 / 512GB / Green / T-Mobile / LOCKED / TPS C+ | D166: 352838116444875
C167: Apple / iPhone 11 Pro Max / A2161 / 256GB / Grey / Unlocked / UNLOCKED / TPS C+ | D167: 352843112285413
C168: Apple / iPhone 11 Pro Max / A2161 / 256GB / Grey / Unlocked / UNLOCKED / TPS C+ | D168: 352844114944262
C169: Apple / iPhone 11 Pro Max / A2161 / 256GB / Grey / Unlocked / UNLOCKED / TPS C+ | D169: 352849114333382
... C177: Apple / iPhone 11 Pro Max / A2218 / 256GB / Grey / Unlocked / UNLOCKED / TPS C+ | D177: 353916104988365
B179: Invoice 2 | C179: Apple / iPhone 12 Pro Max / A2342 / 256GB / Graphite / ATT / LOCKED / TPS A+ | D179: 358686416816894
C180: Apple / iPhone 12 Pro Max / A2342 / 256GB / Graphite / Other / LOCKED / TPS A+ | D180: 354741660139735
C181: Apple / iPhone 13 Pro Max / A2484 / 256GB / Gold / Other / LOCKED / TPS A+ | D181: 352569484750532
C182: Apple / iPhone 13 Pro Max / A2484 / 256GB / Sierra Blue / ATT / LOCKED / TPS B+ | D182: 352396477711747
C183: Apple / iPhone 13 Pro Max / A2484 / 256GB / Sierra Blue / ATT / LOCKED / TPS B+ | D183: 357447886566522
C184: Apple / iPhone 13 / A2482 / 128GB / Blue / Other / LOCKED / TPS B+ | D184: 350225646859065
C185: Apple / iPhone 13 / A2482 / 128GB / Blue / Other / LOCKED / TPS B+ | D185: 350555043566156
C186: Apple / iPhone 13 / A2482 / 128GB / Blue / Other / LOCKED / TPS B+ | D186: 350980293501861
C187: Apple / iPhone 13 / A2482 / 128GB / Blue / Other / LOCKED / TPS B+ | D187: 352941881432180
C188: Apple / iPhone 13 / A2482 / 128GB / Blue / Other / LOCKED / TPS B+ | D188: 354066785774129
C189: Apple / iPhone 13 / A2482 / 128GB / Blue / Other / LOCKED / TPS B+ | D189: 356815607149417
C190: Apple / iPhone 13 Pro Max / A2484 / 128GB / Sierra Blue / Other / LOCKED / TPS B+ | D190: 350879903491598
C191: Apple / iPhone 13 Pro Max / A2484 / 128GB / Sierra Blue / Other / LOCKED / TPS B+ | D191: 358800350734100
... C209: Apple / iPhone 12 Pro / A2341 / 256GB / Silver / Unlocked / UNLOCKED / TPS C+ | D209: 350522072314353
B211: Vendor Name | C211: SHOAIB
B212: Date | C212: 45429
B213: Bill # | C213: PI0007
C214: Model | D214: Imei
C216: MUGHAL ELECTRONICS
C217: SALES INVOICE
C218: 45428
C220: IC ZDA 15 128 GREEN INSIDE BLUE [1] 500 | D220: 353927428469404
C221: INSIDE IMEI | D221: 359817437335072
C222: IC 15 128 PINK [1] 500 | D222: 356630554968622 | E222: unlocking Charges
C223: IC ZDA 15 PRO 128 BLACK [1] 900 | D223: 354321299423253 | E223: unlocking Charges
C224: IC ZDA 15 PLUS 128 BLUE GREEN INSIDE [1] 500 | D224: 354660209965204
C225: INSIDE IMEI | D225: 356223813233605
C227: IC KIT 13 128 RED [300] | D227: 350196696839853
C228: UN ZDA ACT KIT 15 PLUS 128 GREEN [1] 2200 | D228: 354660209965204
C229: CA KIT 15 PRO MAX 256 NAT [1] 3450 | D229: 354645219905688
B231: Vendor Name | C231: MUDASSIR AR
B232: Date | C232: 45441
B233: Bill # | C233: PI0009
C234: Model | D234: Imei
C236: IPHONE 15 PRO MAX 256GB | D236: 352676524721637
B239: Vendor Name | C239: Ali Karachi
B240: Date | C240: 45447
B241: Bill # | C241: PI0012
C242: Model | D242: Imei
G243: AED | H243: other charges Add
B244: Invoice 1 | C244: Apple / iPhone 11 Pro / A2160 / 256GB / Gold / Verizon / UNLOCKED / TPS C+ | D244: 353232102515253 | E244: 205 | F244: 3.674 | G244: =E244*F244 -> 753.17 | H244: 37.09 | I244: =G244+H244 -> 790.26
C245: Apple / iPhone 11 Pro / A2160 / 256GB / Gold / Verizon / UNLOCKED / TPS C+ | D245: 353248105513475 | E245: 205 | F245: 3.674 | G245: =E245*F245 -> 753.17 | H245: 37.09 | I245: =G245+H245 -> 790.26
C246: Apple / iPhone 11 Pro / A2160 / 512GB / Gold / Verizon / UNLOCKED / TPS C+ | D246: 353236103122555 | E246: 205 | F246: 3.674 | G246: =E246*F246 -> 753.17 | H246: 37.09 | I246: =G246+H246 -> 790.26
C247: Apple / iPhone 11 Pro Max / A2161 / 256GB / Grey / Verizon / UNLOCKED / TPS C+ | D247: 352852111541080 | E247: 243 | F247: 3.674 | G247: =E247*F247 -> 892.782 | H247: 37.09 | I247: =G247+H247 -> 929.872
C248: Apple / iPhone 11 Pro Max / A2161 / 256GB / Grey / Verizon / UNLOCKED / TPS C+ | D248: 353895109719159 | E248: 243 | F248: 3.674 | G248: =E248*F248 -> 892.782 | H248: 37.09 | I248: =G248+H248 -> 929.872
C249: Apple / iPhone 11 Pro Max / A2161 / 256GB / Grey / Verizon / UNLOCKED / TPS C+ | D249: 353898108385550 | E249: 243 | F249: 3.674 | G249: =E249*F249 -> 892.782 | H249: 37.09 | I249: =G249+H249 -> 929.872
C250: Apple / iPhone 13 Pro Max / A2484 / 256GB / Graphite / ATT / LOCKED / TPS C+ | D250: 359272531296616 | E250: 412 | F250: 3.674 | G250: =E250*F250 -> 1513.688 | H250: 37.09 | I250: =G250+H250 -> 1550.778
C251: Apple / iPhone 11 Pro Max / A2218 / 256GB / Grey / Unlocked / UNLOCKED / TPS C+ | D251: 352862110068381 | E251: 243 | F251: 3.674 | G251: =E251*F251 -> 892.782 | H251: 37.09 | I251: =G251+H251 -> 929.872
C252: Apple / iPhone 11 Pro Max / A2218 / 256GB / Grey / Unlocked / UNLOCKED / TPS C+ | D252: 353911108155343 | E252: 243 | F252: 3.674 | G252: =E252*F252 -> 892.782 | H252: 37.09 | I252: =G252+H252 -> 929.872
C253: Apple / iPhone 11 Pro Max / A2218 / 256GB / Grey / Unlocked / UNLOCKED / TPS C+ | D253: 353915108783228 | E253: 243 | F253: 3.674 | G253: =E253*F253 -> 892.782 | H253: 37.09 | I253: =G253+H253 -> 929.872
C254: Apple / iPhone 11 Pro Max / A2218 / 256GB / Grey / Unlocked / UNLOCKED / TPS C+ | D254: 353926102230439 | E254: 243 | F254: 3.674 | G254: =E254*F254 -> 892.782 | H254: 37.09 | I254: =G254+H254 -> 929.872
C255: Apple / iPhone 11 Pro Max / A2218 / 256GB / Grey / Unlocked / UNLOCKED / TPS C+ | D255: 353926105563877 | E255: 243 | F255: 3.674 | G255: =E255*F255 -> 892.782 | H255: 37.09 | I255: =G255+H255 -> 929.872
B258: Invoice 2 | C258: Apple / iPhone 13 Pro Max / A2484 / 256GB / Graphite / T-Mobile / LOCKED / TPS A+ | D258: 358074294645513 | E258: 430 | F258: 3.674 | G258: =E258*F258 -> 1579.82 | H258: 37.09 | I258: =G258+H258 -> 1616.91
C259: Apple / iPhone 13 Pro Max / A2484 / 256GB / Silver / Other / LOCKED / TPS A+ | D259: 350019045832868 | E259: 430 | F259: 3.674 | G259: =E259*F259 -> 1579.82 | H259: 37.09 | I259: =G259+H259 -> 1616.91
C260: Apple / iPhone 13 Pro Max / A2484 / 512GB / Sierra Blue / T-Mobile / LOCKED / TPS B+ | D260: 355387491207694 | E260: 430 | F260: 3.674 | G260: =E260*F260 -> 1579.82 | H260: 37.09 | I260: =G260+H260 -> 1616.91
C261: Apple / iPhone 13 Pro Max / A2484 / 256GB / Silver / ATT / LOCKED / TPS B+ | D261: 357680883150300 | E261: 430 | F261: 3.674 | G261: =E261*F261 -> 1579.82 | H261: 37.09 | I261: =G261+H261 -> 1616.91
C262: Apple / iPhone 13 Pro Max / A2484 / 256GB / Graphite / Other / LOCKED / TPS B+ | D262: 358800359651651 | E262: 430 | F262: 3.674 | G262: =E262*F262 -> 1579.82 | H262: 37.09 | I262: =G262+H262 -> 1616.91
C263: Apple / iPhone 13 Pro Max / A2484 / 256GB / Gold / Other / LOCKED / TPS B+ | D263: 352114956483989 | E263: 425 | F263: 3.674 | G263: =E263*F263 -> 1561.45 | H263: 37.09 | I263: =G263+H263 -> 1598.54
C264: Apple / iPhone 13 Pro Max / A2484 / 256GB / Silver / Other / LOCKED / TPS B+ | D264: 353282624489438 | E264: 430 | F264: 3.674 | G264: =E264*F264 -> 1579.82 | H264: 37.09 | I264: =G264+H264 -> 1616.91
C265: Apple / iPhone 13 Pro Max / A2484 / 256GB / Sierra Blue / Other / LOCKED / TPS B+ | D265: 352996435050789 | E265: 430 | F265: 3.674 | G265: =E265*F265 -> 1579.82 | H265: 37.09 | I265: =G265+H265 -> 1616.91
C266: Apple / iPhone 11 / A2111 / 128GB / Red / Other / LOCKED / TPS C+ | D266: 352908116115401 | E266: 120 | F266: 3.674 | G266: =E266*F266 -> 440.88 | H266: 37.09 | I266: =G266+H266 -> 477.97
C267: Apple / iPhone 11 Pro / A2160 / 256GB / Silver / Verizon / UNLOCKED / TPS C+ | D267: 353233101822609 | E267: 205 | F267: 3.674 | G267: =E267*F267 -> 753.17 | H267: 37.09 | I267: =G267+H267 -> 790.26
C268: Apple / iPhone 11 Pro / A2160 / 256GB / Silver / Verizon / UNLOCKED / TPS C+ | D268: 353242100609586 | E268: 205 | F268: 3.674 | G268: =E268*F268 -> 753.17 | H268: 37.09 | I268: =G268+H268 -> 790.26
C269: Apple / iPhone 11 Pro / A2160 / 256GB / Green / Verizon / UNLOCKED / TPS C+ | D269: 353250101825820 | E269: 202 | F269: 3.674 | G269: =E269*F269 -> 742.148 | H269: 37.09 | I269: =G269+H269 -> 779.238
C270: Apple / iPhone 11 Pro Max / A2161 / 256GB / Grey / Verizon / UNLOCKED / TPS C+ | D270: 352852113165888 | E270: 241 | F270: 3.674 | G270: =E270*F270 -> 885.434 | H270: 37.09 | I270: =G270+H270 -> 922.524
... C289: Apple / iPhone 11 Pro Max / A2220 / 256GB / Grey / Unlocked / UNLOCKED / TPS C+ | D289: 353951100826012 | E289: 241 | F289: 3.674 | G289: =E289*F289 -> 885.434 | H289: 37.09 | I289: =G289+H289 -> 922.524
...

Sheet Sell.Invoice
B3: Sell Invoice
B5: Bill No: | C5: SI0001
B7: Name: | C7: Saad & Wajahat Encell Shop | D7: Date: | E7: 45405
B8: Contact
B9: Add:
B11: S.No | C11: Particulars | D11: Rate | E11: Qnty | F11: Amount
B13: 1 | C13: S22 Ultra | D13: 962.5 | E13: 4 | F13: =D13*E13 -> 3850
B14: 2 | C14: Note 20Ultra | D14: 962.5 | E14: 1 | F14: =D14*E14 -> 962.5
B15: 3 | C15: S21 | D15: 962.5 | E15: 3 | F15: =D15*E15 -> 2887.5
B16: 4 | C16: S21Plus | D16: 962.5 | E16: 1 | F16: =D16*E16 -> 962.5
B17: 5 | C17: S23 Ultra | D17: 962.5 | E17: 2 | F17: =D17*E17 -> 1925
B18: 6 | C18: S23Plus | D18: 962.5 | E18: 1 | F18: =D18*E18 -> 962.5
B23: Total | F23: =SUM(F13:F22) -> 11550
L25: EuroNext | M25: SI0025
B26: Sell Invoice
B28: Bill No: | C28: SI0002
B30: Name: | C30: Saad & Wajahat Encell Shop | D30: Date: | E30: 45405
B31: Contact
B32: Add:
B34: S.No | C34: Particulars | D34: Rate | E34: Qnty | F34: Amount
B36: 1 | C36: IP 11 64Gb Box | D36: 620 | E36: 5 | F36: =D36*E36 -> 3100
B37: 2 | C37: IP 15Pro 128Gb (Lock) | D37: 2050 | E37: 1 | F37: =D37*E37 -> 2050
B38: 3 | C38: S24 Ultra | D38: 2600 | E38: 1 | F38: =D38*E38 -> 2600
B39: 4 | C39: S24 | D39: 1350 | E39: 1 | F39: =D39*E39 -> 1350
B43: Total | F43: =SUM(F36:F42) -> 9100
B46: Sell Invoice
B48: Bill No: | C48: SI0003
B50: Name: | C50: Saad & Wajahat Encell Shop | D50: Date: | E50: 45405
B51: Contact
B52: Add:
B54: S.No | C54: Particulars | D54: Rate | E54: Qnty | F54: Amount
B56: 1 | C56: S24 | D56: 1350 | E56: 4 | F56: =D56*E56 -> 5400
B57: 2 | C57: S24 Ultra | D57: 2600 | E57: 7 | F57: =D57*E57 -> 18200
B58: 3 | C58: Fold 5 | D58: 1900 | E58: 1 | F58: =D58*E58 -> 1900
B63: Total | F63: =SUM(F56:F62) -> 25500
B66: Sell Invoice
B68: Bill No: | C68: SI0004
B70: Name: | C70: Saad & Wajahat Encell Shop | D70: Date: | E70: 45405
B71: Contact
B72: Add:
B74: S.No | C74: Particulars | D74: Rate | E74: Qnty | F74: Amount
B76: 1 | C76: Pixel 6A 01pcs | D76: 450 | E76: 1 | F76: =D76*E76 -> 450
B77: 2 | C77: IP 12pro 01pcs | D77: 1250 | E77: 1 | F77: =D77*E77 -> 1250
B78: 3 | C78: SE 3rd Gen 01pcs | D78: 400 | E78: 1 | F78: =D78*E78 -> 400
B79: 4 | C79: IP 13ProMax 02pcs @2100 | D79: 2100 | E79: 2 | F79: =D79*E79 -> 4200
B80: 5 | C80: IP 13Pro (Lock) 01pcs | D80: 1250 | E80: 1 | F80: =D80*E80 -> 1250
B81: 6 | C81: IP 14Pro (Lock) 01pcs | D81: 1600 | E81: 1 | F81: =D81*E81 -> 1600
B82: 7 | C82: IP 13ProMax (Lock) 01pcs | D82: 1500 | E82: 1 | F82: =D82*E82 -> 1500
B83: 8 | C83: IP 12 (Lock) 01pcs | D83: 650 | E83: 1 | F83: =D83*E83 -> 650
B84: 9 | C84: IP 13 (Lock) 02pcs @950 | D84: 950 | E84: 2 | F84: =D84*E84 -> 1900
B85: 10 | C85: IP 15 (Lock) 01pcs | D85: 1450 | E85: 1 | F85: =D85*E85 -> 1450
B86: 11 | C86: IP 15 MDM(Lock) 01pcs | D86: 1200 | E86: 1 | F86: =D86*E86 -> 1200
B90: Total | F90: =SUM(F76:F89) -> 15850
B93: Sell Invoice
B95: Bill No: | C95: SI0006
B97: Name: | C97: EURONEXT | D97: Date: | E97: 45414
B98: Contact
B99: Add:
B101: S.No | C101: Particulars | D101: Rate | E101: Qnty | F101: Amount
B103: 1 | C103: IP 15PRO MAX 512GB 353134983719808 | D103: 360000 | E103: 1 | F103: =D103*E103 -> 360000
F104: =D104*E104 -> 0
B108: Total | F108: =SUM(F103:F107) -> 360000 | G108: PKR
B113: Sell Invoice
B115: Bill No: | C115: SI0007
B116: Name | C116: Saad & Wajahat Encell Shop | D116: Date: | E116: 45415
B117: Contact
B118: Add:
B120: S.No | C120: Particulars | D120: Rate | E120: Qnty | F120: Amount
B122: 1 | C122: IP 11Pro 256Gb | D122: 840 | E122: 29 | F122: =D122*E122 -> 24360
B123: 2 | C123: IP 13ProMax 256Gb | D123: 2070 | E123: 20 | F123: =D123*E123 -> 41400
B124: 3 | C124: IP 11ProMax 256Gb | D124: 1130 | E124: 38 | F124: =D124*E124 -> 42940
B125: 4 | C125: IP 11 128GB | D125: 700 | E125: 2 | F125: =D125*E125 -> 1400
B126: 5 | C126: IP 12Pro 128GB | D126: 1100 | E126: 1 | F126: =D126*E126 -> 1100
B129: Total | F129: =SUM(F122:F128) -> 111200
B132: Sell Returned
B134: Bill No: | C134: SR0008
B136: Name: | C136: Saad & Wajahat Encell Shop | D136: Date: | E136: 45418
B137: Contact
B138: Add:
B140: S.No | C140: Particulars | D140: Rate | E140: Qnty | F140: Amount
B142: 1 | C142: IP 13ProMax 256GB | D142: -2130 | E142: 3 | F142: =D142*E142 -> -6390
F143: =D143*E143 -> 0
F144: =D144*E144 -> 0
B147: Total | F147: =SUM(F142:F146) -> -6390
B150: Sell Invoice
B152: Bill No: | C152: SI0009
B154: Name: | C154: Saad & Wajahat Encell Shop | D154: Date: | E154: 45418
B155: Contact
B156: Add:
B158: S.No | C158: Particulars | D158: Rate | E158: Qnty | F158: Amount
B160: 1 | C160: IP 13ProMax 256GB | D160: 2100 | E160: 1 | F160: =D160*E160 -> 2100
F161: =D161*E161 -> 0
F162: =D162*E162 -> 0
B165: Total | F165: =SUM(F160:F164) -> 2100
B168: Sell Invoice
B170: Bill No: | C170: SI0010
B172: Name: | C172: Saad & Wajahat Encell Shop | D172: Date: | E172: 45419
B173: Contact
B174: Add:
B176: S.No | C176: Particulars | D176: Rate | E176: Qnty | F176: Amount
...

Sheet Pur.Invoice
B3: Purchased Invoice
B5: Bill No: | C5: PI0001
B7: Name: | C7: Muhammad Usman | D7: Date: | E7: 45405
B8: Contact
B9: Add:
B11: S.No | C11: Particulars | D11: Rate | E11: Qnty | F11: Amount
B13: 1 | C13: IP 11 Box | D13: 625 | E13: 5 | F13: =D13*E13 -> 3125
B14: 2 | C14: IP 15ProMax | D14: 2400 | E14: 4 | F14: =D14*E14 -> 9600
B15: 3 | C15: IP 15Pro | D15: 2000 | E15: 1 | F15: =D15*E15 -> 2000
B16: 4 | C16: S24 Ultra | D16: 2350 | E16: 1 | F16: =D16*E16 -> 2350
B17: 5 | C17: S24 | D17: 1300 | E17: 1 | F17: =D17*E17 -> 1300
B21: Total | F21: =SUM(F13:F20) -> 18375
B25: Purchased Invoice | L25: EuroNext | M25: SI0025
B27: Bill No: | C27: PI0002
B29: Name: | C29: Muhammad Usman | D29: Date: | E29: 45405
B30: Contact
B31: Add:
B33: S.No | C33: Particulars | D33: Rate | E33: Qnty | F33: Amount
B35: 1 | C35: S24 box | D35: 1300 | E35: 4 | F35: =D35*E35 -> 5200
B36: 2 | C36: Z Fold 5 | D36: 2000 | E36: 1 | F36: =D36*E36 -> 2000
B37: 3 | C37: S24 Ultra | D37: 2350 | E37: 7 | F37: =D37*E37 -> 16450
B43: Total | F43: =SUM(F35:F42) -> 23650
B45: Purchased Invoice
B47: Bill No: | C47: PI0003
B49: Name: | C49: Muhammad Usman | D49: Date: | E49: 45405
B50: Contact
B51: Add:
B53: S.No | C53: Particulars | D53: Rate | E53: Qnty | F53: Amount
B55: 1 | C55: Google Pixel 7 Locked | D55: 555.555 | E55: 1 | F55: =D55*E55 -> 555.555
B56: 2 | C56: S22 Ultra 128GB | D56: 555.555 | E56: 1 | F56: =D56*E56 -> 555.555
B57: 3 | C57: S22 Ultra 256GB | D57: 555.555 | E57: 1 | F57: =D57*E57 -> 555.555
B58: 4 | C58: A54 128GB Locked | D58: 555.555 | E58: 1 | F58: =D58*E58 -> 555.555
B59: 5 | C59: Flip5 256GB Locked | D59: 555.555 | E59: 1 | F59: =D59*E59 -> 555.555
B60: 6 | C60: Note20 ultra 128GB Locked | D60: 555.555 | E60: 1 | F60: =D60*E60 -> 555.555
B61: 7 | C61: S21 128GB Locked | D61: 555.555 | E61: 2 | F61: =D61*E61 -> 1111.11
B62: 8 | C62: S21 256GB Locked | D62: 555.555 | E62: 1 | F62: =D62*E62 -> 555.555
B63: 9 | C63: S21Plus 128GB Locked | D63: 555.555 | E63: 1 | F63: =D63*E63 -> 555.555
B64: 10 | C64: S22 Ultra 256GB Locked | D64: 555.555 | E64: 1 | F64: =D64*E64 -> 555.555
B65: 11 | C65: S22 Ultra 512GB Locked | D65: 555.555 | E65: 1 | F65: =D65*E65 -> 555.555
B66: 12 | C66: S23 FE 128GB Locked | D66: 555.555 | E66: 1 | F66: =D66*E66 -> 555.555
... B71: 17 | C71: S20 Locked | D71: 555.555 | E71: 1 | F71: =D71*E71 -> 555.555
B74: Total | F74: =SUM(F55:F73) -> 9999.99
B76: Purchased Invoice
B78: Bill No: | C78: PI0004
B80: Name: | C80: Muhammad Usman | D80: Date: | E80: 45405
B81: Contact
B82: Add:
B84: S.No | C84: Particulars | D84: Rate | E84: Qnty | F84: Amount
B86: 1 | C86: Google Pixel 6A | D86: 300 | E86: 1 | F86: =D86*E86 -> 300
B87: 2 | C87: IP 12 64Gb | D87: 400 | E87: 2 | F87: =D87*E87 -> 800
B88: 3 | C88: IP 12 128Gb | D88: 500 | E88: 1 | F88: =D88*E88 -> 500
B89: 4 | C89: IP 12 256Gb | D89: 500 | E89: 1 | F89: =D89*E89 -> 500
B90: 5 | C90: IP 12ProMax 128GB | D90: 520 | E90: 1 | F90: =D90*E90 -> 520
B91: 6 | C91: IP 12ProMax 128GB | D91: 700 | E91: 1 | F91: =D91*E91 -> 700
B92: 7 | C92: IP 13 128Gb | D92: 800 | E92: 2 | F92: =D92*E92 -> 1600
B93: 8 | C93: IP 13 256Gb | D93: 800 | E93: 1 | F93: =D93*E93 -> 800
B94: 9 | C94: IP 13 256Gb | D94: 500 | E94: 1 | F94: =D94*E94 -> 500
B95: 10 | C95: IP 13Pro 128Gb | D95: 1400 | E95: 1 | F95: =D95*E95 -> 1400
B96: 11 | C96: IP 13Pro 256Gb | D96: 1100 | E96: 1 | F96: =D96*E96 -> 1100
B97: 12 | C97: IP 13ProMax 128Gb | D97: 210 | E97: 1 | F97: =D97*E97 -> 210
... B115: 45442 | C115: S24 | D115: 1170 | E115: 1 | F115: =D115*E115 -> 1170
F116: =D116*E116 -> 0
F117: =D117*E117 -> 0
F118: =D118*E118 -> 0
F119: =D119*E119 -> 0
F120: =D120*E120 -> 0
F121: =D121*E121 -> 0
B123: Total | F123: =SUM(F86:F122) -> 31000
B126: Purchased Invoice
B128: Bill No: | C128: PI0005
B130: Name: | C130: ALI KARACHI | D130: Date: | E130: 45409
B131: Contact
B132: Add:
B134: S.No | C134: Particulars | D134: Rate | E134: Qnty | F134: Amount
B136: 1 | C136: Apple / iPhone 13 Pro Max / A2484 / 512GB / Graphite / Other / LOCKED / TPS A+ | D136: =38.42+1616.56 -> 1654.98 | E136: 1 | F136: =D136*E136 -> 1654.98
B137: 2 | C137: Apple / iPhone 13 Pro Max / A2484 / 256GB / Graphite / ATT / LOCKED / TPS B+ | D137: =38.42+1642.278 -> 1680.698 | E137: 1 | F137: =D137*E137 -> 1680.698
B138: 3 | C138: Apple / iPhone 13 Pro Max / A2484 / 256GB / Sierra Blue / Other / LOCKED / TPS B+ | D138: =38.42+1587.168 -> 1625.588 | E138: 1 | F138: =D138*E138 -> 1625.588
B139: 4 | C139: Apple / iPhone 13 Pro Max / A2484 / 256GB / Gold / ATT / LOCKED / TPS A+ | D139: =38.42+1653.3 -> 1691.72 | E139: 1 | F139: =D139*E139 -> 1691.72
B140: 5 | C140: APPL.iPhone 13 Pro Max.A2484.256GB.Silver.UNL.B+ | D140: =38.42+1947.22 -> 1985.64 | E140: 1 | F140: =D140*E140 -> 1985.64
B141: 6 | C141: APPL.iPhone 13 Pro Max.A2484.256GB.Sierra Blue.UNL.B+ | D141: =38.42+1980.286 -> 2018.706 | E141: 4 | F141: =D141*E141 -> 8074.824
B142: 7 | C142: APPL.iPhone 13 Pro Max.A2484.256GB.Alpine Green.ATT.B+ | D142: =38.42+1983.96 -> 2022.38 | E142: 5 | F142: =D142*E142 -> 10111.9
B143: 8 | C143: APPL.iPhone 13 Pro Max.A2484.256GB.Alpine Green.ATT.B+ | D143: =38.42+1947.22 -> 1985.64 | E143: 6 | F143: =D143*E143 -> 11913.84
B144: 9 | C144: APPL.iPhone 13 Pro Max.A2484.256GB.Gold.VZW.B+ | D144: =38.42+1983.96 -> 2022.38 | E144: 1 | F144: =D144*E144 -> 2022.38
B145: 10 | C145: APPL.iPhone 13 Pro Max.A2484.256GB.Silver.VZW.B+ | D145: =38.42+1983.96 -> 2022.38 | E145: 1 | F145: =D145*E145 -> 2022.38
B146: 11 | C146: APPL.iPhone 13 Pro Max.A2484.512GB.Silver.ATT.B+ | D146: =38.42+1969.26 -> 2007.68 | E146: 1 | F146: =D146*E146 -> 2007.68
B147: 12 | C147: APPL.iPhone 13 Pro Max.A2484.256GB.Sierra Blue.VZW.B+ | D147: =38.42+1983.96 -> 2022.38 | E147: 1 | F147: =D147*E147 -> 2022.38
B148: 13 | C148: Apple / iPhone 12 Pro Max / A2342 / 256GB / Blue / ATT / LOCKED / TPS A+ | D148: =38.42+1175.68 -> 1214.1 | E148: 1 | F148: =D148*E148 -> 1214.1
B149: 14 | C149: Apple / iPhone 12 Pro / A2341 / 128GB / Blue / ATT / LOCKED / TPS B+ | D149: =38.42+882.76 -> 921.18 | E149: 2 | F149: =D149*E149 -> 1842.36
B150: 15 | C150: APPL.iPhone 11 Pro Max.A2161.256GB.Space Gray.ATT.A+ | D150: =38.42+1028.72 -> 1067.14 | E150: 28 | F150: =D150*E150 -> 29879.92
B151: 16 | C151: APPL.iPhone 11 Pro Max.A2161.256GB.Gold.UNL.B+ | D151: =38.42+1047.09 -> 1085.51 | E151: 10 | F151: =D151*E151 -> 10855.1
B152: 17 | C152: APPL.iPhone 11 Pro Max.A2161.512GB.Midnight Green.ATT.B+ | D152: =38.42+991.98 -> 1030.4 | E152: 1 | F152: =D152*E152 -> 1030.4
B153: 18 | C153: APPL.iPhone 11 Pro Max.A2161.512GB.Silver.UNL.B+ | D153: =38.42+991.98 -> 1030.4 | E153: 2 | F153: =D153*E153 -> 2060.8
B154: 19 | C154: Apple / iPhone 11 Pro Max / A2161 / 256GB / Silver / Verizon / UNLOCKED / TPS C+ | D154: =38.42+900.13 -> 938.55 | E154: 1 | F154: =D154*E154 -> 938.55
B155: 20 | C155: Apple / iPhone 11 Pro Max / A2161 / 256GB / Green / Verizon / UNLOCKED / TPS C+ | D155: =38.42+881.76 -> 920.18 | E155: 10 | F155: =D155*E155 -> 9201.8
B156: 21 | C156: Apple / iPhone 11 Pro Max / A2161 / 256GB / Grey / Unlocked / UNLOCKED / TPS C+ | D156: =38.42+885.434 -> 923.854 | E156: 10 | F156: =D156*E156 -> 9238.54
B157: 22 | C157: Apple / iPhone 11 Pro Max / A2161 / 64GB / Grey / ATT / LOCKED / TPS B+ | D157: =38.42+742.148 -> 780.568 | E157: 1 | F157: =D157*E157 -> 780.568
B158: 23 | C158: APPL.iPhone 11 Pro Max.A2161.512GB.Gold.UNL.B+ | D158: =38.42+1010 -> 1048.42 | E158: 1 | F158: =D158*E158 -> 1048.42
B159: 24 | C159: APPL.iPhone 11 Pro Max.A2161.256GB.Gold.UNL.B+ | D159: =38.42+991.98 -> 1030.4 | E159: 11 | F159: =D159*E159 -> 11334.4
B160: 25 | C160: Apple / iPhone 11 Pro / A2160 / 256GB / Grey / ATT / LOCKED / TPS C+ | D160: =38.42+624.58 -> 663 | E160: 1 | F160: =D160*E160 -> 663
B161: 26 | C161: Apple / iPhone 11 Pro / A2160 / 256GB / Grey / Other / LOCKED / TPS A+ | D161: =38.42+653.972 -> 692.392 | E161: 1 | F161: =D161*E161 -> 692.392
...

Sheet AR Bank Accounts
D2: AR Dubai Islamic Bank A/C
C3: Date | D3: Details | E3: Debit | F3: Credit | G3: Balance
C4: 45495 | D4: Opening Balance | G4: 46979.46
C5: 45498 | D5: POS Purchase | F5: 41 | G5: =G4+E5-F5 -> 46938.46
C6: 45500 | D6: POS Purchase | F6: 33.5 | G6: =G5+E6-F6 -> 46904.96
C7: 45501 | D7: POS Purchase | F7: 15.5 | G7: =G6+E7-F7 -> 46889.46
C8: 45501 | D8: POS Purchase | F8: 1.5 | G8: =G7+E8-F8 -> 46887.96
C9: 45504 | D9: POS Purchase | F9: 13.6 | G9: =G8+E9-F9 -> 46874.36
C10: 45504 | D10: POS Purchase | F10: 19.5 | G10: =G9+E10-F10 -> 46854.86
C11: 45504 | D11: POS Purchase | F11: 315 | G11: =G10+E11-F11 -> 46539.86
C12: 45504 | D12: POS Purchase | F12: 8 | G12: =G11+E12-F12 -> 46531.86
C13: 45504 | D13: POS Purchase | F13: 18.5 | G13: =G12+E13-F13 -> 46513.36
C14: 45505 | D14: POS Purchase | F14: 10 | G14: =G13+E14-F14 -> 46503.36
C15: 45505 | D15: Salary | E15: 20000 | G15: =G14+E15-F15 -> 66503.36
C16: 45506 | D16: Service Charges | F16: 1.2 | G16: =G15+E16-F16 -> 66502.16
C17: 45506 | D17: Outgoing Domestic Fund Transfer | F17: 108 | G17: =G16+E17-F17 -> 66394.16
C18: 45506 | D18: Service Charges | F18: 1.2 | G18: =G17+E18-F18 -> 66392.96
C19: 45506 | D19: Outgoing Domestic Fund Transfer | F19: 108 | G19: =G18+E19-F19 -> 66284.96
C20: 45506 | D20: Bank Charges | F20: 1 | G20: =G19+E20-F20 -> 66283.96
C21: 45506 | D21: Service Charges | F21: 1.2 | G21: =G20+E21-F21 -> 66282.76
C22: 45506 | D22: Outgoing Domestic Fund Transfer | F22: 108 | G22: =G21+E22-F22 -> 66174.76
C23: 45510 | D23: DU Payment | F23: 35 | G23: =G22+E23-F23 -> 66139.76
C24: 45510 | D24: DU Payment | F24: 65 | G24: =G23+E24-F24 -> 66074.76
C25: 45510 | D25: POS Purchase EMIRATES | F25: 1170 | G25: =G24+E25-F25 -> 64904.76
C26: 45512 | D26: POS Purchase | F26: 39 | G26: =G25+E26-F26 -> 64865.76
C27: 45512 | D27: POS Purchase (royal paris hotel) | F27: 18 | G27: =G26+E27-F27 -> 64847.76
... C39: 45522 | D39: Ticket change Charges | F39: 743 | G39: =G38+E39-F39 -> 49840.79
D40: adjustment | G40: =G39+E40-F40 -> 49840.79
C41: 45537 | D41: DU Payment | F41: 20 | G41: =G40+E41-F41 -> 49820.79
C42: 45538 | D42: Chq Book Charges | F42: 26.25 | G42: =G41+E42-F42 -> 49794.54
C43: 45539 | D43: Salary Deposit (Adjust A/R Cash) | E43: 20000 | G43: =G42+E43-F43 -> 69794.54
C44: 45540 | D44: DU Payment | F44: 20 | G44: =G43+E44-F44 -> 69774.54
C45: 45540 | D45: POS Purchased Flydubai | F45: 345.05 | G45: =G44+E45-F45 -> 69429.49
C46: 45543 | D46: POS Royal Paris Hotel | F46: 18 | G46: =G45+E46-F46 -> 69411.49
C47: 45543 | D47: Trasnfer Credit Card A/C | F47: 3000 | G47: =G46+E47-F47 -> 66411.49
C48: 45543 | D48: Trasnfer Credit Card A/C | F48: 14600 | G48: =G47+E48-F48 -> 51811.49
C49: 45545 | D49: POS (Albaik Dubai) | F49: 16 | G49: =G48+E49-F49 -> 51795.49
C50: 45545 | D50: POS (Dubai Taxi) | F50: 34 | G50: =G49+E50-F50 -> 51761.49
C51: 45545 | D51: POS (Sulaiya Supermarket) | F51: 61.98 | G51: =G50+E51-F51 -> 51699.51
C52: 45545 | D52: POS (Albaik Dubai) | F52: 144 | G52: =G51+E52-F52 -> 51555.51
C53: 45545 | D53: POS (Carrefour Al.ghurair Dubai) | F53: 93.2 | G53: =G52+E53-F53 -> 51462.31
C54: 45545 | D54: DU Payment | F54: 95 | G54: =G53+E54-F54 -> 51367.31
C55: 45547 | D55: POS (Dubai Taxi) | F55: 40.5 | G55: =G54+E55-F55 -> 51326.81
... C61: 45559 | D61: Harvey Norman | F61: 3855.48 | G61: =G60+E61-F61 -> 31826.7
C62: 45560 | D62: Harvey Norman | F62: 10365.45 | G62: =G61+E62-F62 -> 21461.25 | J62: 45556 | K62: Starlink Mini Purchase
C63: 45560 | D63: POS (Coles RYDE) | F63: 3.37 | G63: =G62+E63-F63 -> 21457.88
C64: 45560 | D64: Harvey Norman | F64: 10365.45 | G64: =G63+E64-F64 -> 11092.43 | J64: 45556 | K64: Starlink Mini Purchase
C65: 45566 | D65: POS Islamic Centre Mayfield | F65: 26.19 | G65: =G64+E65-F65 -> 11066.24
C66: 45566 | D66: Salary From AMGT | E66: 20000 | G66: =G65+E66-F66 -> 31066.24
C67: 45571 | D67: POS (chemist warehouse hornsby) | F67: 36.72 | G67: =G66+E67-F67 -> 31029.52
C68: 45571 | D68: POS (Emirates) | F68: 465.32 | G68: =G67+E68-F68 -> 30564.2
C69: 45576 | D69: POS (Castle hill) | F69: 10.27 | G69: =G68+E69-F69 -> 30553.93
C70: 45577 | D70: POS (islamic malay australia) | F70: 25.69 | G70: =G69+E70-F70 -> 30528.24
C71: 45582 | D71: POS PURCHASE | F71: 40 | G71: =G70+E71-F71 -> 30488.24
C72: 45582 | D72: DU PAYMENT - MBA : 971523718190 | F72: 60 | G72: =G71+E72-F72 -> 30428.24
C73: 45583 | D73: POS PURCHASE | F73: 4.09 | G73: =G72+E73-F73 -> 30424.15
C74: 45583 | D74: POS PURCHASE | F74: 7.5 | G74: =G73+E74-F74 -> 30416.65
C75: 45583 | D75: POS PURCHASE | F75: 18 | G75: =G74+E75-F75 -> 30398.65
C76: 45584 | D76: POS PURCHASE | F76: 561.5 | G76: =G75+E76-F76 -> 29837.15
C77: 45584 | D77: POS PURCHASE | F77: 83 | G77: =G76+E77-F77 -> 29754.15
C78: 45585 | D78: DU PAYMENT - MBA : 971523718190 | F78: 20 | G78: =G77+E78-F78 -> 29734.15
... C100: 45597 | D100: VISA CARD PAYMENT | F100: 183.55 | G100: =G99+E100-F100 -> 27780.26
B101: ENBD A/C | C101: 45597 | D101: VISA CARD PAYMENT | F101: 6118.27 | G101: =G100+E101-F101 -> 21661.99
C102: 45598 | D102: POS PURCHASE - AL MADINA DUBAI | F102: 12.64 | G102: =G101+E102-F102 -> 21649.35
C103: 45599 | D103: POS PURCHASE - ROYAL PARIS HOTEL DUBAI | F103: 16 | G103: =G102+E103-F103 -> 21633.35
C104: 45600 | D104: Salary From AMGT | E104: 20000 | G104: =G103+E104-F104 -> 41633.35
C105: 45601 | D105: POS PURCHASE - EMIRATES 1762380421013 E COMMERCE | F105: 1020 | G105: =G104+E105-F105 -> 40613.35
C106: 45602 | D106: DU PAYMENT - MBA : 971523718190 | F106: 20 | G106: =G105+E106-F106 -> 40593.35
C107: 45602 | D107: POS PURCHASE - AL MADINA DUBAI | F107: 4.69 | G107: =G106+E107-F107 -> 40588.66
C108: 45602 | D108: POS PURCHASE - ALBAIK DUBAI | F108: 41 | G108: =G107+E108-F108 -> 40547.66
B109: Flat Rent Chq | C109: 45602 | D109: INHOUSE CHEQUE - DEBIT - CHEQUE 100026 | F109: 5675 | G109: =G108+E109-F109 -> 34872.66
C110: 45605 | D110: POS PURCHASE - EXPRESS FOOD COMPANY A JEDDAH | F110: 18.18 | G110: =G109+E110-F110 -> 34854.48
C111: 45609 | D111: POS PURCHASE - EXPRESS FOOD COMPANY A JEDDAH | F111: 30.29 | G111: =G110+E111-F111 -> 34824.19
C112: 45609 | D112: POS PURCHASE - UNITED PHARMACIES 112 MAKKAH | F112: 4.04 | G112: =G111+E112-F112 -> 34820.15
C113: 45609 | D113: POS PURCHASE - ABRAJ HYPER MARKET MAKKAH | F113: 8.08 | G113: =G112+E113-F113 -> 34812.07
C114: 45609 | D114: POS PURCHASE - ALTAZAJ MAKKAH | F114: 84.84 | G114: =G113+E114-F114 -> 34727.23
C115: 45609 | D115: POS PURCHASE - nasmat almathaq est MAKKAH | F115: 6.06 | G115: =G114+E115-F115 -> 34721.17
C116: 45609 | D116: POS PURCHASE - ALTAZAJ MAKKAH | F116: 42.42 | G116: =G115+E116-F116 -> 34678.75
C117: 45612 | D117: POS PURCHASE - DUBAI TAXI DUBAI | F117: 54 | G117: =G116+E117-F117 -> 34624.75
C118: 45612 | D118: POS PURCHASE - GIFTS LAND CENTRE LLC Dubai | F118: 130 | G118: =G117+E118-F118 -> 34494.75
C119: 45612 | D119: POS PURCHASE - EXPRESS FOOD COMPANY A JEDDAH | F119: 39.39 | G119: =G118+E119-F119 -> 34455.36
C120: 45612 | D120: POS PURCHASE - AL ZAHRA WALANDALEEB REST DUBAI | F120: 33 | G120: =G119+E120-F120 -> 34422.36
C121: 45612 | D121: POS PURCHASE - GIFTS LAND CENTRE LLC Dubai | F121: 15.75 | G121: =G120+E121-F121 -> 34406.61
... C148: 45624 | D148: VISA CARD PAYMENT | F148: 1449.77 | G148: =G147+E148-F148 -> 31259.03
C149: 45624 | D149: SALARY - WPS SALARY | E149: 20000 | G149: =G148+E149-F149 -> 51259.03
C150: 45625 | D150: POS PURCHASE - GLOBAL VILLAGE PARTNERS DUBAI | F150: 10 | G150: =G149+E150-F150 -> 51249.03
C151: 45625 | D151: POS PURCHASE - GLOBAL VILLAGE PARTNERS DUBAI | F151: 15 | G151: =G150+E151-F151 -> 51234.03
C152: 45625 | D152: POS PURCHASE - GLOBAL VILLAGE PARTNERS DUBAI | F152: 30 | G152: =G151+E152-F152 -> 51204.03
C153: 45625 | D153: POS PURCHASE - GLOBAL VILLAGE PARTNERS DUBAI | F153: 55 | G153: =G152+E153-F153 -> 51149.03
C154: 45625 | D154: POS PURCHASE - NWZ WEST ZONE SUPERMARKET DUBAI | F154: 5.75 | G154: =G153+E154-F154 -> 51143.28
C155: 45625 | D155: POS PURCHASE - GLOBAL VILLAGE ENTRY T DUBAI | F155: 75 | G155: =G154+E155-F155 -> 51068.28
C156: 45625 | D156: POS PURCHASE - ANDAAZ APNA APNA RESTAURA DUBAI | F156: 6 | G156: =G155+E156-F156 -> 51062.28
C157: 45625 | D157: DU PAYMENT - MBA : 971555032152 | F157: 20 | G157: =G156+E157-F157 -> 51042.28
C158: 45626 | D158: POS PURCHASE - CARS TAXI SERVICES CO LLC DUBAI | F158: 15.48 | G158: =G157+E158-F158 -> 51026.8
C159: 45626 | D159: POS PURCHASE - Mian jee catering service Dubai | F159: 6 | G159: =G158+E159-F159 -> 51020.8
C160: 45626 | D160: POS PURCHASE - JB HI FI HILL ST AUCKLAND | F160: 1444.82 | G160: =G159+E160-F160 -> 49575.98
C161: 45626 | D161: POS PURCHASE - BUTTKARAHI RESTAURANT CO Dubai | F161: 261 | G161: =G160+E161-F161 -> 49314.98
... C232: 45661 | D232: DU PAYMENT - MBA : 971523718190 | F232: 20 | G232: =G231+E232-F232 -> 4158.96
G233: =G232+E233-F233 -> 4158.96
G234: =G233+E234-F234 -> 4158.96
...

Sheet Mudassir Purchasing
F4: Pur. | H4: Sell To | I4: Price
C5: 45429 | D5: Watch Ultra | E5: 355500639429695 | F5: 185000 | G5: Recvd | H5: Sell To Shoaib Bhai | I5: 2475 Aed
C6: 45429 | D6: Watch Ultra | E6: ?? | F6: 185000 | G6: Recvd | H6: Sell To Shoaib Bhai | I6: 2475 Aed
C8: 45441 | D8: IP 15 proMax blue | E8: 352676524721637 | F8: 180000 | G8: Recvd | H8: Sell To razi | I8: 2430 AED
C10: 45441 | D10: Watch Ultra | E10: ?? | F10: 185000 | G10: USA | J10: Received Encell Shop 24/06/2024
C12: 45442 | D12: IP 15 ProMax White | E12: 358862625559555 | F12: 180000 | G12: USA | H12: Sell To encell Shop | I12: 2500 AED | J12: Received Encell Shop 24/06/2024
C13: 45442 | D13: IP 15 ProMax Natural | E13: 355430975963075 | F13: 190000 | J13: Received Encell Shop 24/06/2024
C14: 45442 | D14: Watch Ultra | E14: 355500636585010 | F14: 180000 | G14: USA | J14: Missing By mistake Send To usman
C15: 45446 | D15: Watch Ultra | E15: 358161185579503 | F15: 180000 | H15: Sell to umair | I15: 2475 AED | J15: Received Encell Shop 27/06/2024 | K15: ok
C16: 45451 | D16: IP 15 ProMax White | E16: 351581974302501 | F16: 180000 | H16: Sell To encell Shop | I16: 2500 AED | J16: Received Encell Shop 27/06/2024 | K16: ok
C17: 45451 | D17: IP 15 ProMax White | E17: 352676525849155 | F17: 180000 | H17: Sell To encell Shop | I17: 2500 AED | J17: Received Encell Shop 27/06/2024 | K17: ok
C18: 45451 | D18: Watch Ultra | E18: 355500637291410 | F18: 180000 | H18: Sell to umair | I18: 2475 AED | J18: Received Encell Shop 27/06/2024 | K18: ok
C19: 45451 | D19: Watch Ultra | E19: 355500639045483 | F19: 180000 | H19: Sell to umair | I19: 2475 AED | J19: Received Encell Shop 27/06/2024 | K19: ok
C20: 45451 | D20: IP 15 ProMax Natural | E20: 355430975754920 | F20: 190000 | H20: Sell To encell Shop | I20: 2720 AED | J20: Received Encell Shop 27/06/2024 | K20: ok
C22: 45453 | D22: Watch Ultra | E22: 355500639599224 | F22: 180000 | H22: Sell to umair | I22: 2475 AED | J22: Received Encell Shop 27/06/2024 | K22: ok
C23: 45454 | D23: Watch Ultra | E23: 355500635523269 | F23: 180000 | H23: Sell to umair | I23: 2475 AED | J23: Received Encell Shop 27/06/2024 | K23: ok
C25: 45455 | D25: Watch Ultra | E25: 355500637698580 | F25: 180000 | J25: Received Encell Shop 11/07/2024
C27: 45457 | D27: Watch Ultra 2 | E27: 355500638142711 | F27: 175000 | H27: Returned 29/07/2024 | J27: Received Encell Shop 11/07/2024
C28: 45457 | D28: Watch Ultra 2 | E28: 355500635621501 | F28: 175000 | J28: Received Encell Shop 11/07/2024
C29: 45457 | D29: Watch Ultra 2 | E29: 355500637698580 | F29: 175000 | J29: Received Encell Shop 11/07/2024
C30: 45457 | D30: Watch Ultra 2 | E30: 357114365908449 | F30: 175000 | J30: Received Encell Shop 11/07/2024
C32: 45463 | D32: Watch Ultra 2 | E32: 355500637735705 | F32: 175000 | J32: Received Encell Shop 11/07/2024
C33: 45469 | D33: Watch Ultra 2 | E33: 357114365969946 | F33: 175000 | H33: Not Received Returned | I33: 45497
C34: 45469 | D34: Watch Ultra 2 | E34: 355500637580994 | F34: 175000 | H34: Not Received Returned | I34: 45497
C36: 45474 | D36: Watch Ultra 2 | E36: 358161187420516 | F36: 175000 | H36: Returned 29/07/2024 | J36: Received Encell Shop 22/07/2024
C37: 45492 | D37: Watch Ultra 2 | E37: 358161188279309 | F37: 175000 | H37: Returned 29/07/2024 | J37: Received Encell Shop 22/07/2024
C39: 45495 | D39: IP 15 Pro 128GB Black | E39: 350404321911646 | F39: 155000 | G39: cancelled | H39: cancelled
C40: 45495 | D40: IP 15 Pro 256GB Black | E40: 356444800452880 | F40: 160000 | H40: USA Office | J40: Received Encell Shop 13/08/2024
C41: 45495 | D41: IP 15 Pro 256GB Black | E41: 350684900665818 | F41: 160000 | H41: USA Office | J41: Received Encell Shop 13/08/2024
C42: 45495 | D42: IP 15 Pro 1TB Black | E42: 350684901224722 | F42: 175000 | H42: USA Office | J42: Received Encell Shop 13/08/2024
C44: 45497 | D44: IP 15 ProMax 256GB Natural | E44: 355430976748020 | F44: 202000 | H44: USA Office | J44: Received Encell Shop 13/08/2024
C45: 45497 | D45: IP 15 ProMax 256GB Natural | E45: 358862626698097 | F45: 202000 | H45: USA Office | J45: Received Encell Shop 13/08/2024
C47: 45503 | D47: Watch Ultra 2 | E47: 358161187828858 | F47: 175000 | G47: Adjust other watch 04/10/2024 | H47: USA Office
C48: 45503 | D48: Watch Ultra 2 | E48: ??? | F48: 0 | G48: cancelled | H48: cancelled
C50: 45503 | D50: IP 15 ProMax 256GB Blue | E50: 352310727115435 | F50: 190000 | G50: Pending | H50: USA Office
C51: 45503 | D51: IP 15 ProMax 256GB Natural | E51: 351646279235530 | F51: 202000 | G51: Pending | H51: USA Office
C52: 45503 | D52: IP 15 ProMax 256GB Black | E52: 352676526208757 | F52: 185000 | G52: Pending | H52: USA Office
B54: Model Update | C54: 45510 | D54: IP 15 128GB Blue | E54: 351335415944581 | F54: 105000 | H54: Mudassir Bhai | J54: Received Encell Shop 13/08/2024
C55: 45510 | D55: IP 15Pro 128GB White | E55: 350839531130745 | F55: 145000 | H55: Mudassir Bhai | J55: Received Encell Shop 13/08/2024
C56: 45510 | D56: IP 15Pro 128GB White | E56: 351418620421437 | F56: 145000 | H56: Mudassir Bhai | J56: Received Encell Shop 13/08/2024
B58: entry done in System by @77.5 | C58: 45568 | D58: IP 15ProMax Natural 256GB | E58: 351306998557264 | F58: 188000 | G58: 18/10/2024 Received | H58: Dubai Office
B59: entry done in System by @77.5 | C59: 45568 | D59: IP 15ProMax Natural 256GB | E59: 351306997008764 | F59: 188000 | G59: 18/10/2024 Received | H59: Dubai Office
B60: entry done in System by @77.5 | C60: 45568 | D60: IP 15ProMax Natural 256GB | E60: 356511217161658 | F60: 188000 | G60: 18/10/2024 Received | H60: Dubai Office
B61: entry done in System by @77.5 | C61: 45569 | D61: IP 15ProMax Natural 256GB | E61: 351581974996914 | F61: 188000 | G61: 18/10/2024 Received | H61: Dubai Office
B62: entry done in System by A/R @77.5 (old payment Done) | C62: 45569 | D62: Apple Watch Ultra 2 49mm | E62: 356245745845462 | F62: Replacement | G62: 18/10/2024 Received | H62: Dubai Office
B64: entry done in System by A/R @77.5 | C64: 45574 | D64: IP 16Plus 128GB | E64: 359410898436785 | F64: 150000 | G64: 04/11/2024 Received | H64: Dubai Office | I64: Active Returned 02/01/2025 | J64: 04/11/2024 Received
B65: entry done in System by A/R @77.5 | C65: 45574 | D65: IP 16Plus 128GB | E65: 359410896985205 | F65: 150000 | G65: 04/11/2024 Received | H65: Dubai Office | J65: 04/11/2024 Received
B66: entry done in System by A/R @77.5 | C66: 45574 | D66: IP 16Plus 128GB | E66: 359410896404926 | F66: 150000 | G66: 04/11/2024 Received | H66: Dubai Office | J66: 04/11/2024 Received
B68: entry done in System by A/R @77.5 | C68: 45587 | D68: IP 16 128GB | E68: 351935560028229 | F68: 130000 | G68: 04/11/2024 Received | H68: Dubai Office | J68: 04/11/2024 Received
B69: entry done in System by A/R @77.5 | C69: 45587 | D69: IP 16Plus 512GB | E69: 351553469141959 | F69: 150000 | G69: 04/11/2024 Received | H69: Dubai Office | J69: 04/11/2024 Received
B71: entry done in System by A/R @77.5 | C71: 45589 | D71: IP 16 Pro Max 512GB Natural | E71: 355138326083838 | F71: 245000 | G71: 20/11/2024 Received | H71: Dubai Office | J71: 20/11/2024 Received
B72: entry done in System by A/R @77.5 | C72: 45589 | D72: IP 15Pro Max 256 GB natural | E72: 352310729040813 | F72: 190000 | G72: 20/11/2024 Received | H72: Dubai Office | J72: 20/11/2024 Received
B73: entry done in System by A/R @77.5 | C73: 45591 | D73: IP 16 Pro Max 512GB Desert | E73: 355762290101472 | F73: 260000 | G73: 20/11/2024 Received | H73: Dubai Office | J73: 20/11/2024 Received
B75: entry done in System by A/R @77.5 | C75: 45593 | D75: IP 16 Pro Max 256GB Natural | E75: 355762293228074 | F75: 240000 | G75: 20/11/2024 Received | H75: Dubai Office | J75: 20/11/2024 Received
B76: entry done in System by A/R @77.5 | C76: 45593 | D76: IP 16 Pro Max 256GB Natural | E76: 355762293235640 | F76: 240000 | G76: 20/11/2024 Received | H76: Dubai Office | J76: 20/11/2024 Received
B77: entry done in System by A/R @77.5 | C77: 45593 | D77: IP 16 Pro Max 512GB Natural | E77: 355762291288229 | F77: 245000 | G77: 20/11/2024 Received | H77: Dubai Office | J77: 20/11/2024 Received
B79: entry done in System by A/R @77.5 | C79: 45598 | D79: IP 16 Pro Max 512GB Desert | E79: 355300183398754 | F79: 260000 | G79: 03/12/2024 Received | H79: Karachi Office
B80: entry done in System by A/R @77.5 | C80: 45598 | D80: IP 16 Pro Max 512GB Natural | E80: 356760684725327 | F80: 245000 | G80: 03/12/2024 Received | H80: Karachi Office
B81: entry done in System by A/R @77.5 | C81: 45598 | D81: IP 16 Pro Max 512GB Natural | E81: 354276351497886 | F81: 245000 | G81: 03/12/2024 Received | H81: Karachi Office

Sheet Stock
J2: Returned & sell | X2: Returned | AB2: Returned
C3: Company | D3: Model Name | E3: 45413 | F3: 45414 | G3: 45415 | H3: 45416 | I3: 45417 | J3: 45418 | K3: 45419 | L3: 45420 | M3: 45421 | N3: 45422 | O3: 45423 | P3: 45424 | Q3: 45425 | R3: 45426 | S3: 45427 | T3: 45428 | U3: 45429 | V3: 45430 | W3: 45431 | X3: 45432 | Y3: 45433 | Z3: 45434 | AA3: 45435 | AB3: 45436 | AC3: 45437 | AD3: 45438 | AE3: 45439 | AF3: 45440 | AG3: 45441 | AH3: 45442 | AI3: Remaining Stock | AL3: Company | AM3: Model Name | AN3: Remaining Stock | AO3: Costing | AP3: Total
C5: APPLE | AL5: APPLE
D6: IP 15ProMax 256 | U6: 1 | AG6: -1 | AI6: =SUM(E6:AH6) -> 0 | AM6: =D6 -> IP 15ProMax 256 | AN6: =AI6 -> 0 | AP6: =AN6*AO6 -> 0
D7: IP 15Pro 128Gb | U7: 1 | AI7: =SUM(E7:AH7) -> 1 | AM7: =D7 -> IP 15Pro 128Gb | AN7: =AI7 -> 1 | AO7: 900 | AP7: =AN7*AO7 -> 900
D8: IP 15plus 128GB | U8: 2 | AG8: -1 | AI8: =SUM(E8:AH8) -> 1 | AM8: =D8 -> IP 15plus 128GB | AN8: =AI8 -> 1 | AO8: 1350 | AP8: =AN8*AO8 -> 1350
D9: IP 15 128GB | U9: 2 | AI9: =SUM(E9:AH9) -> 2 | AM9: =D9 -> IP 15 128GB | AN9: =AI9 -> 2 | AO9: 500 | AP9: =AN9*AO9 -> 1000
D10: IP 14ProMax 128Gb | E10: 1 | AI10: =SUM(E10:AH10) -> 1 | AM10: IP 14ProMax 128Gb | AN10: =AI10 -> 1 | AO10: 1600 | AP10: =AN10*AO10 -> 1600
D11: IP 14ProMax 256Gb | E11: 1 | AI11: =SUM(E11:AH11) -> 1 | AM11: IP 14ProMax 256Gb | AN11: =AI11 -> 1 | AO11: 1600 | AP11: =AN11*AO11 -> 1600
D13: IP 13ProMax 512Gb | E13: 1 | AI13: =SUM(E13:AH13) -> 1 | AM13: IP 13ProMax 512Gb | AN13: =AI13 -> 1 | AO13: 1654.98 | AP13: =AN13*AO13 -> 1654.98 | AU13: IPHONE 13ProMax
D14: IP 13ProMax 128Gb | E14: 1 | R14: 2 | V14: -2 | AI14: =SUM(E14:AH14) -> 1 | AM14: IP 13ProMax 128Gb | AN14: =AI14 -> 1 | AO14: 1500 | AP14: =AN14*AO14 -> 1500 | AU14: 45420 | AV14: 6 | AW14: Match
D15: IP 13ProMax 256Gb | E15: 2 | J15: =3-1 -> 2 | R15: 11 | V15: -10 | X15: 1 | AB15: 1 | AG15: -4 | AI15: =SUM(E15:AH15) -> 3 | AM15: IP 13ProMax 256Gb | AN15: =AI15 -> 3 | AO15: 1527.83 | AP15: =AN15*AO15 -> 4583.49 | AU15: 45426 | AV15: 13 | AW15: Purchase By Ali Karachi
D16: IP 13Pro 256Gb | E16: 1 | AI16: =SUM(E16:AH16) -> 1 | AM16: IP 13Pro 256Gb | AN16: =AI16 -> 1 | AO16: 1100 | AP16: =AN16*AO16 -> 1100 | AU16: 45429 | AV16: -2 | AW16: Sell To encell
D17: IP 13 256Gb | E17: 2 | AI17: =SUM(E17:AH17) -> 2 | AM17: IP 13 256Gb | AN17: =AI17 -> 2 | AO17: 800 | AP17: =AN17*AO17 -> 1600 | AU17: 45430 | AV17: -10 | AW17: Sell To encell
D18: IP 13 128Gb | R18: 10 | U18: 1 | V18: -10 | AI18: =SUM(E18:AH18) -> 1 | AM18: IP 13 128Gb | AN18: =AI18 -> 1 | AO18: 300 | AP18: =AN18*AO18 -> 300 | AU18: 45432 | AV18: 1 | AW18: Returned From Encell
AU19: 45435 | AV19: 1 | AW19: Returned From Encell
D20: IP 12ProMax 256GB | E20: 1 | R20: 2 | V20: -1 | AI20: =SUM(E20:AH20) -> 2 | AM20: IP 12ProMax 256GB | AN20: =AI20 -> 2 | AO20: 1129.755 | AP20: =AN20*AO20 -> 2259.51 | AU20: 45442 | AV20: -4 | AW20: Sell To Euronext
D21: IP 12ProMax 128GB | E21: 1 | AI21: =SUM(E21:AH21) -> 1 | AM21: IP 12ProMax 128GB | AN21: =AI21 -> 1 | AO21: 720 | AP21: =AN21*AO21 -> 720
D22: IP 12 Pro 256GB | R22: 2 | AI22: =SUM(E22:AH22) -> 2 | AM22: IP 12 Pro 256GB | AN22: =AI22 -> 2 | AO22: 973.61 | AP22: =AN22*AO22 -> 1947.22 | AU22: Current Inventory | AV22: =SUM(AV14:AV21) -> 5
D23: IP 12 Pro 128GB | E23: 1 | AI23: =SUM(E23:AH23) -> 1 | AM23: IP 12 Pro 128GB | AN23: =AI23 -> 1 | AO23: 921.18 | AP23: =AN23*AO23 -> 921.18
D24: IP 12 64Gb | E24: 1 | AI24: =SUM(E24:AH24) -> 1 | AM24: IP 12 64Gb | AN24: =AI24 -> 1 | AO24: 400 | AP24: =AN24*AO24 -> 400
D25: IP 12 128Gb | E25: 1 | AI25: =SUM(E25:AH25) -> 1 | AM25: IP 12 128Gb | AN25: =AI25 -> 1 | AO25: 500 | AP25: =AN25*AO25 -> 500
D26: IP 12 256Gb | E26: 1 | AI26: =SUM(E26:AH26) -> 1 | AM26: IP 12 256Gb | AN26: =AI26 -> 1 | AO26: 500 | AP26: =AN26*AO26 -> 500
D28: IP 11ProMax 512Gb | R28: 1 | AI28: =SUM(E28:AH28) -> 1 | AM28: IP 11ProMax 512Gb | AN28: =AI28 -> 1 | AO28: 749.5 | AP28: =AN28*AO28 -> 749.5
D29: IP 11ProMax 256Gb | E29: 36 | O29: -36 | R29: 23 | AE29: -23 | AI29: =SUM(E29:AH29) -> 0 | AM29: IP 11ProMax 256Gb | AN29: =AI29 -> 0 | AO29: 863.39 | AP29: =AN29*AO29 -> 0
D30: IP 11ProMax 64Gb | E30: 1 | AI30: =SUM(E30:AH30) -> 1 | AM30: IP 11ProMax 64Gb | AN30: =AI30 -> 1 | AO30: 780.56 | AP30: =AN30*AO30 -> 780.56
D31: IP 11Pro 256Gb | E31: 4 | AI31: =SUM(E31:AH31) -> 4 | AM31: IP 11Pro 256Gb | AN31: =AI31 -> 4 | AO31: 811.56 | AP31: =AN31*AO31 -> 3246.24
D32: IP 11 128Gb | E32: 2 | R32: 1 | AI32: =SUM(E32:AH32) -> 3 | AM32: IP 11 128Gb | AN32: =AI32 -> 3 | AO32: 524.05 | AP32: =AN32*AO32 -> 1572.15
D34: Watch Ultra 2 | X34: 2 | AH34: 1 | AI34: =SUM(E34:AH34) -> 3 | AM34: =D34 -> Watch Ultra 2 | AN34: =AI34 -> 3 | AO34: =185000/76 -> 2434.2105 | AP34: =AN34*AO34 -> 7302.6316 | AQ34: 370000 PKR
D35: IP 7Plus | E35: 1 | AI35: =SUM(E35:AH35) -> 1 | AM35: IP 7Plus | AN35: =AI35 -> 1 | AO35: 300 | AP35: =AN35*AO35 -> 300
C36: SAMSUNG | AI36: =SUM(E36:AH36) -> 0 | AL36: SAMSUNG
D37: S23 FE 128GB | E37: 1 | AI37: =SUM(E37:AH37) -> 1 | AM37: S23 FE 128GB | AN37: =AI37 -> 1 | AO37: 555.6 | AP37: =AN37*AO37 -> 555.6
D39: S20 | E39: 1 | AI39: =SUM(E39:AH39) -> 1 | AM39: S20 | AN39: =AI39 -> 1 | AO39: 555.6 | AP39: =AN39*AO39 -> 555.6
D40: Flip5 256GB | E40: 1 | AI40: =SUM(E40:AH40) -> 1 | AM40: Flip5 256GB | AN40: =AI40 -> 1 | AO40: 555.6 | AP40: =AN40*AO40 -> 555.6
D41: Samsung A54 | E41: 1 | AI41: =SUM(E41:AH41) -> 1 | AM41: Samsung A54 | AN41: =AI41 -> 1 | AO41: 555.6 | AP41: =AN41*AO41 -> 555.6
C43: GOOGLE | D43: Google Pixel 7 | E43: 1 | AI43: =SUM(E43:AH43) -> 1 | AL43: GOOGLE | AM43: Google Pixel 7 | AN43: =AI43 -> 1 | AO43: 555.6 | AP43: =AN43*AO43 -> 555.6
C45: Starlink | D45: V2 | S45: 2 | AG45: -2 | AI45: =SUM(E45:AH45) -> 0 | AL45: Starlink | AM45: V2 | AN45: =AI45 -> 0 | AP45: =AN45*AO45 -> 0
D46: V3 New | AF46: 35 | AG46: -35 | AI46: =SUM(E46:AH46) -> 0 | AM46: =D46 -> V3 New | AN46: =AI46 -> 0
E47: =SUM(E5:E46) -> 64 | J47: =SUM(J5:J46) -> 2 | O47: =SUM(O5:O46) -> -36 | R47: =SUM(R5:R46) -> 52 | S47: =SUM(S5:S46) -> 2 | U47: =SUM(U5:U46) -> 7 | V47: =SUM(V5:V46) -> -23 | AH47: =SUM(AH5:AH46) -> 1 | AI47: =SUM(AI5:AI46) -> 42 | AN47: =SUM(AN5:AN46) -> 42 | AP47: =SUM(AP5:AP46) -> 41165.462
F53: Sell 01/06 | G53: Purchasing | H53: Purchasing | I53: Razi Sell | J53: Sell | N53: Sell | Q53: Purchasing Ali karachi
C54: Company | D54: Model Name | E54: 45444 | F54: 45445 | G54: 45446 | H54: 45447 | I54: 45448 | J54: 45449 | K54: 45450 | L54: 45451 | M54: 45452 | N54: 45453 | O54: 45454 | P54: 45455 | Q54: 45456 | R54: 45457 | S54: 45458 | T54: 45459 | U54: 45460 | V54: 45461 | W54: 45462 | X54: 45463 | Y54: 45464 | Z54: 45465 | AA54: 45466 | AB54: 45467 | AC54: 45468 | AD54: 45469 | AE54: 45470 | AF54: 45471 | AG54: 45472 | AH54: 45473 | AI54: Remaining Stock | AL54: Company | AM54: Model Name | AN54: Remaining Stock | AO54: Costing | AP54: Total
C56: APPLE | AL56: APPLE
D57: IP 15ProMax 256Gb | E57: 3 | G57: 3 | I57: -1 | AF57: -1 | AI57: =SUM(E57:AH57) -> 4 | AM57: IP 15ProMax 256Gb | AN57: =AI57 -> 4 | AO57: =180000/77 -> 2337.6623 | AP57: =AN57*AO57 -> 9350.6494 | AQ57: 180000 PKR
D58: IP 15Pro 128Gb | E58: 1 | AG58: -1 | AI58: =SUM(E58:AH58) -> 0 | AM58: =D58 -> IP 15Pro 128Gb | AN58: =AI58 -> 0 | AO58: 900 | AP58: =AN58*AO58 -> 0
D59: IP 15plus 128GB | E59: 1 | F59: -1 | AI59: =SUM(E59:AH59) -> 0 | AM59: =D59 -> IP 15plus 128GB | AN59: =AI59 -> 0 | AO59: 0 | AP59: =AN59*AO59 -> 0
D60: IP 15 128GB | E60: 2 | F60: -1 | AG60: -1 | AI60: =SUM(E60:AH60) -> 0 | AM60: =D60 -> IP 15 128GB | AN60: =AI60 -> 0 | AO60: 500 | AP60: =AN60*AO60 -> 0
D61: IP 14ProMax 128Gb | E61: 1 | R61: -1 | AI61: =SUM(E61:AH61) -> 0 | AM61: IP 14ProMax 128Gb | AN61: =AI61 -> 0 | AO61: 1600 | AP61: =AN61*AO61 -> 0
D62: IP 14ProMax 256Gb | E62: 1 | R62: -1 | AI62: =SUM(E62:AH62) -> 0 | AM62: IP 14ProMax 256Gb | AN62: =AI62 -> 0 | AO62: 1600 | AP62: =AN62*AO62 -> 0
D63: IP 14 128Gb | I63: 5 | J63: -5 | AI63: =SUM(E63:AH63) -> 0 | AM63: IP 14 128Gb | AN63: =AI63 -> 0
D65: IP 13ProMax 512Gb | E65: 1 | H65: 1 | Q65: 1 | AD65: -1 | AI65: =SUM(E65:AH65) -> 2 | AM65: IP 13ProMax 512Gb | AN65: =AI65 -> 2 | AO65: 1639.365 | AP65: =AN65*AO65 -> 3278.73
D66: IP 13ProMax 128Gb | E66: 1 | Q66: 6 | AD66: -1 | AG66: 5 | AI66: =SUM(E66:AH66) -> 11 | AM66: IP 13ProMax 128Gb | AN66: =AI66 -> 11 | AO66: 1411.347 | AP66: =AN66*AO66 -> 15524.817
D67: IP 13ProMax 256Gb | E67: 3 | F67: -3 | H67: 8 | N67: -9 | Q67: 10 | AD67: -3 | AG67: 7 | AI67: =SUM(E67:AH67) -> 13 | AM67: IP 13ProMax 256Gb | AN67: =AI67 -> 13 | AO67: 1766.37 | AP67: =AN67*AO67 -> 22962.81
D68: IP 13Pro 256Gb | E68: 1 | Q68: 1 | R68: -1 | AG68: 0 | AI68: =SUM(E68:AH68) -> 1 | AM68: IP 13Pro 256Gb | AN68: =AI68 -> 1 | AO68: 1647.12 | AP68: =AN68*AO68 -> 1647.12
D69: IP 13 256Gb | E69: 2 | AI69: =SUM(E69:AH69) -> 2 | AM69: IP 13 256Gb | AN69: =AI69 -> 2 | AO69: 800 | AP69: =AN69*AO69 -> 1600
D70: IP 13 128Gb | E70: 1 | Q70: 5 | R70: -2 | AG70: 7 | AI70: =SUM(E70:AH70) -> 11 | AM70: IP 13 128Gb | AN70: =AI70 -> 11 | AO70: 925 | AP70: =AN70*AO70 -> 10175
D72: IP 12ProMax 256GB | E72: 2 | AI72: =SUM(E72:AH72) -> 2 | AM72: IP 12ProMax 256GB | AN72: =AI72 -> 2 | AO72: 1169 | AP72: =AN72*AO72 -> 2338
D73: IP 12ProMax 128GB | E73: 1 | R73: -1 | AI73: =SUM(E73:AH73) -> 0 | AM73: IP 12ProMax 128GB | AN73: =AI73 -> 0 | AO73: 720 | AP73: =AN73*AO73 -> 0
D74: IP 12 Pro 256GB | E74: 2 | AI74: =SUM(E74:AH74) -> 2 | AM74: IP 12 Pro 256GB | AN74: =AI74 -> 2 | AO74: 1013 | AP74: =AN74*AO74 -> 2026
D75: IP 12 Pro 128GB | E75: 1 | AI75: =SUM(E75:AH75) -> 1 | AM75: IP 12 Pro 128GB | AN75: =AI75 -> 1 | AO75: 1013 | AP75: =AN75*AO75 -> 1013
D76: IP 12 64Gb | E76: 1 | R76: -1 | AI76: =SUM(E76:AH76) -> 0 | AM76: IP 12 64Gb | AN76: =AI76 -> 0 | AO76: 400 | AP76: =AN76*AO76 -> 0
D77: IP 12 128Gb | E77: 1 | R77: -1 | AI77: =SUM(E77:AH77) -> 0 | AM77: IP 12 128Gb | AN77: =AI77 -> 0 | AO77: 500 | AP77: =AN77*AO77 -> 0
D78: IP 12 256Gb | E78: 1 | R78: -1 | AI78: =SUM(E78:AH78) -> 0 | AM78: IP 12 256Gb | AN78: =AI78 -> 0 | AO78: 500 | AP78: =AN78*AO78 -> 0
D80: IP 11ProMax 512Gb | E80: 1 | H80: 1 | AG80: 4 | AI80: =SUM(E80:AH80) -> 6 | AM80: IP 11ProMax 512Gb | AN80: =AI80 -> 6 | AO80: 926.356 | AP80: =AN80*AO80 -> 5558.136
D81: IP 11ProMax 256Gb | E81: 0 | H81: 24 | Q81: 21 | AG81: 5 | AI81: =SUM(E81:AH81) -> 50 | AM81: IP 11ProMax 256Gb | AN81: =AI81 -> 50 | AO81: 941.305 | AP81: =AN81*AO81 -> 47065.25
D82: IP 11ProMax 64Gb | E82: 1 | AI82: =SUM(E82:AH82) -> 1 | AM82: IP 11ProMax 64Gb | AN82: =AI82 -> 1 | AO82: 780.56 | AP82: =AN82*AO82 -> 780.56
D83: IP 11Pro 512Gb | E83: 0 | H83: 1 | R83: -1 | AI83: =SUM(E83:AH83) -> 0 | AM83: IP 11Pro 512Gb | AN83: =AI83 -> 0
D84: IP 11Pro 256Gb | E84: 4 | H84: 7 | N84: -7 | AI84: =SUM(E84:AH84) -> 4 | AM84: IP 11Pro 256Gb | AN84: =AI84 -> 4 | AO84: 789 | AP84: =AN84*AO84 -> 3156
D85: IP 11 128Gb | E85: 3 | H85: 2 | AI85: =SUM(E85:AH85) -> 5 | AM85: IP 11 128Gb | AN85: =AI85 -> 5 | AO85: 524.05 | AP85: =AN85*AO85 -> 2620.25
D87: Watch Ultra 2 | E87: 3 | F87: -2 | G87: 2 | L87: 2 | N87: 3 | R87: 4 | X87: 1 | AD87: 2 | AG87: -5 | AI87: =SUM(E87:AH87) -> 10 | AM87: =D87 -> Watch Ultra 2 | AN87: =AI87 -> 10 | AO87: =180000/77 -> 2337.6623 | AP87: =AN87*AO87 -> 23376.623 | AQ87: 180000 PKR
D88: IP 7Plus | E88: 1 | AI88: =SUM(E88:AH88) -> 1 | AM88: IP 7Plus | AN88: =AI88 -> 1 | AO88: 300 | AP88: =AN88*AO88 -> 300
C89: SAMSUNG | AI89: =SUM(E89:AH89) -> 0 | AL89: SAMSUNG
D90: S23 FE 128GB | E90: 1 | AI90: =SUM(E90:AH90) -> 1 | AM90: S23 FE 128GB | AN90: =AI90 -> 1 | AO90: 555.6 | AP90: =AN90*AO90 -> 555.6
D92: S20 | E92: 1 | AI92: =SUM(E92:AH92) -> 1 | AM92: S20 | AN92: =AI92 -> 1 | AO92: 555.6 | AP92: =AN92*AO92 -> 555.6
D93: Flip5 256GB | E93: 1 | AI93: =SUM(E93:AH93) -> 1 | AM93: Flip5 256GB | AN93: =AI93 -> 1 | AO93: 555.6 | AP93: =AN93*AO93 -> 555.6
D94: Samsung A54 | E94: 1 | AI94: =SUM(E94:AH94) -> 1 | AM94: Samsung A54 | AN94: =AI94 -> 1 | AO94: 555.6 | AP94: =AN94*AO94 -> 555.6
C96: GOOGLE | D96: Google Pixel 7 | E96: 1 | AI96: =SUM(E96:AH96) -> 1 | AL96: GOOGLE | AM96: Google Pixel 7 | AN96: =AI96 -> 1 | AO96: 555.6 | AP96: =AN96*AO96 -> 555.6
D97: V3 Starlink | I97: 60 | J97: -50 | M97: 47 | N97: -37 | P97: -2 | Q97: =-13-5 -> -18 | AC97: 94 | AD97: -26 | AF97: -20 | AI97: =SUM(E97:AH97) -> 48 | AM97: V3 Starlink | AN97: =AI97 -> 48 | AO97: 1588.12 | AP97: =AN97*AO97 -> 76229.76
E98: =SUM(E56:E97) -> 45 | F98: =SUM(F56:F97) -> -7 | G98: =SUM(G56:G97) -> 5 | H98: =SUM(H56:H97) -> 44 | I98: =SUM(I56:I97) -> 64 | J98: =SUM(J56:J97) -> -55 | M98: =SUM(M56:M97) -> 47 | N98: =SUM(N56:N97) -> -50 | P98: =SUM(P56:P97) -> -2 | Q98: =SUM(Q56:Q97) -> 26 | R98: =SUM(R56:R97) -> -6 | S98: =SUM(S56:S97) -> 0 | U98: =SUM(U56:U97) -> 0 | V98: =SUM(V56:V97) -> 0 | AH98: =SUM(AH56:AH97) -> 0 | AI98: =SUM(AI56:AI97) -> 179 | AN98: =SUM(AN56:AN97) -> 179 | AP98: =SUM(AP56:AP97) -> 231780.71
C106: S# | D106: MAKE | E106: MODEL | F106: GB | G106: COLOR | H106: IMEI/SN BO | I106: X/HSO | J106: STATUS | K106: STATUS | L106: PRICE | O106: Date | P106: Sell TO | Q106: Model | R106: Rate
C107: 1 | D107: Samsung | E107: Galaxy S22 Ultra | F107: 256 | G107: BLACK | H107: 350139675584421 | I107: A BOX | J107: NON-ACTIVE | K107: LOCK | L107: 300 | M107: ok | O107: 45497 | P107: Returned | Q107: =CONCATENATE(E107," ",F107," ",G107) -> Galaxy S22 Ultra 256 BLACK | R107: 0
C108: 2 | D108: Google | E108: Pixel 8 | F108: 128 | G108: BLACK | H108: 358711960272466 | I108: BOX | J108: NON-ACTIVE | K108: LOCK | L108: 250 | M108: ok | O108: 45497 | P108: Returned | Q108: =CONCATENATE(E108," ",F108," ",G108) -> Pixel 8 128 BLACK | R108: 0
C109: 3 | D109: iPhone | E109: 14 | F109: 128 | G109: BLACK | H109: 354553492989371 | I109: BOX | J109: NON-ACTIVE | K109: LOCK | L109: 300 | M109: Purple | O109: 45453 | P109: Rabi | Q109: =CONCATENATE(E109," ",F109," ",G109) -> 14 128 BLACK | R109: 1220
C110: 4 | D110: iPhone | E110: 14 | F110: 128 | G110: BLUE | H110: 355549916437061 | I110: BOX | J110: NON-ACTIVE | K110: LOCK | L110: 300 | M110: ok | O110: 45463 | P110: Encell | Q110: =CONCATENATE(E110," ",F110," ",G110) -> 14 128 BLUE | R110: 1200
C111: 5 | D111: iPhone | E111: 14 | F111: 128 | G111: BLUE | H111: 355549919948734 | I111: BOX | J111: NON-ACTIVE | K111: LOCK | L111: 300 | M111: ok | O111: 45463 | P111: Encell | Q111: =CONCATENATE(E111," ",F111," ",G111) -> 14 128 BLUE | R111: 1200
C112: 6 | D112: iPhone | E112: 14 | F112: 128 | G112: BLUE | H112: 355549917028687 | I112: BOX | J112: NON-ACTIVE | K112: LOCK | L112: 300 | M112: ok | O112: 45463 | P112: Encell | Q112: =CONCATENATE(E112," ",F112," ",G112) -> 14 128 BLUE | R112: 1200
C113: 7 | D113: iPhone | E113: 14 | F113: 128 | G113: MIDNIGHT | H113: 355185497809426 | I113: BOX | J113: NON-ACTIVE | K113: LOCK | L113: 300 | M113: ok | O113: 45463 | P113: Encell | Q113: =CONCATENATE(E113," ",F113," ",G113) -> 14 128 MIDNIGHT | R113: 1200
C114: 8 | D114: iPhone | E114: 15 | F114: 128 | G114: BLUE | H114: 358019945087623 | I114: BOX | J114: NON-ACTIVE | K114: LOCK | L114: 400 | M114: ok | O114: 45465 | P114: Encell | Q114: =CONCATENATE(E114," ",F114," ",G114) -> 15 128 BLUE | R114: 1530
C115: 9 | D115: iPhone | E115: 15 | F115: 128 | G115: PURPLE | H115: 354633853879286 | I115: BOX | J115: NON-ACTIVE | K115: LOCK | L115: 400 | M115: ok | O115: 45465 | P115: Encell | Q115: =CONCATENATE(E115," ",F115," ",G115) -> 15 128 PURPLE | R115: 1530
C116: 10 | D116: iPhone | E116: 15 | F116: 256 | G116: BLACK | H116: 354872880723071 | I116: BOX | J116: NON-ACTIVE | K116: LOCK | L116: 440 | M116: ok | O116: 45497 | P116: Returned | Q116: =CONCATENATE(E116," ",F116," ",G116) -> 15 256 BLACK | R116: 0
C117: 11 | D117: iPhone | E117: 14 Plus | F117: 128 | G117: BLUE | H117: 350915774341114 | I117: BOX | J117: NON-ACTIVE | K117: UNLOCK | L117: 600 | M117: ok | P117: Returned | Q117: =CONCATENATE(E117," ",F117," ",G117) -> 14 Plus 128 BLUE | R117: 0
C118: 12 | D118: iPhone | E118: 14 Plus | F118: 128 | G118: MIDNIGHT | H118: 350028715517840 | I118: BOX | J118: NON-ACTIVE | K118: UNLOCK | L118: 600 | M118: ok | P118: Returned | Q118: =CONCATENATE(E118," ",F118," ",G118) -> 14 Plus 128 MIDNIGHT | R118: 0
C119: 13 | D119: iPhone | E119: 15 Plus | F119: 128 | G119: BLUE | H119: 359081511476191 | I119: BOX | J119: NON-ACTIVE | K119: LOCK | L119: 430 | M119: ok | O119: 45469 | P119: EuroNExt | Q119: =CONCATENATE(E119," ",F119," ",G119) -> 15 Plus 128 BLUE | R119: 1650
C120: 14 | D120: iPhone | E120: 15 Plus | F120: 128 | G120: BLUE | H120: 353896507988644 | I120: BOX | J120: NON-ACTIVE | K120: LOCK | L120: 430 | M120: ok | O120: 45469 | P120: EuroNExt | Q120: =CONCATENATE(E120," ",F120," ",G120) -> 15 Plus 128 BLUE | R120: 1650
C121: 15 | D121: iPhone | E121: 15 Plus | F121: 128 | G121: BLUE | H121: 353896509678854 | I121: BOX | J121: NON-ACTIVE | K121: LOCK | L121: 430 | M121: ok | O121: 45469 | P121: EuroNExt | Q121: =CONCATENATE(E121," ",F121," ",G121) -> 15 Plus 128 BLUE | R121: 1650
C122: 16 | D122: iPhone | E122: 15 Pro | F122: 128 | G122: BLACK | H122: 353468917794051 | I122: BOX | J122: NON-ACTIVE | K122: LOCK | L122: 520 | M122: ok | O122: 45465 | P122: Encell | Q122: =CONCATENATE(E122," ",F122," ",G122) -> 15 Pro 128 BLACK | R122: 1950
C123: 17 | D123: iPhone | E123: 15 Pro | F123: 128 | G123: NATURAL | H123: 352917268437570 | I123: BOX | J123: NON-ACTIVE | K123: LOCK | L123: 550 | M123: ok | O123: 45465 | P123: Encell | Q123: =CONCATENATE(E123," ",F123," ",G123) -> 15 Pro 128 NATURAL | R123: 2080
C124: 18 | D124: iPhone | E124: 15 Pro | F124: 256 | G124: BLACK | H124: 351697430562478 | I124: BOX | J124: NON-ACTIVE | K124: LOCK | L124: 580 | M124: ok | O124: 45465 | P124: Encell | Q124: =CONCATENATE(E124," ",F124," ",G124) -> 15 Pro 256 BLACK | R124: 2080
C125: 19 | D125: iPhone | E125: 15 Pro | F125: 128 | G125: NATURAL | H125: 352917268392445 | I125: BOX | J125: NON-ACTIVE | K125: LOCK | L125: 550 | M125: ok | O125: 45465 | P125: Encell | Q125: =CONCATENATE(E125," ",F125," ",G125) -> 15 Pro 128 NATURAL | R125: 2080
C126: 20 | D126: iPhone | E126: 15 Pro | F126: 256 | G126: BLACK | H126: 351697430563526 | I126: BOX | J126: NON-ACTIVE | K126: LOCK | L126: 580 | M126: ok | O126: 45465 | P126: Encell | Q126: =CONCATENATE(E126," ",F126," ",G126) -> 15 Pro 256 BLACK | R126: 2080
C127: 21 | D127: iPhone | E127: 15 Pro | F127: 512 | G127: NATURAL | H127: 356511214965622 | I127: BOX | J127: NON-ACTIVE | K127: LOCK | L127: 650 | M127: ok | O127: 45465 | P127: Encell | Q127: =CONCATENATE(E127," ",F127," ",G127) -> 15 Pro 512 NATURAL | R127: 2400
...

Sheet Australia 2
J3: Date | K3: Details | L3: GST Charges $
J5: 45439 | K5: 35pcs V3 Starlink GST | L5: 1665.3
J6: 45443 | K6: 35pcs Shipping Charges GST | L6: 16.49
J7: 45449 | K7: 60pcs V3 Starlink GST | L7: 2847.5
J8: 45450 | K8: 40pcs V3 Starlink GST | L8: 1890
J9: 45450 | K9: 05pcs V3 Starlink GST | L9: 193
J10: 45450 | K10: 02pcs V3 Starlink GST | L10: 94.5
J11: 45453 | K11: 47pcs Shipping Charges GST | L11: 24.36
J12: 45456 | K12: 60pcs Shipping Charges GST | L12: 27.72
J14: 45468 | K14: 81.5pcs Refundable Charges | L14: 6109.24
J15: 45468 | K15: 81.5pcs GST Charges | L15: =4472.52/94*81.5 -> 3877.77
J16: 45473 | K16: 46pcs Refundable Charges $75 | L16: =46*75 -> 3450
K18: Total | L18: =SUM(L5:L17) -> 20195.88
D22: Jawed bhai Investment
C23: Date | D23: Particular | E23: Dr | F23: Cr | G23: Balance
C25: 45431 | D25: Investment 27000 Dollar 2.44 Dirham Rate | E25: =27000*2.44 -> 65880 | G25: =G24+E25-F25 -> 65880
C26: 45452 | D26: V3 35pcs Profit $10 Each Total $350 19 May To 8June | E26: =350*2.44 -> 854 | G26: =G25+E26-F26 -> 66734
C27: 45452 | D27: V3 15pcs Profit $10 Each Total $150 19 May To 8June | E27: =150*2.44 -> 366 | G27: =G26+E27-F27 -> 67100
C28: 45474 | D28: Jawed Bhai 2nd Profit 9.June To 29.June $500 | E28: =500*2.44 -> 1220 | G28: =G27+E28-F28 -> 68320
C29: 45492 | D29: Jawed Bhai 3rd Profit 30.June To 20July $500 | E29: =500*2.44 -> 1220 | G29: =G28+E29-F29 -> 69540
C30: 45493 | D30: s | E30: =54000*2.44 -> 131760 | G30: =G29+E30-F30 -> 201300
G31: =G30+E31-F31 -> 201300
G32: =G31+E32-F32 -> 201300
G33: =G32+E33-F33 -> 201300
G34: =G33+E34-F34 -> 201300
G35: =G34+E35-F35 -> 201300
D39: Abdul Rehman Bhai Cash
C40: Date | D40: Particular | E40: Dr | F40: Cr | G40: Balance
A42: Add | C42: 45428 | D42: Send To australia By A/R (AUD 8782.5 @2.28) | E42: 20000 | G42: =G41+E42-F42 -> 20000 | H42: ok
A43: Add | C43: 45432 | D43: Send To australia By A/R (AUD 23152.5 @2.505) | E43: 58000 | G43: =G42+E43-F43 -> 78000 | H43: ok
C44: 45441 | D44: Adjustment Waheed Bhai Old Balance Paid by A/R | F44: 19172 | G44: =G43+E44-F44 -> 58828 | H44: ok
A45: Add | C45: 45440 | D45: Import Charges V3 35pcs | E45: 1230 | G45: =G44+E45-F45 -> 60058 | H45: ok
A46: Add | C46: 45440 | D46: V3 35pcs Hamali Charges | E46: 30 | G46: =G45+E46-F46 -> 60088 | H46: ok
A47: Add | C47: 45442 | D47: Online A/R A/C (Withdraw By Waheed Bhai) | E47: 1264.58 | G47: =G46+E47-F47 -> 61352.58 | H47: ok
A48: Add | C48: 45442 | D48: Sell Encell Shop 2pcs | F48: 3240 | G48: =G47+E48-F48 -> 58112.58 | H48: ok
A49: Add | C49: 45442 | D49: Sell Encell Shop 18pcs | F49: 29520 | G49: =G48+E49-F49 -> 28592.58 | H49: ok
A50: Add | C50: 45442 | D50: Sell AMGT Office 15pcs | F50: 24300 | G50: =G49+E50-F50 -> 4292.58 | H50: ok
C51: 45442 | D51: V3 35pcs Profit | E51: =L136 -> 2878.7416 | G51: =G50+E51-F51 -> 7171.3216
A52: Add | C52: 45447 | D52: Fahib Salary M/O May-2024 (15000 PKR) | E52: 194.81 | G52: =G51+E52-F52 -> 7366.1316 | H52: ok
A53: Add | C53: 45448 | D53: Clearing Charges V3 60pcs | E53: 1660 | G53: =G52+E53-F53 -> 9026.1316 | H53: ok
A54: Add | C54: 45448 | D54: Hamali Charges Paid by Encell Shop | E54: 40 | G54: =G53+E54-F54 -> 9066.1316 | H54: ok
A55: Add | C55: 45448 | D55: Sell Encell Shop 20pcs | F55: 33600 | G55: =G54+E55-F55 -> -24533.868 | H55: ok
A56: Add | C56: 45448 | D56: Paid To Ashfaq Sahab Card Purchasing | E56: 31900 | G56: =G55+E56-F56 -> 7366.1316 | H56: ok
A57: Add | C57: 45449 | D57: Sell Encell Shop 30pcs | F57: 50400 | G57: =G56+E57-F57 -> -43033.868 | H57: ok
C58: 45449 | D58: V3 60pcs Profit | E58: =L158 -> 10856.775 | G58: =G57+E58-F58 -> -32177.094
A59: Add | C59: 45451 | D59: Paid To Ashfaq Sahab Card Purchasing | E59: 40400 | G59: =G58+E59-F59 -> 8222.9062 | H59: ok
A60: Add | C60: 45453 | D60: Sell AMGT Office 2pcs | F60: 3400 | G60: =G59+E60-F60 -> 4822.9062 | H60: ok
C61: 45453 | D61: V3 47pcs Profit | E61: =L187 -> 8600.9964 | G61: =G60+E61-F61 -> 13423.903
A62: Add | C62: 45453 | D62: Starlink v3 47pcs Clearing charges | E62: 1465 | G62: =G61+E62-F62 -> 14888.903 | H62: ok
A63: Add | C63: 45453 | D63: hamali charges | E63: 35 | G63: =G62+E63-F63 -> 14923.903 | H63: ok
A64: Add | C64: 45455 | D64: Sell Encell Shop 35pcs & 2pcs | F64: 62140 | G64: =G63+E64-F64 -> -47216.097 | H64: ok
A65: Add | C65: 45455 | D65: Paid To Ashfaq Sahab Card Purchasing | E65: 60640 | G65: =G64+E65-F65 -> 13423.903 | H65: ok
A66: Add | C66: 45456 | D66: Sell AMGT Office 6pcs | F66: 9990 | G66: =G65+E66-F66 -> 3433.9026 | H66: ok
A67: Add | C67: 45456 | D67: Sell AMGT Office 7pcs | F67: 11655 | G67: =G66+E67-F67 -> -8221.0974 | H67: ok
A68: Add | C68: 45457 | D68: Paid To Ashfaq Sahab Card Purchasing | E68: 21320 | G68: =G67+E68-F68 -> 13098.903 | H68: ok
A69: Add | C69: 45462 | D69: Paid To Ashfaq Sahab Card Purchasing | E69: 6000 | G69: =G68+E69-F69 -> 19098.903 | H69: ok
A70: Add | C70: 45463 | D70: Sell Encell Shop 5pcs | F70: 8350 | G70: =G69+E70-F70 -> 10748.903 | H70: ok
A71: Add | C71: 45463 | D71: Paid To Ashfaq Sahab Card Purchasing | E71: 8350 | G71: =G70+E71-F71 -> 19098.903 | H71: ok
C72: 45463 | D72: Total Business GST Half Payment | E72: =L18/2 -> 10097.94 | G72: =G71+E72-F72 -> 29196.843
A73: Add | C73: 45478 | D73: Send by Sasco | F73: 87500 | G73: =G72+E73-F73 -> -58303.157
G74: =G73+E74-F74 -> -58303.157
G75: =G74+E75-F75 -> -58303.157
G76: =G75+E76-F76 -> -58303.157
G77: =G76+E77-F77 -> -58303.157
G78: =G77+E78-F78 -> -58303.157
G79: =G78+E79-F79 -> -58303.157
G80: =G79+E80-F80 -> -58303.157
D84: Waheed Bhai Cash
C85: Date | D85: Particular | E85: Dr | F85: Cr | G85: Balance
A87: Add | C87: 45428 | D87: V2 1st invoice GST | E87: =577.45*2.42 -> 1397.429 | G87: =G86+E87-F87 -> 1397.429
A88: Add | C88: 45428 | D88: V2 2nd invoice GST | E88: =397*2.42 -> 960.74 | G88: =G87+E88-F88 -> 2358.169
A89: Add | C89: 45428 | D89: Shipping Invoice GST | E89: =29.09*2.42 -> 70.3978 | G89: =G88+E89-F89 -> 2428.5668
A90: Add | C90: 45428 | D90: v3 106 pcs GST | E90: =47.49*106*2.42 -> 12182.135 | G90: =G89+E90-F90 -> 14610.702
C91: 45428 | D91: 106pcs Shipping Invoice GST | G91: =G90+E91-F91 -> 14610.702
A92: Add | C92: 45428 | D92: v2 Shipping Invoice GST | E92: 37.12 | G92: =G91+E92-F92 -> 14647.822
C93: 45441 | D93: Adjustment Waheed Bhai Old Balance Paid by A/R | E93: 19172 | G93: =G92+E93-F93 -> 33819.822 | H93: ok
A94: Add | C94: 45441 | D94: V3 35pcs Other Expense | E94: 307.44 | G94: =G93+E94-F94 -> 34127.262 | H94: ok
A95: Add | C95: 45442 | D95: Online A/R Dubai A/C (Withdraw By Waheed Bhai) | F95: 1264.58 | G95: =G94+E95-F95 -> 32862.682 | H95: ok
C96: 45443 | D96: V3 35pcs Profit | E96: =L137 -> 2878.7416 | G96: =G95+E96-F96 -> 35741.423
A97: Add | C97: 45448 | D97: Other Expense Paid By Waheed Bhai $360 | E97: =360*2.44 -> 878.4 | G97: =G96+E97-F97 -> 36619.823 | H97: ok
C98: 45449 | D98: V3 60pcs Profit | E98: =L159 -> 10856.775 | G98: =G97+E98-F98 -> 47476.598
A99: Add | C99: 45449 | D99: V3 47pcs $40 petrol Charges | E99: 97.6 | G99: =G98+E99-F99 -> 47574.198 | H99: ok
A100: Add | C100: 45453 | D100: V3 47pcs $50 Toll Charges | E100: 122 | G100: =G99+E100-F100 -> 47696.198 | H100: ok
C101: 45453 | D101: V3 47pcs Profit | E101: =L188 -> 8600.9964 | G101: =G100+E101-F101 -> 56297.194
A102: Add | C102: 45463 | D102: ARY Laguna A/C (From Noman Bhai A/R) 200000PKR | F102: =200000/77 -> 2597.4026 | G102: =G101+E102-F102 -> 53699.792
A103: Add | C103: 45463 | D103: ARY Laguna A/C (From Noman Bhai A/R) 62,222PKR | F103: =62222/77 -> 808.07792 | G103: =G102+E103-F103 -> 52891.714
C104: 45463 | D104: Total Business GST Half Payment | E104: =L18/2 -> 10097.94 | G104: =G103+E104-F104 -> 62989.654
G105: =G104+E105-F105 -> 62989.654
G106: =G105+E106-F106 -> 62989.654
D112: Australia Purchasing V3 35Pcs
C113: Date | D113: Details | E113: Dollar | F113: Rate | G113: Aed
A115: Add | C115: 45440 | D115: V3 Import Charges 35pcs | G115: 1230 | H115: ok
A116: Add | C116: 45440 | D116: 35 pcs Purchased @474.58 | E116: =474.58*35 -> 16610.3 | F116: 2.44 | G116: =E116*F116 -> 40529.132
A117: Add | C117: 45440 | D117: 35 pcs GST Charges | E117: 1665.3 | F117: 2.44 | G117: =E117*F117 -> 4063.332
A118: Add | C118: 45440 | D118: Other Expense Paid by Waheed Bhai | E118: 126 | F118: 2.44 | G118: =E118*F118 -> 307.44 | H118: ok
A119: Add | C119: 45440 | D119: Hamali Charges Paid by AR | G119: 30 | H119: ok
A120: Add | C120: 45443 | D120: Shipping Charges | E120: 1638.29 | F120: 2.44 | G120: =E120*F120 -> 3997.4276
A121: Add | B121: ok | C121: 45443 | D121: Shipping Charges GST | E121: 16.49 | F121: 2.44 | G121: =E121*F121 -> 40.2356
A122: Add | C122: 45447 | D122: Fahib Salary M/O May-2024 (15000 PKR) | G122: =15000/77 -> 194.80519 | H122: ok
A123: Add | C123: 45471 | D123: Surcharge Include | E123: 23.01 | F123: 2.44 | G123: =E123*F123 -> 56.1444
...

Sheet AR Expense 
D3: A/R Karachi Expense Ledger
C4: DATE | D4: DETAILS | E4: IN | F4: OUT | G4: BALANCE
D6: Month of Aug-2024 | G6: 0
C7: 45506 | D7: Online Transfer Sania Abdul Rehman (AR Expense) | F7: 100000 | G7: =G6+E7-F7 -> -100000
C8: 45507 | D8: DVAGO POS Purchased (AR Expense) | F8: 2447 | G8: =G7+E8-F8 -> -102447
C9: 45509 | D9: Zellbury POS (AR Expense) | F9: 4582 | G9: =G8+E9-F9 -> -107029
C10: 45509 | D10: Kababjees (AR Expense) | F10: 1700 | G10: =G9+E10-F10 -> -108729
C11: 45509 | D11: United King (AR Expense) | F11: 877 | G11: =G10+E11-F11 -> -109606
C12: 45509 | D12: ATM Withdraw Askari (AR Expense) | F12: 20000 | G12: =G11+E12-F12 -> -129606
C13: 45509 | D13: Paid to Maaz (petrol Exp) | F13: 1000 | G13: =G12+E13-F13 -> -130606
C14: 45510 | D14: Uphone Super Card (AR Expense) | F14: 1600 | G14: =G13+E14-F14 -> -132206
C15: 45510 | D15: Transfer Muhammad ilyas (AR Expense) | F15: 16000 | G15: =G14+E15-F15 -> -148206
C16: 45510 | D16: Transfer Nasir Mahmood (AR Expense) | F16: 10000 | G16: =G15+E16-F16 -> -158206
C17: 45517 | D17: FBR Tax (A/R Exp meezan) | F17: 75.78 | G17: =G16+E17-F17 -> -158281.78
C18: 45517 | D18: Apple.Com Bill (A/R Exp meezan) | F18: 601.46 | G18: =G17+E18-F18 -> -158883.24
... C28: 45530 | D28: AR Personal | F28: 1661 | G28: =G27+E28-F28 -> -414960.24
G29: =G28+E29-F29 -> -414960.24
G30: =G29+E30-F30 -> -414960.24
G31: =G30+E31-F31 -> -414960.24
G32: =G31+E32-F32 -> -414960.24
G33: =G32+E33-F33 -> -414960.24
D34: Total Expense | G34: =G33+E34-F34 -> -414960.24
D38: A/R Dubai Expense Ledger
C39: DATE | D39: DETAILS | E39: IN | F39: OUT | G39: BALANCE
D41: Month of Aug-2024 | G41: 0
C42: 45502 | D42: Room Rent Advance | F42: 0 | G42: =G41+E42-F42 -> 0
C43: 45502 | D43: AR Personal Shop Cash | F43: 210 | G43: =G42+E43-F43 -> -210
C44: 45502 | D44: AR Credit Card Exp | F44: 20 | G44: =G43+E44-F44 -> -230
C45: 45502 | D45: AR Credit Card Exp | F45: 16 | G45: =G44+E45-F45 -> -246
C46: 45502 | D46: AR Credit Card Exp | F46: 87 | G46: =G45+E46-F46 -> -333
C47: 45510 | D47: Flat 307 Rent paid by Faisal Bhai | F47: 0 | G47: =G46+E47-F47 -> -333
C48: 45498 | D48: POS Purchase (AR DIB Online) | F48: 41 | G48: =G47+E48-F48 -> -374
C49: 45500 | D49: POS Purchase (AR DIB Online) | F49: 33.5 | G49: =G48+E49-F49 -> -407.5
C50: 45501 | D50: POS Purchase (AR DIB Online) | F50: 15.5 | G50: =G49+E50-F50 -> -423
C51: 45501 | D51: POS Purchase (AR DIB Online) | F51: 1.5 | G51: =G50+E51-F51 -> -424.5
C52: 45504 | D52: POS Purchase (AR DIB Online) | F52: 13.6 | G52: =G51+E52-F52 -> -438.1
C53: 45504 | D53: POS Purchase (AR DIB Online) | F53: 19.5 | G53: =G52+E53-F53 -> -457.6
... C82: 45520 | D82: Wal-Mart SuperCenter (12.35 CAD) | F82: 34.3 | G82: =G81+E82-F82 -> -3103.65
C83: 45531 | D83: Canadian Dollar 400 | F83: =400*2.7 -> 1080 | G83: =G82+E83-F83 -> -4183.65
G84: =G83+E84-F84 -> -4183.65
G85: =G84+E85-F85 -> -4183.65
G86: =G85+E86-F86 -> -4183.65
G87: =G86+E87-F87 -> -4183.65
D88: Total Expense | G88: =G87+E88-F88 -> -4183.65
D92: A/R Karachi Expense Ledger
C93: DATE | D93: DETAILS | E93: IN | F93: OUT | G93: BALANCE
D95: Month of Sep-2024 | G95: 0
G96: =G95+E96-F96 -> 0
G97: =G96+E97-F97 -> 0
G98: =G97+E98-F98 -> 0
G99: =G98+E99-F99 -> 0
G100: =G99+E100-F100 -> 0
G101: =G100+E101-F101 -> 0
G102: =G101+E102-F102 -> 0
G103: =G102+E103-F103 -> 0
G104: =G103+E104-F104 -> 0
D105: Total Expense | G105: =G104+E105-F105 -> 0
D108: A/R Dubai Expense Ledger
C109: DATE | D109: DETAILS | E109: IN | F109: OUT | G109: BALANCE
D111: Month of Sep-2024 | G111: 0
G112: =G111+E112-F112 -> 0
C113: 45558 | D113: Ali Karachi Receivable Adjust Paid to AMGT | F113: 550 | G113: =G112+E113-F113 -> -550
G114: =G113+E114-F114 -> -550
C115: 45537 | D115: DU Payment (AR DIB Online) | F115: 20 | G115: =G114+E115-F115 -> -570
C116: 45538 | D116: Chq Book Charges (AR DIB Online) | F116: 26.25 | G116: =G115+E116-F116 -> -596.25
C117: 45540 | D117: DU Payment (AR DIB Online) | F117: 20 | G117: =G116+E117-F117 -> -616.25
C118: 45540 | D118: POS Purchased Flydubai (AR DIB Online) | F118: 345.05 | G118: =G117+E118-F118 -> -961.3
C119: 45543 | D119: POS Royal Paris Hotel (AR DIB Online) | F119: 18 | G119: =G118+E119-F119 -> -979.3
C120: 45545 | D120: POS (Albaik Dubai) (AR DIB Online) | F120: 16 | G120: =G119+E120-F120 -> -995.3
C121: 45545 | D121: POS (Dubai Taxi) (AR DIB Online) | F121: 34 | G121: =G120+E121-F121 -> -1029.3
C122: 45545 | D122: POS (Sulaiya Supermarket) (AR DIB Online) | F122: 61.98 | G122: =G121+E122-F122 -> -1091.28
C123: 45545 | D123: POS (Albaik Dubai) (AR DIB Online) | F123: 144 | G123: =G122+E123-F123 -> -1235.28
C124: 45545 | D124: POS (Carrefour Al.ghurair Dubai) (AR DIB Online) | F124: 93.2 | G124: =G123+E124-F124 -> -1328.48
C125: 45545 | D125: DU Payment (AR DIB Online) | F125: 95 | G125: =G124+E125-F125 -> -1423.48
C126: 45547 | D126: POS (Dubai Taxi) (AR DIB Online) | F126: 40.5 | G126: =G125+E126-F126 -> -1463.98
... C131: 45566 | D131: POS Islamic Centre Mayfield (AR DIB Online) | F131: 26.19 | G131: =G130+E131-F131 -> -1537.67
G132: =G131+E132-F132 -> -1537.67
G133: =G132+E133-F133 -> -1537.67
G134: =G133+E134-F134 -> -1537.67
G135: =G134+E135-F135 -> -1537.67
G136: =G135+E136-F136 -> -1537.67
G137: =G136+E137-F137 -> -1537.67
G138: =G137+E138-F138 -> -1537.67
G139: =G138+E139-F139 -> -1537.67
G140: =G139+E140-F140 -> -1537.67
G141: =G140+E141-F141 -> -1537.67
G142: =G141+E142-F142 -> -1537.67
G143: =G142+E143-F143 -> -1537.67
... G153: =G152+E153-F153 -> -1537.67
D154: Total Expense | G154: =G153+E154-F154 -> -1537.67

Sheet Book 1

Sheet Book 2
D4: MODEL | E4: IMEI
D5: IP 16ProMax 256GB Desert Titanium | E5: 359974601808093 | G5: 359974601822136
D6: Samsung SM-S921W 128GB | E6: 356380561350311
D7: IP 16 Pro 128GB Black Titanium | E7: 355171954666715 | G7: 355171954837670
D8: IP 16ProMax 256GB Desert Titanium | E8: 350523895462817 | G8: 350523895270590
D9: IP 16ProMax 256GB Desert Titanium | E9: 351655955619750 | G9: 351655955665670
D10: IP 16 128GB Ultramarine | E10: 352502303969835 | G10: 352502304215782
D11: Samsung SM-A546W 128GB | E11: 351617737060950
D12: Samsung SM-F741W 256GB | E12: 351250615743586 | G12: 359688605743581
D13: IP 16 128GB Black | E13: 358413699819150
D14: IP 16 128GB Black | E14: 359298855052764 | G14: 359298855126972
D15: IP 16 128GB Black | E15: 358413695701980
D16: IP 16Pro 256GB Desert Titanium | E16: 353446782484354 | G16: 353446784675439
D17: IP 16Pro 256GB Desert Titanium | E17: 353446786560563 | G17: 353446781513476
D18: Samsung SM-F741W 256GB | E18: 351250615737612 | G18: 359688605737617
D19: IP 16Pro 256GB Desert Titanium | E19: 353446781287865 | G19: 353446786176923
D20: IP 16Pro 256GB Black Titanium | E20: 354985550609675 | G20: 354985550506525
D21: Samsung SM-A546W 128GB | E21: 351617736910312
D22: Samsung SM-F741W 256GB | E22: 351250615600778 | G22: 359688605600773
